Workbook

Sheet Constants
A1: TBL_NAME | B1: TBL_DESCR | C1: TBL_VOLUME
A2: C1_BI_FTGL_MONTHLY_A | B2: Financial Transaction GL Monthly Aggregate | C2: Medium Volume
A3: C1_BI_FT_MONTHLY_A | B3: Financial Transaction Monthly Aggregate | C3: Medium Volume
A4: C1_BI_SA_SNAPSHOT | B4: SA Arrears Snapshot | C4: Medium Volume
A5: C1_CONT | B5: Consumer Contract | C5: Medium Volume
A6: C1_CS_REQ | B6: Customer Service Request | C6: Medium Volume
A7: C1_CS_REQ_ACCT | B7: Customer Service Request Account | C7: Medium Volume
A8: C1_CS_REQ_CONT | B8: Customer Service Request Consumer Contract | C8: Medium Volume
A9: C1_CS_REQ_CONT_PROD | B9: Customer Service Request Contract Product | C9: Medium Volume
A10: C1_CS_REQ_PER | B10: Customer Service Request Person | C10: Medium Volume
A11: C1_CS_REQ_PREM | B11: Customer Service Request Premise | C11: Medium Volume
A12: C1_CS_REQ_SA | B12: Customer Service Request SA | C12: Medium Volume
... A278: W1_WORK_REQ | B278: Work Request | C278: Medium Volume

Sheet Tabulation
A1: Client | B1: Table Name | C1: Row Count | D1: Table Description | E1: Table Volume
A2: CityCorp | B2: C1_BI_FTGL_MONTHLY_A | C2: 0 | D2: =VLOOKUP(Tabulation!$B2,Constants!$A:$C,2,FALSE) -> Financial Transaction GL Monthly Aggregate | E2: =VLOOKUP(Tabulation!$B2,Constants!$A:$C,3,FALSE) -> Medium Volume
A3: CityCorp | B3: C1_BI_FT_MONTHLY_A | C3: 0 | D3: =VLOOKUP(Tabulation!$B3,Constants!$A:$C,2,FALSE) -> Financial Transaction Monthly Aggregate | E3: =VLOOKUP(Tabulation!$B3,Constants!$A:$C,3,FALSE) -> Medium Volume
A4: CityCorp | B4: C1_BI_SA_SNAPSHOT | C4: 0 | D4: =VLOOKUP(Tabulation!$B4,Constants!$A:$C,2,FALSE) -> SA Arrears Snapshot | E4: =VLOOKUP(Tabulation!$B4,Constants!$A:$C,3,FALSE) -> Medium Volume
A5: CityCorp | B5: C1_CONT | C5: 0 | D5: =VLOOKUP(Tabulation!$B5,Constants!$A:$C,2,FALSE) -> Consumer Contract | E5: =VLOOKUP(Tabulation!$B5,Constants!$A:$C,3,FALSE) -> Medium Volume
A6: CityCorp | B6: C1_CS_REQ | C6: 2031 | D6: =VLOOKUP(Tabulation!$B6,Constants!$A:$C,2,FALSE) -> Customer Service Request | E6: =VLOOKUP(Tabulation!$B6,Constants!$A:$C,3,FALSE) -> Medium Volume
A7: CityCorp | B7: C1_CS_REQ_ACCT | C7: 1569 | D7: =VLOOKUP(Tabulation!$B7,Constants!$A:$C,2,FALSE) -> Customer Service Request Account | E7: =VLOOKUP(Tabulation!$B7,Constants!$A:$C,3,FALSE) -> Medium Volume
A8: CityCorp | B8: C1_CS_REQ_CONT | C8: 0 | D8: =VLOOKUP(Tabulation!$B8,Constants!$A:$C,2,FALSE) -> Customer Service Request Consumer Contract | E8: =VLOOKUP(Tabulation!$B8,Constants!$A:$C,3,FALSE) -> Medium Volume
A9: CityCorp | B9: C1_CS_REQ_CONT_PROD | C9: 0 | D9: =VLOOKUP(Tabulation!$B9,Constants!$A:$C,2,FALSE) -> Customer Service Request Contract Product | E9: =VLOOKUP(Tabulation!$B9,Constants!$A:$C,3,FALSE) -> Medium Volume
A10: CityCorp | B10: C1_CS_REQ_PER | C10: 1558 | D10: =VLOOKUP(Tabulation!$B10,Constants!$A:$C,2,FALSE) -> Customer Service Request Person | E10: =VLOOKUP(Tabulation!$B10,Constants!$A:$C,3,FALSE) -> Medium Volume
A11: CityCorp | B11: C1_CS_REQ_PREM | C11: 1784 | D11: =VLOOKUP(Tabulation!$B11,Constants!$A:$C,2,FALSE) -> Customer Service Request Premise | E11: =VLOOKUP(Tabulation!$B11,Constants!$A:$C,3,FALSE) -> Medium Volume
A12: CityCorp | B12: C1_CS_REQ_SA | C12: 4857 | D12: =VLOOKUP(Tabulation!$B12,Constants!$A:$C,2,FALSE) -> Customer Service Request SA | E12: =VLOOKUP(Tabulation!$B12,Constants!$A:$C,3,FALSE) -> Medium Volume
A13: CityCorp | B13: C1_CS_REQ_SVC_LOC | C13: 0 | D13: =VLOOKUP(Tabulation!$B13,Constants!$A:$C,2,FALSE) -> Customer Service Request Service Location | E13: =VLOOKUP(Tabulation!$B13,Constants!$A:$C,3,FALSE) -> Medium Volume
... A1361: Newark | B1361: W1_WORK_REQ | C1361: 0 | D1361: =VLOOKUP(Tabulation!$B1361,Constants!$A:$C,2,FALSE) -> Work Request | E1361: =VLOOKUP(Tabulation!$B1361,Constants!$A:$C,3,FALSE) -> Medium Volume

Sheet Pivot
A1: Sum of Row Count | B1: Column Labels
A2: Row Labels | B2: Newark | C2: Fond du Lac | D2: Ellensburg | E2: College Station | F2: CityCorp | G2: Total | H2: Table Description | I2: Assignee | J2: Status
A3: C1_BI_FT_MONTHLY_A | B3: 0 | C3: 0 | D3: 0 | E3: 0 | F3: 0 | G3: =SUM(B3,C3,D3,E3,F3) -> 0 | H3: =VLOOKUP(A3,Constants!$A:$C,2,FALSE) -> Financial Transaction Monthly Aggregate
A4: C1_BI_FTGL_MONTHLY_A | B4: 0 | C4: 0 | D4: 0 | E4: 0 | F4: 0 | G4: =SUM(B4,C4,D4,E4,F4) -> 0 | H4: =VLOOKUP(A4,Constants!$A:$C,2,FALSE) -> Financial Transaction GL Monthly Aggregate
A5: C1_BI_SA_SNAPSHOT | B5: 0 | C5: 0 | D5: 500256 | E5: 0 | F5: 0 | G5: =SUM(B5,C5,D5,E5,F5) -> 500256 | H5: =VLOOKUP(A5,Constants!$A:$C,2,FALSE) -> SA Arrears Snapshot
A6: C1_CONT | B6: 0 | C6: 0 | D6: 0 | E6: 0 | F6: 0 | G6: =SUM(B6,C6,D6,E6,F6) -> 0 | H6: =VLOOKUP(A6,Constants!$A:$C,2,FALSE) -> Consumer Contract
A7: C1_CS_REQ | B7: 1618 | C7: 5286 | D7: 7504 | E7: 31 | F7: 2031 | G7: =SUM(B7,C7,D7,E7,F7) -> 16470 | H7: =VLOOKUP(A7,Constants!$A:$C,2,FALSE) -> Customer Service Request
A8: C1_CS_REQ_ACCT | B8: 713 | C8: 4856 | D8: 6151 | E8: 0 | F8: 1569 | G8: =SUM(B8,C8,D8,E8,F8) -> 13289 | H8: =VLOOKUP(A8,Constants!$A:$C,2,FALSE) -> Customer Service Request Account
A9: C1_CS_REQ_CONT | B9: 0 | C9: 0 | D9: 0 | E9: 0 | F9: 0 | G9: =SUM(B9,C9,D9,E9,F9) -> 0 | H9: =VLOOKUP(A9,Constants!$A:$C,2,FALSE) -> Customer Service Request Consumer Contract
A10: C1_CS_REQ_CONT_PROD | B10: 0 | C10: 0 | D10: 0 | E10: 0 | F10: 0 | G10: =SUM(B10,C10,D10,E10,F10) -> 0 | H10: =VLOOKUP(A10,Constants!$A:$C,2,FALSE) -> Customer Service Request Contract Product
A11: C1_CS_REQ_PER | B11: 722 | C11: 5079 | D11: 5557 | E11: 0 | F11: 1558 | G11: =SUM(B11,C11,D11,E11,F11) -> 12916 | H11: =VLOOKUP(A11,Constants!$A:$C,2,FALSE) -> Customer Service Request Person
A12: C1_CS_REQ_PREM | B12: 684 | C12: 4766 | D12: 5421 | E12: 0 | F12: 1784 | G12: =SUM(B12,C12,D12,E12,F12) -> 12655 | H12: =VLOOKUP(A12,Constants!$A:$C,2,FALSE) -> Customer Service Request Premise
A13: C1_CS_REQ_SA | B13: 2091 | C13: 14404 | D13: 18037 | E13: 0 | F13: 4857 | G13: =SUM(B13,C13,D13,E13,F13) -> 39389 | H13: =VLOOKUP(A13,Constants!$A:$C,2,FALSE) -> Customer Service Request SA
A14: C1_CS_REQ_SVC_LOC | B14: 0 | C14: 0 | D14: 0 | E14: 0 | F14: 0 | G14: =SUM(B14,C14,D14,E14,F14) -> 0 | H14: =VLOOKUP(A14,Constants!$A:$C,2,FALSE) -> Customer Service Request Service Location
... A24: C1_PA_RQST | B24: 358 | C24: 0 | D24: 0 | E24: 1 | F24: 0 | G24: =SUM(B24,C24,D24,E24,F24) -> 359 | H24: =VLOOKUP(A24,Constants!$A:$C,2,FALSE) -> Payment Arrangement Request
A25: C1_RESPONSE | E25: 0 | G25: =SUM(B25,C25,D25,E25,F25) -> 0 | H25: =VLOOKUP(A25,Constants!$A:$C,2,FALSE) -> Response
A26: C1_USAGE | B26: 15360951 | C26: 2173379 | D26: 445035 | E26: 1500648 | F26: 251992 | G26: =SUM(B26,C26,D26,E26,F26) -> 19732005 | H26: =VLOOKUP(A26,Constants!$A:$C,2,FALSE) -> Usage
A27: C1_WEB_USER | B27: 0 | C27: 0 | D27: 0 | E27: 0 | F27: 0 | G27: =SUM(B27,C27,D27,E27,F27) -> 0 | H27: =VLOOKUP(A27,Constants!$A:$C,2,FALSE) -> Web User
A28: C1_WEB_USER_ACCT | B28: 0 | C28: 0 | D28: 0 | E28: 0 | F28: 0 | G28: =SUM(B28,C28,D28,E28,F28) -> 0 | H28: =VLOOKUP(A28,Constants!$A:$C,2,FALSE) -> Web User Account
A29: CI_ACCT | B29: 59950 | C29: 29496 | D29: 90087 | E29: 155128 | F29: 22560 | G29: =SUM(B29,C29,D29,E29,F29) -> 357221 | H29: =VLOOKUP(A29,Constants!$A:$C,2,FALSE) -> Account
A30: CI_ADJ | B30: 8715478 | C30: 557276 | D30: 328670 | E30: 2312799 | F30: 197579 | G30: =SUM(B30,C30,D30,E30,F30) -> 12111802 | H30: =VLOOKUP(A30,Constants!$A:$C,2,FALSE) -> Adjustment
A31: CI_ADJ_STG_CTL | B31: 0 | C31: 5 | D31: 1 | E31: 0 | F31: 1 | G31: =SUM(B31,C31,D31,E31,F31) -> 7 | H31: =VLOOKUP(A31,Constants!$A:$C,2,FALSE) -> Adjustment Staging Control
A32: CI_ADJ_STG_UP | B32: 0 | C32: 22839 | D32: 1452 | E32: 0 | F32: 1468 | G32: =SUM(B32,C32,D32,E32,F32) -> 25759 | H32: =VLOOKUP(A32,Constants!$A:$C,2,FALSE) -> Adjustment Upload
A33: CI_AM_REQ | B33: 0 | C33: 0 | D33: 0 | E33: 0 | F33: 0 | G33: =SUM(B33,C33,D33,E33,F33) -> 0 | H33: =VLOOKUP(A33,Constants!$A:$C,2,FALSE) -> Activity Request
A34: CI_APPR_REQ | B34: 2468 | C34: 4252 | D34: 8818 | E34: 3127 | F34: 741 | G34: =SUM(B34,C34,D34,E34,F34) -> 19406 | H34: =VLOOKUP(A34,Constants!$A:$C,2,FALSE) -> Approval Request
A35: CI_AUDIT | B35: 0 | C35: 0 | D35: 0 | E35: 0 | F35: 1348 | G35: =SUM(B35,C35,D35,E35,F35) -> 1348 | H35: =VLOOKUP(A35,Constants!$A:$C,2,FALSE) -> Audit
A36: CI_BAL_CTL_GRP | B36: 21 | C36: 21 | D36: 15 | E36: 14 | F36: 10 | G36: =SUM(B36,C36,D36,E36,F36) -> 81 | H36: =VLOOKUP(A36,Constants!$A:$C,2,FALSE) -> Balance Control Group
A37: CI_BATCH_JOB | B37: 2928 | C37: 1319 | D37: 1329 | E37: 4256 | F37: 829 | G37: =SUM(B37,C37,D37,E37,F37) -> 10661 | H37: =VLOOKUP(A37,Constants!$A:$C,2,FALSE) -> Batch Job Ad-Hoc Queues
... A274: W1_WORK_REQ | B274: 0 | C274: 0 | D274: 0 | E274: 0 | F274: 0 | G274: =SUM(B274,C274,D274,E274,F274) -> 0 | H274: =VLOOKUP(A274,Constants!$A:$C,2,FALSE) -> Work Request
A275: CI_SPR | E275: 0 | G275: =SUM(B275,C275,D275,E275,F275) -> 0 | H275: =VLOOKUP(A275,Constants!$A:$C,2,FALSE) -> Service Provider - CCB
A276: D1_EVT_PARTICIPATION | E276: 0 | G276: =SUM(B276,C276,D276,E276,F276) -> 0 | H276: =VLOOKUP(A276,Constants!$A:$C,2,FALSE) -> Event Participation
A277: F1_BATCH_RUN_ANALYTICS_SNAP | E277: 0 | G277: =SUM(B277,C277,D277,E277,F277) -> 0 | H277: =VLOOKUP(A277,Constants!$A:$C,2,FALSE) -> Batch Run Analytics Snapshot
A278: F1_BATCH_THD_ANALYTICS_SNAP | E278: 0 | G278: =SUM(B278,C278,D278,E278,F278) -> 0 | H278: =VLOOKUP(A278,Constants!$A:$C,2,FALSE) -> Batch Thread Analytics Snapshot
A279: Grand Total | B279: 124534458 | C279: 14903796 | D279: 17545023 | E279: 76034132 | F279: 13783055 | G279: =SUM(B279,C279,D279,E279,F279) -> 246800464 | H279: =VLOOKUP(A279,Constants!$A:$C,2,FALSE) -> #N/A

Sheet Summary
A1: Table Name | B1: Table Description | C1: Newark | D1: Fond du Lac | E1: Ellensburg | F1: College Station | G1: CityCorp | H1: Total | I1: Designer | J1: Status | K1: CLOB Data Source | L1: Designer Notes | M1: Josh's Notes | N1: Link | O1: Justification
A2: C1_BI_FT_MONTHLY_A | B2: Financial Transaction Monthly Aggregate | C2: 0 | D2: 0 | E2: 0 | F2: 0 | G2: 0 | H2: 0
A3: C1_BI_FTGL_MONTHLY_A | B3: Financial Transaction GL Monthly Aggregate | C3: 0 | D3: 0 | E3: 0 | F3: 0 | G3: 0 | H3: 0
A4: C1_BI_SA_SNAPSHOT | B4: SA Arrears Snapshot | C4: 0 | D4: 0 | E4: 500256 | F4: 0 | G4: 0 | H4: 500256 | I4: Josh | J4: DEV - Complete | M4: Likely, this needs to be created as it's one of the views for OUAV
A5: C1_CONT | B5: Consumer Contract | C5: 0 | D5: 0 | E5: 0 | F5: 0 | G5: 0 | H5: 0
A6: C1_CS_REQ | B6: Customer Service Request | C6: 1618 | D6: 5286 | E6: 7504 | F6: 31 | G6: 2031 | H6: 16470 | I6: Doms | J6: Skip - Confirmed | L6: This is related to Process Flows and more on an Internal Processing of the lifecycle-based transaction. We can skip as the content is more technical than functional.
A7: C1_CS_REQ_ACCT | B7: Customer Service Request Account | C7: 713 | D7: 4856 | E7: 6151 | F7: 0 | G7: 1569 | H7: 13289 | I7: Doms | J7: Skip - Confirmed | L7: This is related to Process Flows and more on an Internal Processing of the lifecycle-based transaction. We can skip as the content is more technical than functional.
A8: C1_CS_REQ_CONT | B8: Customer Service Request Consumer Contract | C8: 0 | D8: 0 | E8: 0 | F8: 0 | G8: 0 | H8: 0
A9: C1_CS_REQ_CONT_PROD | B9: Customer Service Request Contract Product | C9: 0 | D9: 0 | E9: 0 | F9: 0 | G9: 0 | H9: 0
A10: C1_CS_REQ_PER | B10: Customer Service Request Person | C10: 722 | D10: 5079 | E10: 5557 | F10: 0 | G10: 1558 | H10: 12916 | I10: Doms | J10: Skip - Confirmed | L10: This is related to Process Flows and more on an Internal Processing of the lifecycle-based transaction. We can skip as the content is more technical than functional.
A11: C1_CS_REQ_PREM | B11: Customer Service Request Premise | C11: 684 | D11: 4766 | E11: 5421 | F11: 0 | G11: 1784 | H11: 12655 | I11: Doms | J11: Skip - Confirmed | L11: This is related to Process Flows and more on an Internal Processing of the lifecycle-based transaction. We can skip as the content is more technical than functional.
A12: C1_CS_REQ_SA | B12: Customer Service Request SA | C12: 2091 | D12: 14404 | E12: 18037 | F12: 0 | G12: 4857 | H12: 39389 | I12: Doms | J12: Skip - Confirmed | L12: This is related to Process Flows and more on an Internal Processing of the lifecycle-based transaction. We can skip as the content is more technical than functional.
A13: C1_CS_REQ_SVC_LOC | B13: Customer Service Request Service Location | C13: 0 | D13: 0 | E13: 0 | F13: 0 | G13: 0 | H13: 0
A14: C1_CUST_REL_REQ | B14: Customer Relationship Request | C14: 0 | D14: 0 | E14: 0 | F14: 0 | G14: 0 | H14: 0
A15: C1_LEAD | B15: Lead | C15: 0 | D15: 0 | E15: 0 | F15: 0 | G15: 0 | H15: 0
A16: C1_LEAD_EVT | B16: Lead Event | C16: 0 | D16: 0 | E16: 0 | F16: 0 | G16: 0 | H16: 0
A17: C1_MKT_RP | B17: Registration Point | C17: 0 | D17: 0 | E17: 0 | F17: 0 | G17: 0 | H17: 0
A18: C1_MKTMSG_CHG | B18: Market Charge | C18: 0 | D18: 0 | E18: 0 | F18: 0 | G18: 0 | H18: 0
A19: C1_MKTMSG_PAY | B19: Market Payment | C19: 0 | D19: 0 | E19: 0 | F19: 0 | G19: 0 | H19: 0
A20: C1_MKTMSG_USG | B20: Market Usage | C20: 0 | D20: 0 | E20: 0 | F20: 0 | G20: 0 | H20: 0
A21: C1_NTF_PREF | B21: Communication Preference | C21: 0 | D21: 0 | E21: 0 | F21: 0 | G21: 0 | H21: 0
A22: C1_OFFCYC_BGEN | B22: Off Cycle Bill Generator | C22: 52675 | D22: 169 | E22: 36816 | F22: 6073 | G22: 9 | H22: 95742 | I22: Doms | J22: Skip - Confirmed | L22: Agree, this is more of an internal transaction to process and correct the read and rebill of the old bill segment using the new usage. This can be skipped | M22: This is more of an internal transaction, whose results are stored in a bill. It's best to keep track of the bills instead.
A23: C1_PA_RQST | B23: Payment Arrangement Request | C23: 358 | D23: 0 | E23: 0 | F23: 1 | G23: 0 | H23: 359 | I23: Doms | J23: DEV - Complete | L23: Agree, a domain should be created as this table contains information on the arrangement downpayment, arrangement amounts, number of installments, and installment amount. | M23: This needs to be created because we don't have a fixed set of tables for the payment arrangements. We only use the SA's recurring charge history page to keep track of payment arrangements. | O23: This table contains information on the arrangement downpayment, arrangement amounts, number of installments, and installment amount.
A24: C1_RESPONSE | B24: Response | F24: 0 | H24: 0
A25: C1_USAGE | B25: C-side Usage | C25: 15360951 | D25: 2173379 | E25: 445035 | F25: 1500648 | G25: 251992 | H25: 19732005 | I25: Lennice | J25: DEV - Complete
A26: C1_WEB_USER | B26: Web User | C26: 0 | D26: 0 | E26: 0 | F26: 0 | G26: 0 | H26: 0
A27: C1_WEB_USER_ACCT | B27: Web User Account | C27: 0 | D27: 0 | E27: 0 | F27: 0 | G27: 0 | H27: 0
A28: CI_ACCT | B28: Account | C28: 59950 | D28: 29496 | E28: 90087 | F28: 155128 | G28: 22560 | H28: 357221 | I28: Josh | J28: DEV - Complete
A29: CI_ADJ | B29: Adjustment | C29: 8715478 | D29: 557276 | E29: 328670 | F29: 2312799 | G29: 197579 | H29: 12111802 | I29: Josh | J29: DEV - Complete
A30: CI_ADJ_STG_CTL | B30: Adjustment Staging Control | C30: 0 | D30: 5 | E30: 1 | F30: 0 | G30: 1 | H30: 7 | I30: Doms | J30: Skip - Confirmed | L30: Agree, this is transitory/internal transaction. This can be skipped | M30: This is a transitory transaction which results to an adjustment being created and we have a report for that already.
A31: CI_ADJ_STG_UP | B31: Adjustment Upload | C31: 0 | D31: 22839 | E31: 1452 | F31: 0 | G31: 1468 | H31: 25759 | I31: Doms | J31: Skip - Confirmed | L31: Agree, this is transitory/internal transaction. This can be skipped | M31: This is a transitory transaction which results to an adjustment being created and we have a report for that already.
A32: CI_AM_REQ | B32: Activity Request | C32: 0 | D32: 0 | E32: 0 | F32: 0 | G32: 0 | H32: 0
A33: CI_APPR_REQ | B33: Approval Request | C33: 2468 | D33: 4252 | E33: 8818 | F33: 3127 | G33: 741 | H33: 19406 | I33: Doms | J33: DEV - Complete | L33: Agree, a domain should be created as this table contains information for the Approval History of the Adjustment until it is Frozen | M33: Related to adjustments. Seems that we need to track this. | O33: This table contains information for the Approval History of the Adjustment until it is Frozen
A34: CI_AUDIT | B34: Audit | C34: 0 | D34: 0 | E34: 0 | F34: 0 | G34: 1348 | H34: 1348 | I34: Doms | J34: Skip - Confirmed | L34: We can skip this since only a few tables have audit turned on. It's also not recommended to turn on auditing for many transaction tables at this time, as it would consume a lot of database space and may cause slowness on the server. | M34: Audit of database tables. No need to keep track of this. Just use the C2M pages
A35: CI_BAL_CTL_GRP | B35: Balance Control Group | C35: 21 | D35: 21 | E35: 15 | F35: 14 | G35: 10 | H35: 81 | I35: Doms | J35: Skip - Confirmed | L35: We can skip this. The data being stored here which is the sum of Total and Current of FTs, are being processed by its background processes to check Integrity of the FTs in each historical Balance Control Group | M35: Similar to balancing deposit controls and tender controls, we should keep track of this as well. See if creating a report here is still needed as c2m looks straightforward though.
A36: CI_BATCH_JOB | B36: Batch Job Ad-Hoc Queues | C36: 2928 | D36: 1319 | E36: 1329 | F36: 4256 | G36: 829 | H36: 10661 | I36: Doms | J36: Skip - Confirmed | M36: Records on this table came from the submitted rundeck jobs. There is no need to keep track of these as we keep track of CI_BATCH_INST table separately.
A37: CI_BATCH_RUN | B37: Batch Run | C37: 312507 | D37: 446935 | E37: 394785 | F37: 443985 | G37: 305236 | H37: 1903448 | I37: Josh | J37: DEV - Complete
A38: CI_BCHG_UP | B38: Billable Charge Upload | C38: 0 | D38: 0 | E38: 0 | F38: 0 | G38: 0 | H38: 0
A39: CI_BILL | B39: Bill Header | C39: 4175472 | D39: 467909 | E39: 538151 | F39: 2582940 | G39: 740293 | H39: 8504765 | I39: Doms | J39: DEV - Complete | O39: This table contains information of the Bill Details
A40: CI_BILL_CHG | B40: Billable Charge | C40: 1893 | D40: 9626 | E40: 18110 | F40: 5394 | G40: 0 | H40: 35023 | I40: Doms | J40: Skip - Confirmed | L40: The CI_BILL_CHG table does not need to be designed since it functions as an internal/staging record. It will be picked up in the next bill, and the calculation line details will be reflected in CI_BSEG_CALC_LN. The Billable Charge ID will be linked to CI_BSEG_CALC.
A41: CI_BILL_RVW_SCH | B41: Bill Review Schedule | C41: 0 | D41: 0 | E41: 0 | F41: 0 | G41: 0 | H41: 0
A42: CI_BPRT_GRP | B42: Bill Print Group | C42: 0 | D42: 0 | E42: 0 | F42: 0 | G42: 0 | H42: 0
A43: CI_BSEG | B43: Bill Segment | C43: 12920736 | D43: 1428974 | E43: 1836637 | F43: 12115681 | G43: 2318982 | H43: 30621010 | I43: Doms | J43: DEV - Complete
A44: CI_BUD_RVW | B44: Budget Review | C44: 0 | D44: 0 | E44: 978 | F44: 1415 | G44: 1 | H44: 2394 | I44: Doms | J44: Skip - Confirmed | L44: We can skip this. It’s mainly for C2M online use for users to easily view budget review records and directly navigate to the account. | M44: This is just one table and it's better to simply use what’s on C2M as it does more by going to the specific SA for further actionn
A45: CI_CASE | B45: Case | C45: 49 | D45: 8 | E45: 0 | F45: 0 | G45: 4 | H45: 61 | I45: Josh | J45: DEV - Complete
A46: CI_CC | B46: Customer Contact | C46: 933459 | D46: 22886 | E46: 96066 | F46: 407356 | G46: 176609 | H46: 1636376 | I46: Josh | J46: DEV - Complete
A47: CI_COLL_AGY_REF | B47: Collection Agency Referral | C47: 0 | D47: 0 | E47: 2213 | F47: 7619 | G47: 0 | H47: 9832 | I47: Josh | J47: DEV - Complete
A48: CI_COLL_PROC | B48: Collection Process | C48: 19502 | D48: 6114 | E48: 32502 | F48: 27904 | G48: 299 | H48: 86321 | I48: Josh | J48: DEV - Complete
A49: CI_COP | B49: Contract Option | C49: 0 | D49: 0 | E49: 0 | F49: 0 | G49: 0 | H49: 0
A50: CI_COP_EVT | B50: Contract Option Event | C50: 0 | D50: 0 | E50: 0 | F50: 0 | G50: 0 | H50: 0
A51: CI_CUT_PROC | B51: Cut Process | C51: 0 | D51: 0 | E51: 0 | F51: 0 | G51: 0 | H51: 0
A52: CI_DCL | B52: Declaration | C52: 0 | D52: 0 | E52: 0 | F52: 0 | G52: 0 | H52: 0
A53: CI_DEP_CTL | B53: Deposit Control | C53: 2022 | D53: 1495 | E53: 1421 | F53: 1969 | G53: 754 | H53: 7661 | I53: Josh | J53: DEV - Complete
A54: CI_DEP_CTL_ST | B54: Deposit Control Staging | C54: 167 | D54: 47 | E54: 53 | F54: 38 | G54: 139 | H54: 444 | I54: Doms | J54: Skip - Confirmed | L54: We can skip this. This is a staging table for internal processing | M54: The information in the staging table is captured on both actual Deposit Control and Tender Control recods.
A55: CI_DEP_RVW | B55: Deposit Review | C55: 0 | D55: 0 | E55: 0 | F55: 0 | G55: 674 | H55: 674 | I55: Doms | J55: Skip - Confirmed | L55: We can skip this. It’s mainly for C2M online use for users to easily view deposit review records and directly navigate to the account. | M55: This is just one table and it's better to simply use what’s on C2M as it does more by going to the specific SA for further actionn
A56: CI_DV_TEST | B56: Device Test | C56: 0 | D56: 0 | E56: 0 | F56: 0 | G56: 0 | H56: 0
A57: CI_DV_TEST_SEL | B57: Device Test Selection | C57: 0 | D57: 0 | E57: 0 | F57: 0 | G57: 0 | H57: 0
A58: CI_ENRL | B58: Order | C58: 0 | D58: 0 | E58: 0 | F58: 10372 | G58: 0 | H58: 10372 | I58: Doms | J58: Skip - Confirmed | L58: The order is being used by College Station to start a service, which is the object created by OCX during move-in. The end result is that the customer will have their SA started at the premise being moved into. We can skip this. | M58: We can secure a lot of insights here, especially for College Station
A59: CI_FA | B59: Field Activity | C59: 26866 | D59: 20033 | E59: 38063 | F59: 73934 | G59: 10973 | H59: 169869 | I59: Doms | J59: Skip - Confirmed | K59: No | M59: This can be skipped. In C2M this more on a backend data and the one being displayed online is the Activity (D1-Activity) which is the SOM Counterpart
A60: CI_FA_STAGE_UP | B60: FA Upload Staging | C60: 0 | D60: 0 | E60: 0 | F60: 0 | G60: 0 | H60: 0
A61: CI_FO | B61: Field Order | C61: 0 | D61: 0 | E61: 0 | F61: 0 | G61: 0 | H61: 0
A62: CI_FO_STG_DWN | B62: Field Order Download Staging | C62: 0 | D62: 0 | E62: 0 | F62: 0 | G62: 0 | H62: 0
A63: CI_FT | B63: Financial Transaction | C63: 29847799 | D63: 3665021 | E63: 3985463 | F63: 25792770 | G63: 4732297 | H63: 68023350 | I63: Doms | J63: DEV - Complete | O63: This table contains information of the Financial Transactions
A64: CI_INTV_DATA_SET | B64: Interval Data Set | C64: 0 | D64: 0 | E64: 0 | F64: 0 | G64: 0 | H64: 0
A65: CI_INTV_PF | B65: Interval Data Profile | C65: 0 | D65: 0 | E65: 0 | F65: 0 | G65: 0 | H65: 0
A66: CI_INTV_VAL_SET | B66: Interval Value Set | C66: 0 | D66: 0 | E66: 0 | F66: 0 | G66: 0 | H66: 0
A67: CI_ITEM | B67: Item | C67: 0 | D67: 0 | E67: 0 | F67: 0 | G67: 0 | H67: 0
A68: CI_ITEM_SQ_EST | B68: Item Type SQ Estimate | C68: 0 | D68: 0 | E68: 0 | F68: 0 | G68: 0 | H68: 0
A69: CI_LANDLORD | B69: Landlord Agreement | C69: 0 | D69: 0 | E69: 2423 | F69: 15020 | G69: 1707 | H69: 19150 | I69: Josh | J69: DEV - Complete
A70: CI_MATCH_EVT | B70: Match Event | C70: 0 | D70: 0 | E70: 0 | F70: 0 | G70: 0 | H70: 0
A71: CI_MR | B71: Meter Read | C71: 0 | D71: 0 | E71: 0 | F71: 0 | G71: 0 | H71: 0
A72: CI_MR_STAGE_DWN | B72: Meter Read Download Staging | C72: 0 | D72: 0 | E72: 0 | F72: 0 | G72: 0 | H72: 0
A73: CI_MR_STAGE_UP | B73: Meter Read Upload Staging | C73: 0 | D73: 0 | E73: 0 | F73: 0 | G73: 0 | H73: 0
A74: CI_MSG_LOG | B74: Message Log | C74: 916103 | D74: 987729 | E74: 815772 | F74: 1035955 | G74: 631739 | H74: 4387298 | I74: Doms | J74: Skip - Confirmed | M74: This can be skipped. These are batch run tree substitution values.
A75: CI_MTR | B75: Meter | C75: 0 | D75: 0 | E75: 0 | F75: 0 | G75: 0 | H75: 0
A76: CI_MTR_CONFIG | B76: Meter Configuration | C76: 0 | D76: 0 | E76: 0 | F76: 0 | G76: 0 | H76: 0
A77: CI_NT_DWN | B77: Notification Download Staging | C77: 0 | D77: 0 | E77: 0 | F77: 0 | G77: 0 | H77: 0
A78: CI_NT_UP | B78: Notification Upload Staging | C78: 0 | D78: 0 | E78: 0 | F78: 0 | G78: 0 | H78: 0
A79: CI_NT_UP_XSPL | B79: NT Upload Staging Extension Sample | C79: 0 | D79: 0 | E79: 0 | F79: 0 | G79: 0 | H79: 0
A80: CI_OD_PROC | B80: Overdue Process | C80: 0 | D80: 0 | E80: 0 | F80: 0 | G80: 0 | H80: 0
A81: CI_PAY | B81: Payment Header | C81: 2731089 | D81: 455524 | E81: 537659 | F81: 2449489 | G81: 708986 | H81: 6882747 | I81: Josh | J81: DEV - Complete
A82: CI_PAY_EVENT | B82: Payment Event | C82: 2729439 | D82: 450702 | E82: 537390 | F82: 2448621 | G82: 708700 | H82: 6874852 | I82: Josh | J82: DEV - Complete
A83: CI_PAY_TNDR_ST | B83: Payment Tender Staging | C83: 32519 | D83: 388 | E83: 1754 | F83: 5098 | G83: 4790 | H83: 44549 | I83: Doms | J83: Skip - Confirmed | L83: We can skip this. This is a staging table for internal processing | M83: The information in the staging table is captured on both actual Deposit Control and Tender Control recods.
A84: CI_PER | B84: Person | C84: 58435 | D84: 25395 | E84: 49261 | F84: 107202 | G84: 27939 | H84: 268232 | I84: Josh | J84: DEV - Complete
A85: CI_PEVT_DTL_ST | B85: Payment Event Upload Staging | C85: 0 | D85: 0 | E85: 0 | F85: 0 | G85: 0 | H85: 0
A86: CI_PP | B86: Pay Plan | C86: 7 | D86: 16 | E86: 4442 | F86: 2648 | G86: 38 | H86: 7151 | I86: Josh | J86: DEV - Complete
A87: CI_PREM | B87: Premise | C87: 49890 | D87: 16282 | E87: 12006 | F87: 69240 | G87: 15184 | H87: 162602 | I87: Lennice | J87: DEV - Complete
A88: CI_QUOTE | B88: Quote | C88: 0 | D88: 0 | E88: 0 | F88: 0 | G88: 0 | H88: 0
A89: CI_REBATE_CLAIM | B89: Rebate Claim | C89: 0 | D89: 0 | E89: 0 | F89: 0 | G89: 0 | H89: 0
A90: CI_REBATE_LINE | B90: Rebate Claim Line | C90: 0 | D90: 0 | E90: 0 | F90: 0 | G90: 0 | H90: 0
A91: CI_REG_DATA_SET | B91: Interval Register Data Set | C91: 0 | D91: 0 | E91: 0 | F91: 0 | G91: 0 | H91: 0
A92: CI_SA | B92: SA (Service Agreement) | C92: 194102 | D92: 144153 | E92: 119294 | F92: 943834 | G92: 75469 | H92: 1476852 | I92: Josh | J92: DEV - Complete
A93: CI_SA_REL | B93: SA Relationship | C93: 0 | D93: 0 | E93: 0 | F93: 0 | G93: 7948 | H93: 7948 | I93: Doms | J93: Skip - Confirmed | L93: We can skip this. The purpose of the SA Relationship is to record information if we handle the Billing of an External Server Provider (We Bill for Them) or it's us (the current utility provider). Currently, only City Corp is using this table, but only billing the currently utility, not an external service provide. So its not fully utilizing the Functionality. | M93: We are reporting on Sas anyways
A94: CI_SCM | B94: Service Credit Membership | C94: 0 | D94: 0 | E94: 0 | F94: 0 | G94: 0 | H94: 0
A95: CI_SC_EVT | B95: Service Credit Event | C95: 0 | D95: 0 | E95: 0 | F95: 0 | G95: 0 | H95: 0
A96: CI_SEV_PROC | B96: Severance Process | C96: 30490 | D96: 0 | E96: 17041 | F96: 47105 | G96: 0 | H96: 94636 | I96: Josh | J96: DEV - Complete
A97: CI_SP | B97: Service Point - CCB | C97: 44699 | D97: 17674 | E97: 32598 | F97: 226778 | G97: 29259 | H97: 351008 | I97: Lennice | J97: Skip - Confirmed | L97: We can skip this, the SP information in C2M is retrieved from the D1_SP table.
A98: CI_SP_ITEM_HIST | B98: SP Item History | C98: 0 | D98: 0 | E98: 0 | F98: 0 | G98: 0 | H98: 0
A99: CI_SP_MTR_HIST | B99: SP/Meter History | C99: 0 | D99: 0 | E99: 0 | F99: 0 | G99: 0 | H99: 0
A100: CI_STK_LOC | B100: Stock Location | C100: 0 | D100: 0 | E100: 0 | F100: 0 | G100: 0 | H100: 0
...

Sheet Manual Labels
A1: Table | B1: Field | C1: Contrived Description
A2: CMS_D1_ACTIVITY_D1FA_BODA_VW | B2: APPOINTMENT_COMMENTS | C2: Appointment Comments
A3: CMS_D1_ACTIVITY_D1FA_BODA_VW | B3: APPOINTMENT_FLG | C3: Appointment Necessary
A4: CMS_D1_ACTIVITY_D1FA_BODA_VW | B4: APPOINTMENT_TAKEN_BY | C4: Appointment Taken By
A5: CMS_D1_ACTIVITY_D1FA_BODA_VW | B5: APPOINTMENT_TAKEN_DATE | C5: Appointement Taken Date
A6: CMS_D1_SP_BODA_VW | B6: SVC_QTY_IDNTFR_CD_ITEM_TYPE | C6: Item Type (SQI)

Sheet SP upgrades
A1: w1_asset

Sheet BODA
A1: Table | B1: BODA VW Created (Y/N) | C1: BODA VW Name | D1: Alternate BODA VW
A2: W1_ASSET | B2: N | C2: N/A | D2: N/A
A3: W1_NODE | B3: N | C3: N/A | D3: D1_SP
A4: D1_SP | B4: Y | C4: CMS_D1_SP_BODA_VW | D4: N/A
A5: D1_ACTIVITY | B5: Y | C5: CMS_D1_ACTIVITY_D1FA_BODA_VW | D5: N/A
A6: C1_PA_RQST | B6: Y | C6: CMS_C1_PA_RQST_BODA_VW | D6: N/A
A7: D1_ACTIVITY | B7: Y | C7: CMS_D1_ACTIVITY_D1FA_W_ML_BODA_VW | D7: N/A
A8: C1_REPRESENTATIVE | B8: Y | C8: CMS_C1_REPRESENTATIVE_BODA_VW | D8: N/A
A9: CI_APPR_REQ | B9: Y | C9: CMS_CI_APPR_REQ_BODA_VW | D9: N/A

Sheet Malformed XML DA
A1: Client | B1: Environment | C1: Table | D1: Primary Key
A2: Newark | B2: TST | C2: D1_ACTIVITY | D2: 01211419413092
A3: Newark | B3: TST | C3: D1_ACTIVITY | D3: 51125812041817

Sheet D1_ACTIVITY (with ML)
B1: Summary
B2: Table Name: D1_ACTIVITY
B3: Justification | C3: =Summary!O118 -> This table records information about Field Activities. It is useful for Clients as it allows them to easily access and extract FA-related data via reports.
B4: Designer | C4: Doms
A5: Table Name | B5: Field Name | C5: Field Description | D5: Related Table | E5: Filter | F5: Join Type | G5: Designer Notes | H5: Reviewer Notes
A6: D1_ACTIVITY | B6: D1_ACTIVITY_ID | C6: Activity ID | D6: N/A | F6: N/A
A7: D1_ACTIVITY | B7: BUS_OBJ_CD | C7: Business Object | D7: * F1_BUS_OBJ_L | F7: Inner Join
A8: D1_ACTIVITY | B8: BO_STATUS_CD | C8: Status | D8: * F1_BUS_OBJ_STATUS_L | F8: Inner Join
A9: D1_ACTIVITY | B9: ACTIVITY_TYPE_CD | C9: Activity Type | D9: * D1_ACTIVITY_TYPE * D1_ACTIVITY_TYPE_L | E9: ACTIVITY_TYPE_CAT_FLG = ‘D1FA’ | F9: Inner Join
A10: D1_ACTIVITY | B10: START_DTTM | C10: Start Date/Time | D10: N/A | F10: N/A
A11: D1_ACTIVITY | B11: END_DTTM | C11: End Date/Time | D11: N/A | F11: N/A
A12: D1_ACTIVITY | B12: CRE_DTTM | C12: Create Date/Time | D12: N/A | F12: N/A
A13: D1_ACTIVITY | B13: STATUS_UPD_DTTM | C13: Status Date/Time | D13: N/A | F13: N/A
A14: D1_ACTIVITY | B14: BO_STATUS_REASON_CD | C14: Status Reason | D14: * F1_BUS_OBJ_STATUS_RSN_L | F14: Left Join
A15: D1_ACTIVITY | B15: VERSION | C15: Version | D15: N/A | F15: N/A
A16: D1_ACTIVITY | B16: EFF_DTTM | C16: Effective Date/Time | D16: N/A | F16: N/A
A17: D1_ACTIVITY | B17: FIELD_TASK_TYPE | C17: Field Task Type | D17: * F1_EXT_LOOKUP_VAL, * F1_EXT_LOOKUP_VAL_L | E17: BUS_OBJ_CD = ‘D1-FieldTaskTypeLookup’ | F17: Inner Join
A18: D1_ACTIVITY | B18: CANCEL_REASON | C18: Cancel Reason | D18: * F1_EXT_LOOKUP_VAL * F1_EXT_LOOKUP_VAL_L | E18: BUS_OBJ_CD = ‘D1-CancelReasonLookup’ | F18: Left Join
A24: D1_ACTIVITY | B24: ILM_DT | C24: ILM Date | D24: N/A. We can ignore | F24: N/A
A25: D1_ACTIVITY | B25: ILM_ARCH_SW | C25: ILM Archive Switch | D25: N/A. We can ignore | F25: N/A
A26: D1_ACTIVITY | B26: RETENTION_PERIOD | C26: Retention Period | D26: N/A. We can ignore | F26: N/A
A27: D1_ACTIVITY | B27: RESCHEDULE_REASON | C27: Reschedule Reason | D27: * F1_EXT_LOOKUP_VAL * F1_EXT_LOOKUP_VAL_L | E27: BUS_OBJ_CD = ‘D1-RescheduleReasonLookup’ | F27: Left Outer
A28: D1_ACTIVITY | B28: EXPIRATION_DTTM | C28: Expiration Date Time | D28: BO_DATA_AREA | F28: TBD. Left Outer if we are going to use a View to get the BO_DATA_AREA values
A29: D11_ACTIVITY_REL | B29: PARENT_ACTIVITY_ID | C29: Parent Activity ID | D29: * D1_ACTIVITY_REL | E29: ACTIVITY_REL_TYPE_FLG = ‘D1PR’ | F29: Left Outer
A30: D1_SP | B30: D1_SP | C30: Service Point | D30: * D1_ACTIVITY_REL_OBJ * D1_SP | E30: MAINT_OBJ_CD = ‘D1-SP’ ACTIVITY_REL_OBJ_TYPE_FLG = ‘D1RO’ | F30: Inner Join
A31: D1_SP | B31: D1_SP_TYPE_CD | C31: Service Point Type | D31: * D1_SP * D1_SP_TYPE_L | F31: Inner Join
A32: D1_SP | B32: APPOINTMENT_WINDOW_START_DTTM | C32: Appointment Window Start Date/Time | D32: BO_DATA_AREA | F32: TBD. Left Outer if we are going to use a View to get the BO_DATA_AREA values
A33: D1_SP | B33: APPOINTMENT_WINDOW_END_DTTM | C33: Appointment Window End Date/Time | D33: BO_DATA_AREA | F33: TBD. Left Outer if we are going to use a View to get the BO_DATA_AREA values
A34: D1_SP | B34: D1_TAKEN_BY | C34: Appointment Taken By | D34: BO_DATA_AREA | F34: TBD. Left Outer if we are going to use a View to get the BO_DATA_AREA values
A35: D1_SP | B35: D1_TAKEN_DATE | C35: Appointment Taken Date | D35: BO_DATA_AREA | F35: TBD. Left Outer if we are going to use a View to get the BO_DATA_AREA values
A36: D1_SP | B36: D1_COMMENT | C36: Appointment Comment | D36: BO_DATA_AREA | F36: TBD. Left Outer if we are going to use a View to get the BO_DATA_AREA values
A37: D1_SP | B37: CR_RECIPIENT | C37: Recipient | D37: * D1_ACTIVITY_REL_OBJ * D1_SPR_L | E37: MAINT_OBJ_CD = ‘D1-SVCPROVDR’ ACTIVITY_REL_OBJ_TYPE_FLG = ‘D1RC’ | F37: Left Outer
A38: D1_SP | B38: COMMENTS | C38: Comments | D38: BO_DATA_AREA | F38: TBD. Left Outer if we are going to use a View to get the BO_DATA_AREA values
A39: D1_SP | B39: D1_INSTRUCTIONS | C39: Instructions | D39: BO_DATA_AREA | F39: TBD. Left Outer if we are going to use a View to get the BO_DATA_AREA values
A40: D1_SP | B40: D1_DEVICE_ID | C40: Device ID | D40: * D1_ACTIVITY_REL_OBJ * D1_DVC | E40: MAINT_OBJ_CD = ‘D1-DEVICE’ | F40: Left Outer
A41: D1_SP | B41: DEVICE_TYPE_CD | C41: Device Type | D41: * D1_DVC * D1_DVC_TYPE * D1_DVC_TYPE_L | F41: Left Outer
A42: D1_SP | B42: D1_BADGE_NBR | C42: Badge Number | D42: * D1_DVC * D1_DVC_IDENTIFIER | E42: DVC_ID_TYPE_FLG = ‘D1BN’ | F42: Left Outer
A43: D1_SP | B43: CR_REQUESTER | C43: Requester | D43: * D1_ACTIVITY_REL_OBJ * D1_SPR_L | E43: MAINT_OBJ_CD = ‘D1-SVCPROVDR’ ACTIVITY_REL_OBJ_TYPE_FLG = ‘D1RC’ | F43: Left Outer
A44: D1_SP | B44: CR_RQSTR_TRAN_ID | C44: Requester Transaction ID | D44: * D1_ACTIVITY_IDENTIFIER | E44: ACTIVITY_ID_TYPE_FLG = ‘D1RI’ | F44: Left Outer
A45: D1_SP | B45: EXT_REFERENCE_ID | C45: External Reference ID | D45: BO_DATA_AREA | F45: TBD.Left Join if we are going to use a View to get the BO_DATA_AREA values
A46: D1_SP | B46: ADDRESS1_UPR | C46: Address | D46: D1_SP | F46: Inner Join | G46: Additional info outside D1_ACTIVITY
A47: D1_SP | B47: CITY_UPPER | C47: City | D47: D1_SP | F47: Inner Join | G47: Additional info outside D1_ACTIVITY
A48: D1_SP | B48: COUNTY | C48: County | D48: D1_SP | F48: Inner Join | G48: Additional info outside D1_ACTIVITY
A49: D1_SP | B49: POSTAL | C49: Postal | D49: D1_SP | F49: Inner Join | G49: Additional info outside D1_ACTIVITY
A50: D1_SP | B50: STATE | C50: State | D50: D1_SP | F50: Inner Join | G50: Additional info outside D1_ACTIVITY
A51: D1_SP | B51: COUNTRY | C51: Country | D51: D1_SP | F51: Inner Join | G51: Additional info outside D1_ACTIVITY
A52: D1_SP | B52: D1_GEO_LAT | C52: Geographic Latitude | D52: D1_SP | F52: Inner Join | G52: Additional info outside D1_ACTIVITY
A53: D1_SP | B53: D1_GEO_LONG | C53: Geographic Longitude | D53: D1_SP | F53: Inner Join | G53: Additional info outside D1_ACTIVITY
A54: D1_SP | B54: D1_CONT_EXTERNAL_ID | C54: Person ID | D54: BO_DATA_AREA | F54: TBD.Left Join if we are going to use a View to get the BO_DATA_AREA values
A55: D1_SP | B55: D1_CUSTOMERNAME | C55: Customer Name | D55: BO_DATA_AREA | F55: TBD.Left Join if we are going to use a View to get the BO_DATA_AREA values
A56: D1_SP | B56: D1_CONTACTNAME | C56: Contact Name | D56: BO_DATA_AREA | F56: TBD.Left Join if we are going to use a View to get the BO_DATA_AREA values
A57: D1_SP | B57: D1_MAINPHONE | C57: Main Phone | D57: BO_DATA_AREA | F57: TBD.Left Join if we are going to use a View to get the BO_DATA_AREA values
A58: D1_SP | B58: D1_CELLPHONE | C58: Cell Phone | D58: BO_DATA_AREA | F58: TBD.Left Join if we are going to use a View to get the BO_DATA_AREA values
A59: D1_SP | B59: EMAIL_VALUE | C59: Email | D59: BO_DATA_AREA | F59: TBD.Left Join if we are going to use a View to get the BO_DATA_AREA values
A60: D1_SP | B60: EXTERNAL_ACCT_ID | C60: Account ID | D60: BO_DATA_AREA | F60: TBD.Left Join if we are going to use a View to get the BO_DATA_AREA values

Sheet D1_ACTIVITY (no ML)
B1: Summary
B2: Table Name: D1_ACTIVITY
B3: Justification | C3: =Summary!O118 -> This table records information about Field Activities. It is useful for Clients as it allows them to easily access and extract FA-related data via reports.
A5: Table Name | B5: Field Name | C5: Field Description | D5: Related Table | E5: Filter | F5: Join Type | G5: Designer Notes | H5: Reviewer Notes
A6: D1_ACTIVITY | B6: D1_ACTIVITY_ID | C6: Activity ID | D6: N/A | F6: N/A
A7: D1_ACTIVITY | B7: BUS_OBJ_CD | C7: Business Object | D7: * F1_BUS_OBJ_L | F7: Inner Join
A8: D1_ACTIVITY | B8: BO_STATUS_CD | C8: Status | D8: * F1_BUS_OBJ_STATUS_L | F8: Inner Join
A9: D1_ACTIVITY | B9: ACTIVITY_TYPE_CD | C9: Activity Type | D9: * D1_ACTIVITY_TYPE * D1_ACTIVITY_TYPE_L | E9: ACTIVITY_TYPE_CAT_FLG = ‘D1FA’ | F9: Inner Join
A10: D1_ACTIVITY | B10: START_DTTM | C10: Start Date/Time | D10: N/A | F10: N/A
A11: D1_ACTIVITY | B11: END_DTTM | C11: End Date/Time | D11: N/A | F11: N/A
A12: D1_ACTIVITY | B12: CRE_DTTM | C12: Create Date/Time | D12: N/A | F12: N/A
A13: D1_ACTIVITY | B13: STATUS_UPD_DTTM | C13: Status Date/Time | D13: N/A | F13: N/A
A14: D1_ACTIVITY | B14: BO_STATUS_REASON_CD | C14: Status Reason | D14: * F1_BUS_OBJ_STATUS_RSN_L | F14: Left Join
A15: D1_ACTIVITY | B15: VERSION | C15: Version | D15: N/A | F15: N/A
A16: D1_ACTIVITY | B16: EFF_DTTM | C16: Effective Date/Time | D16: N/A | F16: N/A
A17: D1_ACTIVITY | B17: FIELD_TASK_TYPE | C17: Field Task Type | D17: * F1_EXT_LOOKUP_VAL * F1_EXT_LOOKUP_VAL_L | E17: BUS_OBJ_CD = ‘D1-FieldTaskTypeLookup’ | F17: Inner Join
A18: D1_ACTIVITY | B18: CANCEL_REASON | C18: Cancel Reason | D18: * F1_EXT_LOOKUP_VAL * F1_EXT_LOOKUP_VAL_L | E18: BUS_OBJ_CD = ‘D1-CancelReasonLookup’ | F18: Left Outer
A19: D1_ACTIVITY | B19: ILM_DT | C19: ILM Date | D19: N/A. We can ignore | F19: N/A
A20: D1_ACTIVITY | B20: ILM_ARCH_SW | C20: ILM Archive Switch | D20: N/A. We can ignore | F20: N/A
A21: D1_ACTIVITY | B21: RETENTION_PERIOD | C21: Retention Period | D21: N/A. We can ignore | F21: N/A
A22: D1_ACTIVITY | B22: RESCHEDULE_REASON | C22: Reschedule Reason | D22: * F1_EXT_LOOKUP_VAL * F1_EXT_LOOKUP_VAL_L | E22: BUS_OBJ_CD = ‘D1-RescheduleReasonLookup’ | F22: Left Outer
A23: D1_ACTIVITY | B23: EXPIRATION_DTTM | C23: Expiration Date Time | D23: BO_DATA_AREA | F23: TBD. Left Outer if we are going to use a View to get the BO_DATA_AREA values
A24: D1_ACTIVITY | B24: PARENT_ACTIVITY_ID | C24: Parent Activity ID | D24: * D1_ACTIVITY_REL | E24: ACTIVITY_REL_TYPE_FLG = ‘D1PR’ | F24: Left Outer
B25: D1_SP | C25: Service Point | D25: * D1_ACTIVITY_REL_OBJ * D1_SP | E25: MAINT_OBJ_CD = ‘D1-SP’ ACTIVITY_REL_OBJ_TYPE_FLG = ‘D1RO’ | F25: Inner Join
B26: D1_SP_TYPE_CD | C26: Service Point Type | D26: * D1_SP * D1_SP_TYPE_L | F26: Inner Join
A27: CMS_D1_ACTIVITY_D1FA_BODA_VW | B27: APPOINTMENT_WINDOW_START_DTTM | C27: Appointment Window Start Date/Time | D27: BO_DATA_AREA | F27: Left Outer
B28: APPOINTMENT_WINDOW_END_DTTM | C28: Appointment Window End Date/Time | D28: BO_DATA_AREA | F28: TBD. Left Outer if we are going to use a View to get the BO_DATA_AREA values
B29: D1_TAKEN_BY | C29: Appointment Taken By | D29: BO_DATA_AREA | F29: TBD. Left Outer if we are going to use a View to get the BO_DATA_AREA values
B30: D1_TAKEN_DATE | C30: Appointment Taken Date | D30: BO_DATA_AREA | F30: TBD. Left Outer if we are going to use a View to get the BO_DATA_AREA values
B31: D1_COMMENT | C31: Appointment Comment | D31: BO_DATA_AREA | F31: TBD. Left Outer if we are going to use a View to get the BO_DATA_AREA values
B32: CR_RECIPIENT | C32: Recipient | D32: * D1_ACTIVITY_REL_OBJ * D1_SPR_L | E32: MAINT_OBJ_CD = ‘D1-SVCPROVDR’ ACTIVITY_REL_OBJ_TYPE_FLG = ‘D1RC’ | F32: Left Outer
B33: COMMENTS | C33: Comments | D33: BO_DATA_AREA | F33: TBD. Left Outer if we are going to use a View to get the BO_DATA_AREA values
B34: D1_INSTRUCTIONS | C34: Instructions | D34: BO_DATA_AREA | F34: TBD. Left Outer if we are going to use a View to get the BO_DATA_AREA values
B35: D1_DEVICE_ID | C35: Device ID | D35: * D1_ACTIVITY_REL_OBJ * D1_DVC | E35: MAINT_OBJ_CD = ‘D1-DEVICE’ | F35: Left Outer
B36: DEVICE_TYPE_CD | C36: Device Type | D36: * D1_DVC * D1_DVC_TYPE * D1_DVC_TYPE_L | F36: Left Outer
B37: D1_BADGE_NBR | C37: Badge Number | D37: * D1_DVC * D1_DVC_IDENTIFIER | E37: DVC_ID_TYPE_FLG = ‘D1BN’ | F37: Left Outer
B38: CR_REQUESTER | C38: Requester | D38: * D1_ACTIVITY_REL_OBJ * D1_SPR_L | E38: MAINT_OBJ_CD = ‘D1-SVCPROVDR’ ACTIVITY_REL_OBJ_TYPE_FLG = ‘D1RC’ | F38: Left Outer
B39: CR_REQUESTER | C39: Requester Transaction ID | D39: * D1_ACTIVITY_IDENTIFIER | E39: ACTIVITY_ID_TYPE_FLG = ‘D1RI’ | F39: Left Outer
B40: EXT_REFERENCE_ID | C40: External Reference ID | D40: BO_DATA_AREA | F40: TBD. Left Outer if we are going to use a View to get the BO_DATA_AREA values
B41: ADDRESS1_UPR | C41: Address | D41: D1_SP | F41: Inner Join
B42: CITY_UPPER | C42: City | D42: D1_SP | F42: Inner Join
B43: COUNTY | C43: County | D43: D1_SP | F43: Inner Join
B44: POSTAL | C44: Postal | D44: D1_SP | F44: Inner Join
B45: STATE | C45: State | D45: D1_SP | F45: Inner Join
B46: COUNTRY | C46: Country | D46: D1_SP | F46: Inner Join
B47: D1_GEO_LAT | C47: Geographic Latitude | D47: D1_SP | F47: Inner Join
B48: D1_GEO_LONG | C48: Geographic Longitude | D48: D1_SP | F48: Inner Join
B49: D1_CONT_EXTERNAL_ID | C49: Person ID | D49: BO_DATA_AREA | F49: TBD. Left Outer if we are going to use a View to get the BO_DATA_AREA values
B50: D1_CUSTOMERNAME | C50: Customer Name | D50: BO_DATA_AREA | F50: TBD. Left Outer if we are going to use a View to get the BO_DATA_AREA values
B51: D1_CONTACTNAME | C51: Contact Name | D51: BO_DATA_AREA | F51: TBD. Left Outer if we are going to use a View to get the BO_DATA_AREA values
... B55: EXTERNAL_ACCT_ID | C55: Account ID | D55: BO_DATA_AREA | F55: TBD. Left Outer if we are going to use a View to get the BO_DATA_AREA values

Sheet D1_ACTIVITY
B1: Summary
B2: Table Name: D1_ACTIVITY
B3: Data Area: D1-FieldActivity
B4: Justification | C4: =Summary!O118 -> This table records information about Field Activities. It is useful for Clients as it allows them to easily access and extract FA-related data via reports.
A6: Table Name | B6: Field Name | C6: Field Description | D6: Related Table / XPAth | E6: Filter | F6: Join Type | G6: Designer Notes | H6: Reviewer Notes
A7: D1_ACTIVITY | B7: ACTIVITY_TYPE_CD | C7: Activity Type | D7: D1_ACTIVITY_TYPE_L | E7: ACTIVITY_TYPE_CAT_FLG = 'D1FA' | F7: Left Join
A8: D1_ACTIVITY | B8: BO_DATA_AREA | C8: Business Object Data Area | D8: N/A | F8: N/A
A9: D1_ACTIVITY | B9: BO_STATUS_CD | C9: Status | D9: F1_BUS_OBJ_STATUS_L | F9: Inner Join
A10: D1_ACTIVITY | B10: BO_STATUS_REASON_CD | C10: Status Reason | D10: F1_BUS_OBJ_STATUS_RSN_L | F10: Left Join
A11: D1_ACTIVITY | B11: BUS_OBJ_CD | C11: Business Object | D11: F1_BUS_OBJ_L | F11: Inner Join
A12: D1_ACTIVITY | B12: CANCEL_REASON | C12: Cancel Reason | D12: F1_EXT_LOOKUP_VAL_L | E12: BUS_OBJ_CD = 'D1-CancelReasonLookup' | F12: Left Outer
A13: D1_ACTIVITY | B13: CRE_DTTM | C13: Create Date/Time | D13: N/A | F13: N/A
A14: D1_ACTIVITY | B14: D1_ACTIVITY_ID | C14: Activity ID | D14: N/A | F14: N/A
A15: D1_ACTIVITY | B15: EFF_DTTM | C15: Effective Date/Time | D15: N/A | F15: N/A
A16: D1_ACTIVITY | B16: END_DTTM | C16: End Date/Time | D16: N/A | F16: N/A
A17: D1_ACTIVITY | B17: FIELD_TASK_TYPE | C17: Field Task Type | D17: F1_EXT_LOOKUP_VAL_L | E17: BUS_OBJ_CD = 'D1-FieldTaskTypeLookup' | F17: Left Outer
A18: D1_ACTIVITY | B18: ILM_ARCH_SW | C18: ILM Archive Switch | D18: N/A | F18: N/A
A19: D1_ACTIVITY | B19: ILM_DT | C19: ILM Date | D19: N/A | F19: N/A
A20: D1_ACTIVITY | B20: RESCHEDULE_REASON | C20: Reschedule Reason | D20: F1_EXT_LOOKUP_VAL_L | E20: BUS_OBJ_CD = 'D1-RescheduleReasonLookup' | F20: Left Outer
A21: D1_ACTIVITY | B21: RETENTION_PERIOD | C21: Retention Period | D21: N/A | F21: N/A
A22: D1_ACTIVITY | B22: START_DTTM | C22: Start Date/Time | D22: N/A | F22: N/A
A23: D1_ACTIVITY | B23: STATUS_UPD_DTTM | C23: Status Date/Time | D23: N/A | F23: N/A
A24: D1_ACTIVITY | B24: VERSION | C24: Version | D24: N/A | F24: N/A
A25: D1_ACTIVITY_REL (linkage) | B25: ACTIVITY_REL_TYPE_FLG | C25: Activity Relationship Type | E25: FIELD_NAME = 'ACTIVITY_REL_TYPE_FLG' Field_VALUE = parent | F25: Left Outer
A26: D1_ACTIVITY_REL (linkage) | B26: D1_ACTIVITY_ID | C26: Activity ID | D26: N/A | F26: N/A
A27: D1_ACTIVITY_REL (linkage) | B27: REL_ACTIVITY_ID | C27: Related Activity | D27: D1_ACTIVITY | F27: Right Outer
A28: D1_ACTIVITY_REL (linkage) | B28: VERSION | C28: Version | D28: N/A | F28: N/A
A29: D1_ACTIVITY_REL_OBJ (linkage to D1_SP) | B29: ACTIVITY_REL_OBJ_TYPE_FLG | C29: Activity Related Object Type | D29: N/A | E29: ACTIVITY_REL_OBJ_TYPE_FLG = 'D1RO' | F29: Right Outer
A30: D1_ACTIVITY_REL_OBJ (linkage to D1_SP) | B30: D1_ACTIVITY_ID | C30: Activity ID | D30: D1_ACTIVITY | F30: Right Outer
A31: D1_ACTIVITY_REL_OBJ (linkage to D1_SP) | B31: MAINT_OBJ_CD | C31: Maintenance Object | D31: CI_MD_MO_L | E31: MAINT_OBJ_CD = 'D1-SP' | F31: Inner Join
A32: D1_ACTIVITY_REL_OBJ (linkage to D1_SP) | B32: PK_VALUE1 | C32: Primary Key 1 | D32: N/A | F32: N/A
A33: D1_ACTIVITY_REL_OBJ (linkage to D1_SP) | B33: PK_VALUE2 | C33: Primary Key 2 | D33: N/A | F33: N/A
A34: D1_ACTIVITY_REL_OBJ (linkage to D1_SP) | B34: PK_VALUE3 | C34: Primary Key 3 | D34: N/A | F34: N/A
A35: D1_ACTIVITY_REL_OBJ (linkage to D1_SP) | B35: PK_VALUE4 | C35: Primary Key 4 | D35: N/A | F35: N/A
A36: D1_ACTIVITY_REL_OBJ (linkage to D1_SP) | B36: PK_VALUE5 | C36: Primary Key 5 | D36: N/A | F36: N/A
A37: D1_ACTIVITY_REL_OBJ (linkage to D1_SP) | B37: VERSION | C37: Version | D37: N/A | F37: N/A
A38: CMS_D1_ACTIVITY_D1FA_BODA_VW | B38: APPOINTMENT_COMMENTS | C38: Appointment Comments | D38: N/A | F38: N/A
A39: CMS_D1_ACTIVITY_D1FA_BODA_VW | B39: APPOINTMENT_FLG | C39: Appointment | D39: N/A | F39: N/A
A40: CMS_D1_ACTIVITY_D1FA_BODA_VW | B40: APPOINTMENT_TAKEN_BY | C40: Appointment Taken By | D40: N/A | F40: N/A
A41: CMS_D1_ACTIVITY_D1FA_BODA_VW | B41: APPOINTMENT_TAKEN_DATE | C41: Appointment Taken Date | D41: N/A | F41: N/A
A42: CMS_D1_ACTIVITY_D1FA_BODA_VW | B42: APPOINTMENT_WINDOW_END_DTTM | C42: Appointment End Date Time | D42: N/A | F42: N/A
A43: CMS_D1_ACTIVITY_D1FA_BODA_VW | B43: APPOINTMENT_WINDOW_START_DTTM | C43: Appointment Window Date Time | D43: N/A | F43: N/A
... A80: D1_SP | B80: D1_SP_TYPE_CD | C80: Service Point Type | D80: D1_SP_TYPE_L | F80: Inner Join
A81: D1_SP | B81: DISCONN_LOC_FLG | C81: Disconnect Location | D81: CI_LOOKUP_VAL_L | E81: FieldName = 'DISCONN_LOC_FLG' | F81: Left Join
A82: D1_SP | B82: DIVISION_CD | C82: Division | D82: N/A | F82: N/A
A83: D1_SP | B83: GEO_CODE | C83: Geographical Code | D83: N/A | F83: N/A
A84: D1_SP | B84: HOUSE_TYPE | C84: House Type | D84: N/A | F84: N/A
A85: D1_SP | B85: IN_CITY_LIMIT | C85: In City Limit | D85: N/A | F85: N/A
A86: D1_SP | B86: MKT_CD | C86: Market | D86: D1_MKT_L | F86: Left Join
A87: D1_SP | B87: MSRMT_CYC_CD | C87: Measurement Cycle | D87: D1_MSRMT_CYC_L | F87: Left Join
A88: D1_SP | B88: MSRMT_CYC_RTE_CD | C88: Route | D88: D1_MSMRT_CYC_RTE_L | F88: Left Join
A89: D1_SP | B89: MSRMT_CYC_RTE_SEQ | C89: Sequence | D89: N/A | F89: N/A
A90: D1_SP | B90: NUM1 | C90: Number 1 | D90: N/A | F90: N/A
A91: D1_SP | B91: NUM2 | C91: Number 2 | D91: N/A | F91: N/A
A92: D1_SP | B92: POSTAL | C92: Postal | D92: N/A | F92: N/A
A93: D1_SP | B93: SP_SRC_STAT_FLG | C93: Source Status | D93: CI_LOOKUP_VAL_L | E93: FIeldName = 'SP_SRC_STAT_FLG' | F93: Inner Join
A94: D1_SP | B94: STATE | C94: State | D94: CI_STATE_L | F94: Inner Join
A95: D1_SP | B95: STATUS_UPD_DTTM | C95: Status Date/Time | D95: N/A | F95: N/A
A96: D1_SP | B96: TIME_ZONE_CD | C96: Time Zone | D96: CI_TIME_ZONE_L | F96: Inner Join
A97: D1_SP | B97: VERSION | C97: Version | D97: N/A | F97: N/A
A98: CMS_D1_ACTIVITY_D1FA_BODA_VW | B98: CM_ML_IS_PICKUP_FLG | C98: Is Pickup Order | D98: * BO_DATA_AREA * CI_LOOKUP_VAL * CI_LOOKUP_VAL_L | E98: FIELD_NAME = ‘F1_YESNO_FLG’ | F98: TBD.Left Join if we are going to use a View to get the BO_DATA_AREA values *** This will be introduced on 25.1 Release | G98: Mobile Lite Details
A99: D1_ACTIVITY_CHAR | B99: FA_PRIORITY_FLG | C99: Field Activity Priority | D99: * D1_ACTIVITY_CHAR * CI_LOOKUP_VAL * CI_LOOKUP_VAL_L | E99: CHAR_TYPE_CD = ‘CMFAPRIO’ FIELD_NAME = ‘FA_PRIORITY_FLG’ | F99: Left Join | G99: Mobile Lite Details
A100: D1_ACTIVITY_CHAR | B100: FA_INT_STATUS_FLG | C100: Intermediate Status | D100: * D1_ACTIVITY_CHAR * CI_LOOKUP_VAL * CI_LOOKUP_VAL_L | E100: CHAR_TYPE_CD = ‘CMFAINST’ FIELD_NAME = ‘FA_INT_STATUS_FLG’ | F100: Left Join | G100: Mobile Lite Details
A101: D1_ACTIVITY_CHAR | B101: THRD_PTY_REP_CD | C101: Representative | D101: * D1_ACTIVITY_CHAR * C1_REPRESENTATIVE * C1_REPRESENTATIVE_L | E101: CHAR_TYPE_CD = ‘CMFAREP ’ | F101: Left Join | G101: Mobile Lite Details
A102: D1_ACTIVITY_CHAR | B102: CM_ML_SVC_AREA | C102: Service Area | D102: * D1_ACTIVITY_CHAR * F1_EXT_LOOKUP_VAL * F1_EXT_LOOKUP_VAL_L | E102: CHAR_TYPE_CD = ‘CMMLSVAR’ BUS_OBJ_CD = ‘CM-MLServiceArea’ | F102: Left Join *** This will be introduced on 25.1 Release | G102: Mobile Lite Details

Sheet D1_DVC
B1: Summary
B2: Table Name: D1_DVC
B3: Justification: | C3: =Summary!O127 -> This table records information about a Device. It is useful for Clients as it allows them to view information of existing Device in C2M. Where they're located or if they're installed at a Service Point. | L3: Domain -> Device
B4: Designer: | C4: =Summary!I127 -> Lennice | L4: D1_DVC - display | N4: done
L5: D1_DVC_CFG - display | N5: done
A6: Table Name | B6: Field Name | C6: Field Description | D6: Related Table/ Xpath | E6: Filter | F6: Join Type | G6: Designer Notes | H6: Reviewer Notes | L6: D1_INSTALL_EVT - display | N6: done
A7: D1_DVC | B7: D1_DEVICE_ID | C7: Device ID | D7: N/A | F7: N/A | L7: D1_SP - link only | N7: done
A8: D1_DVC | B8: DEVICE_TYPE_CD | C8: Device Type | D8: * D1_DVC_TYPE * D1_DVC_TYPE_L | F8: Inner Join | L8: CI_PREM - display | N8: done
A9: D1_DVC | B9: BUS_OBJ_CD | C9: Business Object | D9: * F1_BUS_OBJ_L | F9: Inner Join | L9: CI_ACCT - link
A10: D1_DVC | B10: MANUFACTURER_CD | C10: Manufacturer | D10: * D1_MANUFACTURER_L | F10: Left Outer | L10: CI_PER_NAME - display
A11: D1_DVC | B11: D1_MODEL_CD | C11: Model | D11: * D1_MODEL_L | F11: Left Outer | L11: D1_SP_CONTACT | N11: n/a
A12: D1_DVC | B12: D1_SPR_CD | C12: Service Provider | D12: D1_SPR_L | F12: Left Outer
A13: D1_DVC | B13: IN_DATA_SHIFT_FLG | C13: Incoming Data Shift | D13: * CI_LOOKUP_VAL_L | F13: Left Outer
A14: D1_DVC | B14: BO_STATUS_CD | C14: Status | D14: * F1_BUS_OBJ_STATUS_L | F14: Inner Join
A15: D1_DVC | B15: STATUS_UPD_DTTM | C15: Status Date/Time | D15: N/A | F15: N/A | L15: Change to MEASUREMENT
A16: D1_DVC | B16: BO_STATUS_REASON_CD | C16: Status Reason | D16: * F1_BUS_OBJ_STATUS_RSN_L | F16: Left Outer | L16: D1_DVC
A17: D1_DVC | B17: CRE_DTTM | C17: Create Date/Time | D17: N/A | F17: N/A | L17: D1_DVC_CFG
A18: D1_DVC | B18: BO_DATA_AREA | C18: Business Object Data Area | D18: N/A | F18: N/A | L18: D1_DVC_CFG_CHAR --remove
A19: D1_DVC | B19: VERSION | C19: Version | D19: N/A | F19: N/A | L19: D1_INSTALL_EVT - link only
A20: D1_DVC | B20: ARMING_REQ_FLG | C20: Arming Required | D20: * CI_LOOKUP_VAL_L | E20: Field = ARMING_REQ_FLG | F20: Left Outer | L20: D1_MEASR_COMP - display
A21: D1_DVC | B21: HEAD_END_REGISTR_STATUS_FLG | C21: Head-End Registration Status | D21: * CI_LOOKUP_VAL_L | E21: Field = HEAD_END_REGISTR_STATUS_FLG | F21: Left Outer | L21: D1_MSRMT - display
A22: D1_DVC | B22: D1_CMD_SET_CD | C22: Command Set | D22: * D1_COMMAND_SET_L | F22: Left Outer
A23: D1_DVC | B23: ACCESS_GRP_CD | C23: Access Group | D23: * CI_ACC_GRP_L | F23: Left Outer | L23: Device Events
B24: BO_STATUS_CD | C24: Status | D24: * F1_BUS_OBJ_STATUS_L * latestBoStatus | F24: Left Outer | G24: This information is stored on BO_DATA_AREA. Not all records have this value | L24: D1_DVC_EVT -display
B25: RETIREMENT_DTTM | C25: Retirement Date/Time | D25: * retirementDateTime | F25: Left Outer | G25: This information is stored on BO_DATA_AREA. Not all records have this value | L25: D1_DVC - display
A26: D1_DVC_IDENTIFIER | B26: DVC_ID_TYPE_FLG | C26: Device Identifier Type | D26: * CI_LOOKUP_VAL_L | E26: Field = DVC_ID_TYPE_FLG | F26: Inner Join
A27: D1_DVC_IDENTIFIER | B27: ID_VALUE | C27: Identifier Value | D27: * D1_DVC_IDENTIFIER | E27: DVC_ID_TYPE_FLG = D1BN | F27: Inner Join | L27: MDM Usage - not needed included in CI_BSEG_SQ Domain
A28: D1_DVC_CFG | B28: DEVICE_CONFIG_ID | C28: Device Configuration | D28: * D1_DVC | E28: D1_DEVICE_ID | F28: Inner Join | G28: Retrieve using Device Id | L28: D1_USAGE
A29: D1_DVC_CFG | B29: DEVICE_CONFIG_TYPE_CD | C29: Device Configuration Type | D29: * D1_DVC_CFG_TYPE_L | F29: Inner Join | L29: C1_USAGE
A30: D1_DVC_CFG | B30: EFF_DTTM | C30: Effective Date/Time | F30: Inner Join | L30: CI_BSEG
A31: D1_DVC_CFG | B31: BO_STATUS_CD | C31: Status | D31: * F1_BUS_OBJ | F31: Inner Join | L31: D1_USAGE_PERIOD_SQ
A32: D1_INSTALL_EVT | B32: INSTALL_EVT_ID | C32: Install Event ID | D32: * D1_DVC_CFG | E32: DEVICE_CONFIG_ID | F32: Left Outer | G32: Retrieve using Device Config Id | L32: D1_USAGE_EXCP
A33: D1_INSTALL_EVT | B33: BO_STATUS_CD | C33: Status Date/Time | D33: * F1_BUS_OBJ_STATUS_L | E33: BUS_OBJ_CD in D1-ItemInstallEvent,D1-ManualMeterInstallEvent,D1-SmartMeterInstallEvent | F33: Left Outer | G33: Retrieve using Device Config Id
A34: D1_INSTALL_EVT | B34: D1_INSTALL_DTTM | C34: Install Date/Time | G34: Retrieve the latest install date
A35: D1_INSTALL_EVT | B35: D1_REMOVAL_DTTM | C35: Removal Date/Time | G35: Retrieve the latest removal date | L35: D1_SP - TBD check if can be included on the Customer Information
L36: D1_US
L37: D1_SP_CONTACT - add to device
A38: FROM JACOB | L38: D1_SP_IDENTIFIER
A39: D1_INSTALL_EVT | B39: ARM_STAT_FLG | C39: Arming Status | D39: N/A | F39: N/A | L39: D1_INSTALL_EVT - to display
A40: D1_INSTALL_EVT | B40: BO_DATA_AREA | C40: Business Object Data Area | D40: N/A | F40: N/A
A41: D1_INSTALL_EVT | B41: BO_STATUS_CD | C41: Status | D41: N/A | F41: N/A
A42: D1_INSTALL_EVT | B42: BO_STATUS_REASON_CD | C42: Status Reason | D42: N/A | F42: N/A | L42: D1_US - TBD for now
A43: D1_INSTALL_EVT | B43: BUS_OBJ_CD | C43: Business Object | D43: N/A | F43: N/A | L43: D1_US_IDENTIFIER
A44: D1_INSTALL_EVT | B44: CRE_DTTM | C44: Create Date/Time | D44: N/A | F44: N/A | L44: D1_US_CONTACT
A45: D1_INSTALL_EVT | B45: D1_INSTALL_DTTM | C45: Installation Date/Time | D45: N/A | F45: N/A | L45: D1_US_SP
A46: D1_INSTALL_EVT | B46: D1_REMOVAL_DTTM | C46: Removal Date/Time | D46: N/A | F46: N/A | L46: CI_SA
A47: D1_INSTALL_EVT | B47: D1_SP_ID | C47: Service Point ID | D47: D1_SP | F47: Left Outer | L47: D1_USAGE
A48: D1_INSTALL_EVT | B48: DEVICE_CONFIG_ID | C48: Device Configuration | D48: N/A | F48: N/A
A49: D1_INSTALL_EVT | B49: INSTALLATION_CONST | C49: Installation Constant | D49: N/A | F49: N/A | L49: D1_USAGE_EXCP
A50: D1_INSTALL_EVT | B50: INSTALL_EVT_ID | C50: Install Event ID | D50: N/A | F50: N/A | L50: D1_USAGE_EXCP_CHAR - need to be verified
A51: D1_INSTALL_EVT | B51: STATUS_UPD_DTTM | C51: Status Date/Time | D51: N/A | F51: N/A
A52: D1_DVC_CFG | B52: BO_DATA_AREA | C52: Business Object Data Area | D52: N/A | F52: N/A | L52: INSTALL EVT - not needed included in Measurement Domain
A53: D1_DVC_CFG | B53: BO_STATUS_CD | C53: Status | D53: N/A | F53: N/A | L53: D1_INSTALL_EVT
A54: D1_DVC_CFG | B54: BO_STATUS_REASON_CD | C54: Status Reason | D54: N/A | F54: N/A | L54: D1_DVC_IDENTIFIER
A55: D1_DVC_CFG | B55: BUS_OBJ_CD | C55: Business Object | D55: N/A | F55: N/A | L55: D1_DVC_CFG
A56: D1_DVC_CFG | B56: CRE_DTTM | C56: Create Date/Time | D56: N/A | F56: N/A | L56: D1_DVC
A57: D1_DVC_CFG | B57: D1_DEVICE_ID | C57: Device ID | D57: D1_DVC | F57: Left Outer | L57: D1_SP
A58: D1_DVC_CFG | B58: DEVICE_CONFIG_ID | C58: Device Configuration | D58: D1_INSTALL_EVT | F58: Right Outer | L58: D1_MEASR_COMP
A59: D1_DVC_CFG | B59: DEVICE_CONFIG_TYPE_CD | C59: Device Configuration Type | D59: D1_DVC_CFG_L | F59: Inner Join
A60: D1_DVC_CFG | B60: EFF_DTTM | C60: Effective Date/Time | D60: N/A | F60: N/A | L60: IMD - remove
A61: D1_DVC_CFG | B61: STATUS_UPD_DTTM | C61: Status Date/Time | D61: N/A | F61: N/A | L61: D1_INIT_MSRMT_DATA
A62: D1_DVC_CFG | B62: TIME_ZONE_CD | C62: Time Zone | D62: N/A | F62: N/A | L62: D1_MEASR_COMP
A63: D1_DVC_CFG | B63: VERSION | C63: Version | D63: N/A | F63: N/A | L63: D1_VEE_EXCP - on a separate domain
A64: D1_DVC | B64: ACCESS_GRP_CD | C64: Access Group | D64: N/A | F64: N/A
A65: D1_DVC | B65: ARMING_REQ_FLG | C65: Arming Required | D65: N/A | F65: N/A | L65: D1_MEASR_COMP - not needed included in Measurement Domain
A66: D1_DVC | B66: BO_DATA_AREA | C66: Business Object Data Area | D66: N/A | F66: N/A | L66: D1_INSTALL_EVT
A67: D1_DVC | B67: BO_STATUS_CD | C67: Status | D67: N/A | F67: N/A | L67: D1_DVC_CFG
A68: D1_DVC | B68: BO_STATUS_REASON_CD | C68: Status Reason | D68: N/A | F68: N/A | L68: D1_DVC_IDENTIFIER
A69: D1_DVC | B69: BUS_OBJ_CD | C69: Business Object | D69: N/A | F69: N/A | L69: D1_SP
A70: D1_DVC | B70: CRE_DTTM | C70: Create Date/Time | D70: N/A | F70: N/A | L70: D1_MSRMT
A71: D1_DVC | B71: D1_CMD_SET_CD | C71: Command Set | D71: N/A | F71: N/A
A72: D1_DVC | B72: D1_DEVICE_ID | C72: Device ID | D72: N/A | F72: N/A
A73: D1_DVC | B73: D1_MODEL_CD | C73: Model | D73: N/A | F73: N/A | L73: D1_MSRMT - not needed included in Measurement Domain
A74: D1_DVC | B74: D1_SPR_CD | C74: Service Provider | D74: N/A | F74: N/A | L74: D1_MSRMT
A75: D1_DVC | B75: DEVICE_TYPE_CD | C75: Device Type | D75: N/A | F75: N/A | L75: D1_INIT_MSRMT_DATA
A76: D1_DVC | B76: HEAD_END_REGISTR_STATUS_FLG | C76: Head-End Registration Status | D76: N/A | F76: N/A
A77: D1_DVC | B77: IN_DATA_SHIFT_FLG | C77: Incoming Data Shift | D77: N/A | F77: N/A | L77: D1_MSRMT_LOG - not needed included in Measurement Domain
A78: D1_DVC | B78: MANUFACTURER_CD | C78: Manufacturer | D78: N/A | F78: N/A | L78: D1_MSRMT
A79: D1_DVC | B79: STATUS_UPD_DTTM | C79: Status Date/Time | D79: N/A | F79: N/A | L79: D1_INIT_MSRMT_DATA
A80: D1_DVC | B80: VERSION | C80: Version | D80: N/A | F80: N/A
A82: D1_SP | B82: TIME_ZONE_CD | C82: Time Zone | D82: * CI_TIME_ZONE_L | F82: Inner Join
A83: D1_SP | B83: ACCESS_GRP_CD | C83: Access Group | D83: *CI_ACC_GRP_L | F83: Left Join
A84: D1_SP | B84: COUNTRY | C84: Country | D84: * CI_COUNTRY_L | F84: Inner Join
A85: D1_SP | B85: POSTAL | C85: Postal | D85: N/A | F85: N/A
A86: D1_SP | B86: ADDRESS1 | C86: Address | D86: N/A | F86: N/A
A87: D1_SP | B87: ADDRESS1_UPPER | C87: Address Line 1 Upper Case | D87: N/A | F87: N/A
A88: D1_SP | B88: ADDRESS2 | C88: Address 2 | D88: N/A | F88: N/A
A89: D1_SP | B89: ADDRESS3 | C89: Address 3 | D89: N/A | F89: N/A
A90: D1_SP | B90: ADDRESS4 | C90: Address 4 | D90: N/A | F90: N/A
A91: D1_SP | B91: CITY | C91: City | D91: N/A | F91: N/A
A92: D1_SP | B92: CITY_UPPER | C92: City Upper Case | D92: N/A | F92: N/A
... A109: D1_SP | B109: DISCONN_LOC_FLG | C109: Disconnect Location | D109: * CI_LOOKUP_VAL * CI_LOOKUP_VAL_L | F109: Left Join
A110: D1_SP | B110: D1_SP_ID | C110: Service Point ID | D110: * D1_INSTALL_EVT | E110: D1_SP_ID | F110: Inner Join
A111: D1_SP | B111: D1_GEO_LONG | C111: Geographic Longitude | D111: N/A | F111: N/A
A112: D1_SP | B112: MSRMT_CYC_RTE_SEQ | C112: Sequence | D112: N/A | F112: N/A
A113: D1_SP | B113: DIVISION_CD | C113: Division | D113: D1_DIVISION_L | F113: Left Join
A114: D1_SP | B114: MSRMT_CYC_RTE_CD | C114: Route | D114: D1_MSRMT_CYC_RTE_L | F114: Left Join
A115: - | B115: D1_ABOLISH_DT | C115: Abolish Date | D115: N/A | F115: N/A
A116: D1_SP | B116: D1_SP_TYPE_CD | C116: Service Point Type | D116: * D1_SP_TYPE * D1_SP_TYPE_L | F116: Inner Join
A117: - | B117: D1_INSTALL_DT | C117: Install Date | D117: N/A | F117: N/A
...

Sheet Measurement
A4: Table Name | B4: Field Name | C4: Field Description | D4: Related Table/ Xpath | E4: Filter | F4: Join Type | G4: Designer Notes | H4: Reviewer Notes
A5: D1_DVC | B5: D1_DEVICE_ID | C5: Device ID | D5: N/A | F5: N/A
A6: D1_DVC | B6: DEVICE_TYPE_CD | C6: Device Type | D6: * D1_DVC_TYPE * D1_DVC_TYPE_L | F6: Inner Join
A7: D1_DVC | B7: BUS_OBJ_CD | C7: Business Object | D7: * F1_BUS_OBJ_L | F7: Inner Join
A8: D1_DVC | B8: MANUFACTURER_CD | C8: Manufacturer | D8: * D1_MANUFACTURER_L | F8: Left Outer
A9: D1_DVC | B9: D1_MODEL_CD | C9: Model | D9: * D1_MODEL_L | F9: Left Outer
A10: D1_DVC | B10: D1_SPR_CD | C10: Service Provider | D10: D1_SPR_L | F10: Left Outer
A11: D1_DVC | B11: IN_DATA_SHIFT_FLG | C11: Incoming Data Shift | D11: * CI_LOOKUP_VAL_L | F11: Left Outer
A12: D1_DVC | B12: BO_STATUS_CD | C12: Status | D12: * F1_BUS_OBJ_STATUS_L | F12: Inner Join
A13: D1_DVC | B13: STATUS_UPD_DTTM | C13: Status Date/Time | D13: N/A | F13: N/A
A14: D1_DVC | B14: BO_STATUS_REASON_CD | C14: Status Reason | D14: * F1_BUS_OBJ_STATUS_RSN_L | F14: Left Outer
A15: D1_DVC | B15: CRE_DTTM | C15: Create Date/Time | D15: N/A | F15: N/A
A16: D1_DVC | B16: BO_DATA_AREA | C16: Business Object Data Area | D16: N/A | F16: N/A
A17: D1_DVC | B17: VERSION | C17: Version | D17: N/A | F17: N/A
A18: D1_DVC | B18: ARMING_REQ_FLG | C18: Arming Required | D18: * CI_LOOKUP_VAL_L | E18: Field = ARMING_REQ_FLG | F18: Left Outer
A19: D1_DVC | B19: HEAD_END_REGISTR_STATUS_FLG | C19: Head-End Registration Status | D19: * CI_LOOKUP_VAL_L | E19: Field = HEAD_END_REGISTR_STATUS_FLG | F19: Left Outer
A20: D1_DVC | B20: D1_CMD_SET_CD | C20: Command Set | D20: * D1_COMMAND_SET_L | F20: Left Outer
A21: D1_DVC | B21: ACCESS_GRP_CD | C21: Access Group | D21: * CI_ACC_GRP_L | F21: Left Outer
B22: BO_STATUS_CD | C22: Status | D22: * F1_BUS_OBJ_STATUS_L * latestBoStatus | F22: Left Outer | G22: This information is stored on BO_DATA_AREA. Not all records have this value
B23: RETIREMENT_DTTM | C23: Retirement Date/Time | D23: * retirementDateTime | F23: Left Outer | G23: This information is stored on BO_DATA_AREA. Not all records have this value
A24: D1_DVC_CFG | B24: DEVICE_CONFIG_ID | C24: Device Configuration | D24: N/A | F24: N/A
A25: D1_DVC_CFG | B25: DEVICE_CONFIG_TYPE_CD | C25: Device Configuration Type | D25: * D1_DVC_CFG_TYPE * D1_DVC_CFG_TYPE_L | F25: Inner Join
A26: D1_DVC_CFG | B26: BUS_OBJ_CD | C26: Business Object | D26: F1_BUS_OBJ_L | F26: Inner Join
A27: D1_DVC_CFG | B27: D1_DEVICE_ID | C27: Device ID | D27: * D1_DVC | F27: Inner Join
A28: D1_DVC_CFG | B28: EFF_DTTM | C28: Effective Date/Time | D28: N/A | F28: N/A
A29: D1_DVC_CFG | B29: TIME_ZONE_CD | C29: Time Zone | D29: * CI_TIME_ZONE_L | F29: Inner Join
A30: D1_DVC_CFG | B30: BO_STATUS_CD | C30: Status | D30: * F1_BUS_OBJ_STATUS_L | F30: Inner Join | H30: Adhoc Filter
A31: D1_DVC_CFG | B31: STATUS_UPD_DTTM | C31: Status Date/Time | D31: N/A | F31: N/A
A32: D1_DVC_CFG | B32: BO_STATUS_REASON_CD | C32: Status Reason | D32: * F1_BUS_OBJ_STATUS_RSN_L | F32: Left Outer
A33: D1_DVC_CFG | B33: CRE_DTTM | C33: Create Date/Time | D33: N/A | F33: N/A
A34: D1_DVC_CFG | B34: BO_DATA_AREA | C34: Business Object Data Area | D34: N/A | F34: N/A | G34: No element is stored on this field.
A35: D1_DVC_CFG | B35: VERSION | C35: Version | D35: N/A | F35: N/A
A36: D1_INSTALL_EVT | B36: INSTALL_EVT_ID | C36: Install Event ID | D36: N/A | F36: N/A
A37: D1_INSTALL_EVT | B37: DEVICE_CONFIG_ID | C37: Device Configuration | D37: * D1_DVC_CFG | E37: INSTALL_EVT_ID | F37: Inner
A38: D1_INSTALL_EVT | B38: INSTALLATION_CONST | C38: Installation Constant | D38: N/A | F38: N/A
A39: D1_INSTALL_EVT | B39: BUS_OBJ_CD | C39: Business Object | D39: * F1_BUS_OBJ_L | F39: Inner Join
A40: D1_INSTALL_EVT | B40: BO_STATUS_CD | C40: Status | D40: * F1_BUS_OBJ_STATUS_L | E40: BO_STATUS_CD IN ('ON','CONN-COMM') | F40: Inner Join | G40: This would retrieve all the devices that were installed/removed to an SP | H40: Adhoc Filter
A41: D1_INSTALL_EVT | B41: BO_STATUS_REASON_CD | C41: Status Reason | D41: * F1_BUS_OBJ_STATUS_RSN_L | F41: Left Join
A42: D1_INSTALL_EVT | B42: STATUS_UPD_DTTM | C42: Status Date/Time | D42: N/A | F42: N/A
A43: D1_INSTALL_EVT | B43: CRE_DTTM | C43: Create Date/Time | D43: N/A | F43: N/A
A44: D1_INSTALL_EVT | B44: BO_DATA_AREA | C44: Business Object Data Area | D44: N/A | F44: N/A | G44: Retrieve the Removal Type, Crew from the CLOB that could be used as reference
A45: BODA_VIEW | B45: EVT_DTTM | C45: Date/Time | D45: eventDateTime
A46: BODA_VIEW | B46: BO_STATUS_CD | C46: Status | D46: latestBoStatus
A47: BODA_VIEW | B47: REMOVAL_TYPE_FLG | C47: Removal Type | D47: * CI_LOOKUP_VAL_L | E47: Field = REMOVAL_TYPE_FLG | G47: possible not to be used
A48: BODA_VIEW | B48: CREW
A49: D1_INSTALL_EVT | B49: VERSION | C49: Version | D49: N/A | F49: N/A
A50: D1_INSTALL_EVT | B50: D1_SP_ID | C50: Service Point ID | D50: * D1_SP | E50: INSTALL_EVT_ID | F50: Inner Join
A51: D1_INSTALL_EVT | B51: ARM_STAT_FLG | C51: Arming Status | D51: N/A | F51: N/A
A52: D1_INSTALL_EVT | B52: D1_INSTALL_DTTM | C52: Installation Date/Time | D52: N/A | F52: N/A
A53: D1_INSTALL_EVT | B53: D1_REMOVAL_DTTM | C53: Removal Date/Time | D53: N/A | F53: N/A
A54: D1_MEASR_COMP | B54: ACCESS_GRP_CD | C54: Access Group
A55: D1_MEASR_COMP | B55: ADJ_LATEST_MSRMT_DTTM | C55: Adjust Latest Measurement Date/Time
A56: D1_MEASR_COMP | B56: ATTR_VAL_ID | C56: Attribute Value ID | D56: * D1_ATTR_VAL | E56: MEASR_COMP_ID | F56: Left Join
A57: D1_MEASR_COMP | B57: BO_DATA_AREA | C57: Business Object Data Area
A58: To check | B58: READ_OUT_TYPE_FLG | D58: * CI_LOOKUP_VAL * CI_LOOKUP_VAL_L | F58: Left Join
A59: To check | B59: D1_TOLERANCE
A60: To check | B60: IGNORE_INST_CONST_FLG | D60: * CI_LOOKUP_VAL * CI_LOOKUP_VAL_L | F60: Left Join
A61: D1_MEASR_COMP | B61: BO_STATUS_CD | C61: Status | D61: * F1_BUS_OBJ_STATUS_L
A62: D1_MEASR_COMP | B62: BO_STATUS_REASON_CD | C62: Status Reason | D62: * F1_BUS_OBJ_STATUS_RSN_L | F62: Left Join
A63: D1_MEASR_COMP | B63: BUS_OBJ_CD | C63: Business Object | D63: * F1_BUS_OBJ_L | F63: Inner Join
A64: D1_MEASR_COMP | B64: CRE_DTTM | C64: Create Date/Time
A65: D1_MEASR_COMP | B65: D1_FULL_SCALE | C65: Full Scale
A66: D1_MEASR_COMP | B66: D1_NBR_OF_DGTS_LFT | C66: Number of Digits Left
A67: D1_MEASR_COMP | B67: D1_NBR_OF_DGTS_RGT | C67: Number of Digits Right
A68: D1_MEASR_COMP | B68: D1_READ_SEQ | C68: Read Sequence
A69: D1_MEASR_COMP | B69: DEVICE_CONFIG_ID | C69: Device Configuration | D69: * D1_DVC_CFG | E69: INSTALL_EVT_ID | F69: Inner
A70: D1_MEASR_COMP | B70: LATEST_MSRMT_DTTM | C70: Latest Measurement Date/Time
A71: D1_MEASR_COMP | B71: MEASR_COMP_ID | C71: Measuring Component ID
A72: D1_MEASR_COMP | B72: MEASR_COMP_MULTIPLIER | C72: Measuring Component Multiplier
A73: D1_MEASR_COMP | B73: MEASR_COMP_TYPE_CD | C73: Measuring Component Type | D73: * D1_MEASR_COMP_TYPE | E73: MEASR_COMP_ID | F73: Inner
A74: D1_MEASR_COMP | B74: MEASR_COMP_USAGE_FLG | C74: How To Use
A75: D1_MEASR_COMP | B75: MOST_RECENT_MSRMT_DTTM | C75: Most Recent Read Date/Time
A76: D1_MEASR_COMP | B76: MOST_RECENT_MSRMT_READING_COND | C76: Most Recent Read Condition
A77: D1_MEASR_COMP | B77: MOST_RECENT_MSRMT_READING_VAL | C77: Most Recent Read Value
A78: D1_MEASR_COMP | B78: MOST_RECENT_NON_EST_MSRMT_DTTM | C78: Most Recent Non Estimated Read Date/Time
A79: D1_MEASR_COMP | B79: STATUS_UPD_DTTM | C79: Status Date/Time
A80: D1_MEASR_COMP | B80: TIME_ZONE_CD | C80: Time Zone | D80: * CI_TIME_ZONE_L | F80: Left Join
A81: D1_MEASR_COMP | B81: USER_ID | C81: User | D81: * SC_USER | F81: Left Join
A82: D1_MEASR_COMP | B82: VERSION | C82: Version
A83: D1_MSRMT | B83: BO_STATUS_CD | C83: Status | D83: * F1_BUS_OBJ_STATUS_L | F83: Inner Join
A84: D1_MSRMT | B84: BUS_OBJ_CD | C84: Business Object | D84: * F1_BUS_OBJ_L | F84: Inner Join
A85: D1_MSRMT | B85: COMBINED_MULTIPLIER | C85: Combined Multiplier
A86: D1_MSRMT | B86: CRE_DTTM | C86: Create Date/Time
A87: D1_MSRMT | B87: LAST_UPDATE_DTTM | C87: Last Update Timestamp
A88: D1_MSRMT | B88: MEASR_COMP_ID | C88: Measuring Component ID | D88: * D1_MEASR_COMP | E88: MEASR_COMP_ID | F88: Inner Join
A89: D1_MSRMT | B89: MSRMT_COND_FLG | C89: Condition
A90: D1_MSRMT | B90: MSRMT_DTTM | C90: Measurement Date/Time
A91: D1_MSRMT | B91: MSRMT_LOCAL_DTTM | C91: Local Date/Time
A92: D1_MSRMT | B92: MSRMT_USE_FLG | C92: Measurement Use
A93: D1_MSRMT | B93: MSRMT_VAL | C93: Measurement
A94: D1_MSRMT | B94: MSRMT_VAL1 | C94: Value 1
A95: D1_MSRMT | B95: MSRMT_VAL10 | C95: Value 10
A96: D1_MSRMT | B96: MSRMT_VAL2 | C96: Value 2
A97: D1_MSRMT | B97: MSRMT_VAL3 | C97: Value 3
A98: D1_MSRMT | B98: MSRMT_VAL4 | C98: Value 4
A99: D1_MSRMT | B99: MSRMT_VAL5 | C99: Value 5
A100: D1_MSRMT | B100: MSRMT_VAL6 | C100: Value 6
... A110: D1_MSRMT | B110: VERSION | C110: Version

Sheet D1_DVC_CFG
B1: Summary
B2: Table Name: D1_MSRMT
B3: Justification: | C3: =Summary!O128 -> Device configurations represent specific configurations of a device as of a certain time. During the life of a device it can have different configuration (effective-dated). A device configuration can have one or more measuring component associated with it. It is useful for Clients as it allows them to easily access and extract the information. These includes Install Event and Measuring Component and Device.
B4: Designer | C4: =Summary!I128 -> Lennice
A6: Table Name | B6: Field Name | C6: Field Description | D6: Related Table/ Xpath | E6: Filter | F6: Join Type | G6: Designer Notes | H6: Reviewer Notes
A7: D1_DVC_CFG | B7: DEVICE_CONFIG_ID | C7: Device Configuration | D7: N/A | F7: N/A
A8: D1_DVC_CFG | B8: DEVICE_CONFIG_TYPE_CD | C8: Device Configuration Type | D8: * D1_DVC_CFG_TYPE * D1_DVC_CFG_TYPE_L | F8: Inner Join
A9: D1_DVC_CFG | B9: BUS_OBJ_CD | C9: Business Object | D9: F1_BUS_OBJ_L | F9: Inner Join
A10: D1_DVC_CFG | B10: D1_DEVICE_ID | C10: Device ID | D10: * D1_DVC | F10: Inner Join
A11: D1_DVC_CFG | B11: EFF_DTTM | C11: Effective Date/Time | D11: N/A | F11: N/A
A12: D1_DVC_CFG | B12: TIME_ZONE_CD | C12: Time Zone | D12: * CI_TIME_ZONE_L | F12: Inner Join
A13: D1_DVC_CFG | B13: BO_STATUS_CD | C13: Status | D13: * F1_BUS_OBJ_STATUS_L | F13: Inner Join
A14: D1_DVC_CFG | B14: STATUS_UPD_DTTM | C14: Status Date/Time | D14: N/A | F14: N/A
A15: D1_DVC_CFG | B15: BO_STATUS_REASON_CD | C15: Status Reason | D15: * F1_BUS_OBJ_STATUS_RSN_L | F15: Left Outer
A16: D1_DVC_CFG | B16: CRE_DTTM | C16: Create Date/Time | D16: N/A | F16: N/A
A17: D1_DVC_CFG | B17: BO_DATA_AREA | C17: Business Object Data Area | D17: N/A | F17: N/A | G17: No element is stored on this field.
A18: D1_DVC_CFG | B18: VERSION | C18: Version | D18: N/A | F18: N/A
A19: D1_DVC_CFG_CHAR | B19: D1_DEVICE_ID | C19: Device ID | D19: * D1_DVC
A20: D1_DVC_CFG_CHAR | B20: D1_DC_EXTERNAL_ID | C20: External Id | D20: * D1_DVC_CFG_CHAR | E20: CHAR_TYPE_CD = ‘D1-EXTID’ | F20: Left Outer | G20: Found data in City Corp and Ellensburg
A21: D1_DVC_CFG_CHAR | B21: D1_MDM_DC_EXTERNAL_ID | C21: MDM External Id | D21: * D1_DVC_CFG_CHAR | E21: CHAR_TYPE_CD = ‘D1-EXMID’ | F21: Left Outer
A22: D1_INSTALL_EVT | B22: INSTALL_EVT_ID | C22: Install Event Id | D22: * D1_INSTALL_EVT | E22: DEVICE_CONFIG_ID | F22: Left Outer
A23: D1_INSTALL_EVT | B23: D1_SP_ID | C23: Service Point Id | D23: * D1_INSTALL_EVT | F23: Inner Join
A24: D1_INSTALL_EVT | B24: BO_STATUS_CD | C24: Status | D24: * D1_INSTALL_EVT | E24: BO_STATUS_CD IN ('ON','CONN-COMM') | F24: Inner Join | G24: This filter is only for the installed device on the SP at the given date. Other filters will be included in the D1_INSTALL_EVT domain
A25: D1_MEASR_COMP | B25: MEASR_COMP_ID | C25: Measuring Component ID | D25: * D1_MEASR_COMP | E25: DEVICE_CONFIG_ID | F25: Inner Join | G25: This is dependent if the Install Event is Connected/Commissioned or ON
A26: D1_MEASR_COMP | B26: MEASR_COMP_TYPE_CD | C26: Measuring Component Type | D26: * D1_MEASR_COMP_TYPE_L | F26: Inner Join
A27: D1_MEASR_COMP | B27: LATEST_MSRMT_DTTM | C27: Latest Measurement Date/Time | D27: * D1_MEASR_COMP | F27: Left Outer | G27: This would only provide the most recent non estimated read date but not the actual measurement value.
A28: D1_MEASR_COMP | B28: MOST_RECENT_NON_EST_MSRMT_DTTM | C28: Most Recent Non Estimated Read Date/Time | D28: * D1_MEASR_COMP | F28: Left Outer | G28: This would only provide the most recent non estimated read date but not the actual measurement value.
A29: D1_MSRMT | B29: MEASR_COMP_ID | C29: Measuring Component ID | D29: * D1_MEASR_COMP | E29: MEASR_COMP_ID | F29: Left Outer
A30: D1_MSRMT | B30: MSRMT_DTTM | C30: Measurement Date/Time | D30: * D1_MSRMT | E30: MSRMT_LOCAL_DTTM >='LATEST_MSRMT_DTTM' | F30: Left Outer | G30: This needs to be specific as only the latest/most recent value is retrieved
A31: D1_MSRMT | B31: MSRMT_VAL | C31: Measurement | D31: * D1_MSRMT | F31: Left Outer
A32: D1_MSRMT | B32: MSRMT_COND_FLG | C32: Condition | D32: * F1_EXT_LOOKUP_VAL * F1_EXT_LOOKUP_VAL_L | E32: BUS_OBJ_CD='D1-MeasurementConditionLookup' | F32: Left Outer
A35: SELECT A1.DEVICE_CONFIG_ID, A1.DEVICE_CONFIG_TYPE_CD, A1.D1_DEVICE_ID, A1.EFF_DTTM, A2.INSTALL_EVT_ID, A2.D1_SP_ID, A2.BO_STATUS_CD, A3.MEASR_COMP_ID, A3.MEASR_COMP_TYPE_CD, A3.LATEST_MSRMT_DTTM, A3.MOST_RECENT_NON_EST_MSRMT_DTTM, A4.MSRMT_COND_FLG, A4.MSRMT_DTTM, A4.MSRMT_VAL, A4.ORIG_INIT_MSRMT_ID FROM CISADM.D1_DVC_CFG A1 JOIN CISADM.D1_INSTALL_EVT A2 ON A1.DEVICE_CONFIG_ID = A2.DEVICE_CONFIG_ID JOIN CISADM.D1_MEASR_COMP A3 ON A2.DEVICE_CONFIG_ID = A3.DEVICE_CONFIG_ID JOIN CISADM.D1_MSRMT A4 ON A3.MEASR_COMP_ID = A4.MEASR_COMP_ID WHERE A2.BO_STATUS_CD IN ('ON', 'CONN-COMM') AND A1.DEVICE_CONFIG_ID = '895680366000' AND A4.MSRMT_LOCAL_DTTM >= TO_DATE('27-APR-25', 'DD-MON-YY');

Sheet D1_DVC_EVT
B1: Summary
B2: Table Name: D1_DVC_EVT
B3: Justification | C3: =Summary!O129 -> Device events are developments that have taken place relative to a device, and can include power outages, power restorations, tampering alerts, command completions, among others.
A5: Table Name | B5: Field Name | C5: Field Description | D5: Related Table/ Xpath | E5: Filter | F5: Join Type | G5: Designer Notes | H5: Designer Notes
A6: D1_DVC_EVT | B6: DVC_EVT_ID | C6: Device Event ID | D6: N/A | F6: N/A
A7: D1_DVC_EVT | B7: DVC_EVT_TYPE_CD | C7: Device Event Type | D7: * D1_DVC_EVT_TYPE * D1_DVC_EVT_TYPE_L | F7: Inner Join
A8: D1_DVC_EVT | B8: BUS_OBJ_CD | C8: Business Object | D8: * F1_BUS_OBJ_STATUS_L | F8: Inner Join
A9: D1_DVC_EVT | B9: EXT_EVT_NAME_FLG | C9: External Event Name | D9: * CI_LOOKUP_VAL_L | E9: Field: EXT_EVT_NAME_FLG | F9: Left Outer
A10: D1_DVC_EVT | B10: D1_SPR_CD | C10: Service Provider | D10: * D1_SPR_L | F10: Inner Join
A11: D1_DVC_EVT | B11: BO_STATUS_CD | C11: Status | D11: * F1_BUS_OBJ_STATUS_L | F11: Inner Join
A12: D1_DVC_EVT | B12: STATUS_UPD_DTTM | C12: Status Date/Time | D12: N/A | F12: N/A
A13: D1_DVC_EVT | B13: BO_STATUS_REASON_CD | C13: Status Reason | D13: * F1_BUS_OBJ_STATUS_RSN_L | F13: Left Outer
A14: D1_DVC_EVT | B14: DVC_EVT_END_DTTM | C14: Device Event End Date/Time | D14: N/A | F14: N/A
A15: D1_DVC_EVT | B15: CRE_DTTM | C15: Create Date/Time | D15: N/A | F15: N/A
A16: D1_DVC_EVT | B16: VERSION | C16: Version | D16: N/A | F16: N/A
A17: D1_DVC_EVT | B17: DVC_EVT_DTTM | C17: Device Event Date/Time | D17: N/A | F17: N/A
A18: D1_DVC_EVT | B18: D1_DEVICE_ID | C18: Device ID | D18: * D1_DVC | F18: Inner Join
A19: D1_DVC_EVT | B19: ILM_DT | C19: ILM Date | D19: N/A | F19: N/A
A20: D1_DVC_EVT | B20: ILM_ARCH_SW | C20: ILM Archive Switch | D20: N/A | F20: N/A
A21: D1_DVC_EVT | B21: RETENTION_PERIOD | C21: Retention Period | D21: N/A | F21: N/A
B22: SENDER_LBL | C22: Sender | D22: * BO_DATA_AREA | G22: Inner Join if we are going to use a View to get the BO_DATA_AREA values

Sheet D1_INSTALL_EVT
A1: Summary
A2: Table Name: | B2: D1_INSTALL_EVT
A3: Justification | B3: =Summary!O135 -> The Install Event records the history of the device that has been installed or removed at a Service Point. It is useful for Clients as it allows them to easily fetch the list of Service Points and the related device history
A4: Designer | B4: =Summary!I135 -> Lennice
A6: Table Name | B6: Field Name | C6: Field Description | D6: Related Table / XPAth | E6: Filter | F6: Join Type | G6: Designer Notes | H6: Reviewer Notes | J6: SELECT A1.INSTALL_EVT_ID, A1.D1_SP_ID, A1.DEVICE_CONFIG_ID, A1.BO_STATUS_CD, A3.DEVICE_CONFIG_TYPE_CD, A2.BO_STATUS_CD, A4.MEASR_COMP_ID, A4.MEASR_COMP_TYPE_CD, A4.MOST_RECENT_MSRMT_DTTM, A4.MOST_RECENT_NON_EST_MSRMT_DTTM FROM CISADM.D1_INSTALL_EVT A1 JOIN CISADM.D1_SP A2 ON A2.D1_SP_ID = A1.D1_SP_ID JOIN CISADM.D1_DVC_CFG A3 ON A1.DEVICE_CONFIG_ID = A3.DEVICE_CONFIG_ID JOIN CISADM.D1_MEASR_COMP A4 ON A3.DEVICE_CONFIG_ID = A4.DEVICE_CONFIG_ID WHERE A1.BO_STATUS_CD IN ('ON', 'CONN-COMM', 'OFF', 'REMOVE', 'DISCONN-COMM', 'CONN-DECOMM');
A7: D1_INSTALL_EVT | B7: INSTALL_EVT_ID | C7: Install Event ID | D7: N/A | F7: N/A
A8: D1_INSTALL_EVT | B8: DEVICE_CONFIG_ID | C8: Device Configuration | D8: * D1_DVC_CFG | E8: INSTALL_EVT_ID | F8: Inner
A9: D1_INSTALL_EVT | B9: INSTALLATION_CONST | C9: Installation Constant | D9: N/A | F9: N/A
A10: D1_INSTALL_EVT | B10: BUS_OBJ_CD | C10: Business Object | D10: * F1_BUS_OBJ_L | F10: Inner Join
A11: D1_INSTALL_EVT | B11: BO_STATUS_CD | C11: Status | D11: * F1_BUS_OBJ_STATUS_L | E11: BO_STATUS_CD IN ('ON','CONN-COMM','OFF','REMOVE','DISCONN-COMM','CONN-DECOMM') | F11: Inner Join | G11: This would retrieve all the devices that were installed/removed to an SP | J11: D1_DVC_IDENTIFIER | K11: ID_VALUE | L11: Identifier Value | M11: * D1_DVC_IDENTIFIER | N11: D1_DEVICE_ID DVC_ID_TYPE_FLG = D1BN | O11: Inner Join | P11: Can be removed and only use the install event status to filter the meter related to the SP
A12: D1_INSTALL_EVT | B12: BO_STATUS_REASON_CD | C12: Status Reason | D12: * F1_BUS_OBJ_STATUS_RSN_L | F12: Left Join | J12: D1_DVC_CFG | K12: DEVICE_CONFIG_ID | L12: Device Configuration | M12: * D1_INSTALL_EVT | N12: INSTALL_EVT_ID | O12: Inner
A13: D1_INSTALL_EVT | B13: STATUS_UPD_DTTM | C13: Status Date/Time | D13: N/A | F13: N/A | J13: D1_DVC_CFG | K13: D1_DEVICE_ID | L13: Device ID | M13: * D1_DVC_CFG | N13: DEVICE_CONFIG_ID | O13: Inner Join | P13: Retrieve device using the device config from the install event table
A14: D1_INSTALL_EVT | B14: CRE_DTTM | C14: Create Date/Time | D14: N/A | F14: N/A | J14: D1_DVC | K14: D1_DEVICE_ID | L14: Device ID | M14: * D1_DVC_CFG | N14: D1_DEVICE_ID
A15: D1_INSTALL_EVT | B15: BO_DATA_AREA | C15: Business Object Data Area | D15: N/A | F15: N/A | G15: Retrieve the Removal Type, Crew from the CLOB that could be used as reference | J15: D1_DVC | K15: DEVICE_TYPE_CD | L15: Device Type | P15: Added as part of the comment in SC WS by Analytics - Working Doc
A16: VIEW | B16: EVT_DTTM | C16: Date/Time | D16: eventDateTime | J16: D1_SP | K16: D1_SP_TYPE_CD | L16: Service Point Type | M16: * D1_SP_TYPE_CD_L | N16: D1_SP_ID | O16: Inner Join
A17: VIEW | B17: BO_STATUS_CD | C17: Status | D17: latestBoStatus | J17: D1_MEASR_COMP | K17: MEASR_COMP_ID | L17: Measuring Component ID | M17: * D1_MEASR_COMP | N17: DEVICE_CONFIG_ID | O17: Inner Join | P17: This is dependent if the Install Event is Connected/Commissioned or ON
A18: VIEW | B18: REMOVAL_TYPE_FLG | C18: Removal Type | D18: * CI_LOOKUP_VAL_L | E18: Field = REMOVAL_TYPE_FLG | J18: D1_MEASR_COMP | K18: MEASR_COMP_TYPE_CD | L18: Measuring Component Type | M18: * D1_MEASR_COMP_TYPE_L | O18: Inner Join
A19: VIEW | B19: CREW | J19: D1_MEASR_COMP | K19: LATEST_MSRMT_DTTM | L19: Latest Measurement Date/Time | M19: * D1_MEASR_COMP | O19: Left Outer | P19: This would only provide the most recent non estimated read date but not the actual measurement value.
A20: D1_INSTALL_EVT | B20: VERSION | C20: Version | D20: N/A | F20: N/A | J20: D1_MEASR_COMP | K20: MOST_RECENT_NON_EST_MSRMT_DTTM | L20: Most Recent Non Estimated Read Date/Time | M20: * D1_MEASR_COMP | O20: Left Outer | P20: This would only provide the most recent non estimated read date but not the actual measurement value.
A21: D1_INSTALL_EVT | B21: D1_SP_ID | C21: Service Point ID | D21: * D1_SP | E21: INSTALL_EVT_ID | F21: Inner Join
A22: D1_INSTALL_EVT | B22: ARM_STAT_FLG | C22: Arming Status | D22: N/A | F22: N/A
A23: D1_INSTALL_EVT | B23: D1_INSTALL_DTTM | C23: Installation Date/Time | D23: N/A | F23: N/A
A24: D1_INSTALL_EVT | B24: D1_REMOVAL_DTTM | C24: Removal Date/Time | D24: N/A | F24: N/A
A25: D1_DVC_IDENTIFIER | B25: ID_VALUE | C25: Identifier Value | D25: * D1_DVC_IDENTIFIER | E25: D1_DEVICE_ID DVC_ID_TYPE_FLG = D1BN | F25: Inner Join | G25: Can be removed and only use the install event status to filter the meter related to the SP
A26: D1_DVC_CFG | B26: DEVICE_CONFIG_ID | C26: Device Configuration | D26: * D1_INSTALL_EVT | E26: INSTALL_EVT_ID | F26: Inner
A27: D1_DVC_CFG | B27: D1_DEVICE_ID | C27: Device ID | D27: * D1_DVC_CFG | E27: DEVICE_CONFIG_ID | F27: Inner Join | G27: Retrieve device using the device config from the install event table
A28: D1_DVC | B28: D1_DEVICE_ID | C28: Device ID | D28: * D1_DVC_CFG | E28: D1_DEVICE_ID
A29: D1_DVC | B29: DEVICE_TYPE_CD | C29: Device Type | G29: Added as part of the comment in SC WS by Analytics - Working Doc
A30: D1_SP | B30: D1_SP_TYPE_CD | C30: Service Point Type | D30: * D1_SP_TYPE_CD_L | E30: D1_SP_ID | F30: Inner Join
A31: D1_MEASR_COMP | B31: MEASR_COMP_ID | C31: Measuring Component ID | D31: * D1_MEASR_COMP | E31: DEVICE_CONFIG_ID | F31: Inner Join | G31: This is dependent if the Install Event is Connected/Commissioned or ON
A32: D1_MEASR_COMP | B32: MEASR_COMP_TYPE_CD | C32: Measuring Component Type | D32: * D1_MEASR_COMP_TYPE_L | F32: Inner Join
A33: D1_MEASR_COMP | B33: LATEST_MSRMT_DTTM | C33: Latest Measurement Date/Time | D33: * D1_MEASR_COMP | F33: Left Outer | G33: This would only provide the most recent non estimated read date but not the actual measurement value.
A34: D1_MEASR_COMP | B34: MOST_RECENT_NON_EST_MSRMT_DTTM | C34: Most Recent Non Estimated Read Date/Time | D34: * D1_MEASR_COMP | F34: Left Outer | G34: This would only provide the most recent non estimated read date but not the actual measurement value.

Sheet D1_INIT_MSRMT_DATA
B1: Summary
B2: Table Name: | C2: D1_INIT_MSRMT_DATA
B3: Justification | C3: =Summary!O133 -> Initial measurement data (IMD) is the term for measurement data in its initial (or raw) form. This is received from an external system or user created or system estimated in C2M. Once it's processed it will be stored as measurement(D1_MSRMT) or the IMD will be in Exception state depending on the VEE Rules setup. It is useful for Clients as it allows them to review the information of the expected number of reads uploaded to the system and how many are processed at a given period of time. Note: This table holds a lot of data as a meter can have daily IMDs loaded into C2M. The adhoc view would be used to limit it via Badge Number, Measuring Component and IMD Date.
B4: Designer | C4: =Summary!I133 -> Lennice
A6: Table | B6: Field Name | C6: Field Description | D6: Related Table | E6: Filter | F6: Join Type | G6: Designer Notes | H6: Reviewer Notes
A7: D1_INIT_MSRMT_DATA | B7: BO_STATUS_CD | C7: Status | D7: * F1_BUS_OBJ_STATUS_L | F7: Inner Join
A8: D1_INIT_MSRMT_DATA | B8: BO_STATUS_REASON_CD | C8: Status Reason | D8: * F1_BUS_OBJ_STATUS_RSN_L | F8: Left Join
A9: D1_INIT_MSRMT_DATA | B9: BUS_OBJ_CD | C9: Business Object | D9: * F1_BUS_OBJ_L | F9: Inner Join
A10: D1_INIT_MSRMT_DATA | B10: CRE_DTTM | C10: Create Date/Time
A11: D1_INIT_MSRMT_DATA | B11: D1_FROM_DTTM | C11: From Date/Time
A12: D1_INIT_MSRMT_DATA | B12: D1_TO_DTTM | C12: To Date/Time
A13: D1_INIT_MSRMT_DATA | B13: DATA_SRC_FLG | C13: Data Source | D13: * CI_LOOKUP_VAL_L | E13: Field: DATA_SRC_FLG
A14: D1_INIT_MSRMT_DATA | B14: ILM_ARCH_SW | C14: ILM Archive Switch
A15: D1_INIT_MSRMT_DATA | B15: ILM_DT | C15: ILM Date
A16: D1_INIT_MSRMT_DATA | B16: IMD_BO_DATA_AREA | C16: IMD Data Area
A17: D1_INIT_MSRMT_DATA | B17: IMD_EXT_ID | C17: External ID
A18: D1_INIT_MSRMT_DATA | B18: INIT_MSRMT_DATA_ID | C18: Initial Measurement Data ID
A19: D1_INIT_MSRMT_DATA | B19: LAST_UPDATE_DTTM | C19: Last Update Timestamp
A20: D1_INIT_MSRMT_DATA | B20: MEASR_COMP_ID | C20: Measuring Component ID | D20: * D1_MEASR_COMP | F20: Left Outer
A21: D1_INIT_MSRMT_DATA | B21: POSTVEE_BO_DATA_AREA | C21: Post VEE BO Data Area
A22: D1_INIT_MSRMT_DATA | B22: PREVEE_BO_DATA_AREA | C22: Pre VEE BO Data Area
A23: D1_INIT_MSRMT_DATA | B23: RAW_BO_DATA_AREA | C23: Raw BO Data Area
A24: D1_INIT_MSRMT_DATA | B24: RETENTION_PERIOD | C24: Retention Period
A25: D1_INIT_MSRMT_DATA | B25: STATUS_UPD_DTTM | C25: Status Date/Time
A26: D1_INIT_MSRMT_DATA | B26: TIME_ZONE_CD | C26: Time Zone | D26: * CI_TIME_ZONE_L
A27: D1_INIT_MSRMT_DATA | B27: TRACE_BO_DATA_AREA | C27: Trace BO Data Area
A28: D1_INIT_MSRMT_DATA | B28: VERSION | C28: Version
A29: D1_MEASR_COMP | B29: ACCESS_GRP_CD | C29: Access Group
A30: D1_MEASR_COMP | B30: ADJ_LATEST_MSRMT_DTTM | C30: Adjust Latest Measurement Date/Time
A31: D1_MEASR_COMP | B31: ATTR_VAL_ID | C31: Attribute Value ID
A32: D1_MEASR_COMP | B32: BO_DATA_AREA | C32: Business Object Data Area
A33: D1_MEASR_COMP | B33: BO_STATUS_CD | C33: Status
A34: D1_MEASR_COMP | B34: BO_STATUS_REASON_CD | C34: Status Reason
A35: D1_MEASR_COMP | B35: BUS_OBJ_CD | C35: Business Object
A36: D1_MEASR_COMP | B36: CRE_DTTM | C36: Create Date/Time
A37: D1_MEASR_COMP | B37: D1_FULL_SCALE | C37: Full Scale
A38: D1_MEASR_COMP | B38: D1_NBR_OF_DGTS_LFT | C38: Number of Digits Left
... A42: D1_MEASR_COMP | B42: LATEST_MSRMT_DTTM | C42: Latest Measurement Date/Time
A43: D1_MEASR_COMP | B43: MEASR_COMP_ID | C43: Measuring Component ID | D43: * D1_INIT_MSRMT_DATA | E43: MEASR_COMP_ID
A44: D1_MEASR_COMP | B44: MEASR_COMP_MULTIPLIER | C44: Measuring Component Multiplier
A45: D1_MEASR_COMP | B45: MEASR_COMP_TYPE_CD | C45: Measuring Component Type
A46: D1_MEASR_COMP | B46: MEASR_COMP_USAGE_FLG | C46: How To Use
A47: D1_MEASR_COMP | B47: MOST_RECENT_MSRMT_DTTM | C47: Most Recent Read Date/Time
A48: D1_MEASR_COMP | B48: MOST_RECENT_MSRMT_READING_COND | C48: Most Recent Read Condition
A49: D1_MEASR_COMP | B49: MOST_RECENT_MSRMT_READING_VAL | C49: Most Recent Read Value
A50: D1_MEASR_COMP | B50: MOST_RECENT_NON_EST_MSRMT_DTTM | C50: Most Recent Non Estimated Read Date/Time
A51: D1_MEASR_COMP | B51: STATUS_UPD_DTTM | C51: Status Date/Time
A52: D1_MEASR_COMP | B52: TIME_ZONE_CD | C52: Time Zone
A53: D1_MEASR_COMP | B53: USER_ID | C53: User
A54: D1_MEASR_COMP | B54: VERSION | C54: Version
A55: D1_VEE_EXCP | B55: BO_STATUS_CD | C55: Status
... A62: VEE Exception | B62: ILM_DT | C62: ILM Date
A63: VEE Exception | B63: INIT_MSRMT_DATA_ID | C63: Initial Measurement Data ID | D63: * D1_INIT_MSRMT_DATA | E63: INIT_MSRMT_DATA_ID | F63: LEFT
A64: VEE Exception | B64: MESSAGE_CAT_NBR | C64: Message Category | D64: * CI_MSG
A65: VEE Exception | B65: MESSAGE_NBR | C65: Message Number | D65: * CI_MSG
A66: VEE Exception | B66: OPEN_CLOSE_FLG | C66: Exception Status
A67: VEE Exception | B67: STATUS_UPD_DTTM | C67: Status Date/Time
A68: VEE Exception | B68: VEE_EXCP_ID | C68: VEE Exception ID
A69: VEE Exception | B69: VEE_GRP_CD | C69: VEE Group
A70: VEE Exception | B70: VEE_RULE_CD | C70: VEE Rule
A71: VEE Exception | B71: VERSION | C71: Version

Sheet D1_MEASR_COMP
B1: Summary
B2: Table Name: D1_MEASR_COMP
B3: Justification | C3: =Summary!O140 -> Measuring components are single points for which data will be received and stored in the system. Measuring components can be associated to a device or not (these are virtual or stand-alone). This is helpful for the Clients as it allows them to retrieve the Measuring Components that's either related to a SP or not used.
B4: Designer | C4: Lennice
A6: Table Name | B6: Field Name | C6: Field Description | D6: Related Table | E6: Filter | F6: Join Type | G6: Designer Notes | H6: Reviewer Notes
A7: D1_MEASR_COMP | B7: ACCESS_GRP_CD | C7: Access Group
A8: D1_MEASR_COMP | B8: ADJ_LATEST_MSRMT_DTTM | C8: Adjust Latest Measurement Date/Time
A9: D1_MEASR_COMP | B9: ATTR_VAL_ID | C9: Attribute Value ID | D9: * D1_ATTR_VAL | E9: MEASR_COMP_ID | F9: Left Join
A10: D1_MEASR_COMP | B10: BO_DATA_AREA | C10: Business Object Data Area
B11: READ_OUT_TYPE_FLG | D11: * CI_LOOKUP_VAL * CI_LOOKUP_VAL_L | F11: Left Join
B12: D1_TOLERANCE
B13: IGNORE_INST_CONST_FLG | D13: * CI_LOOKUP_VAL * CI_LOOKUP_VAL_L | F13: Left Join
A14: D1_MEASR_COMP | B14: BO_STATUS_CD | C14: Status | D14: * F1_BUS_OBJ_STATUS_L
A15: D1_MEASR_COMP | B15: BO_STATUS_REASON_CD | C15: Status Reason | D15: * F1_BUS_OBJ_STATUS_RSN_L | F15: Left Join
A16: D1_MEASR_COMP | B16: BUS_OBJ_CD | C16: Business Object | D16: * F1_BUS_OBJ_L | F16: Inner Join
A17: D1_MEASR_COMP | B17: CRE_DTTM | C17: Create Date/Time
A18: D1_MEASR_COMP | B18: D1_FULL_SCALE | C18: Full Scale
A19: D1_MEASR_COMP | B19: D1_NBR_OF_DGTS_LFT | C19: Number of Digits Left
A20: D1_MEASR_COMP | B20: D1_NBR_OF_DGTS_RGT | C20: Number of Digits Right
A21: D1_MEASR_COMP | B21: D1_READ_SEQ | C21: Read Sequence
A22: D1_MEASR_COMP | B22: DEVICE_CONFIG_ID | C22: Device Configuration | D22: * D1_DVC_CFG | E22: INSTALL_EVT_ID | F22: Inner
A23: D1_MEASR_COMP | B23: LATEST_MSRMT_DTTM | C23: Latest Measurement Date/Time
A24: D1_MEASR_COMP | B24: MEASR_COMP_ID | C24: Measuring Component ID
A25: D1_MEASR_COMP | B25: MEASR_COMP_MULTIPLIER | C25: Measuring Component Multiplier
A26: D1_MEASR_COMP | B26: MEASR_COMP_TYPE_CD | C26: Measuring Component Type | D26: * D1_MEASR_COMP_TYPE | E26: MEASR_COMP_ID | F26: Inner
A27: D1_MEASR_COMP | B27: MEASR_COMP_USAGE_FLG | C27: How To Use
A28: D1_MEASR_COMP | B28: MOST_RECENT_MSRMT_DTTM | C28: Most Recent Read Date/Time
A29: D1_MEASR_COMP | B29: MOST_RECENT_MSRMT_READING_COND | C29: Most Recent Read Condition
A30: D1_MEASR_COMP | B30: MOST_RECENT_MSRMT_READING_VAL | C30: Most Recent Read Value
A31: D1_MEASR_COMP | B31: MOST_RECENT_NON_EST_MSRMT_DTTM | C31: Most Recent Non Estimated Read Date/Time
A32: D1_MEASR_COMP | B32: STATUS_UPD_DTTM | C32: Status Date/Time
A33: D1_MEASR_COMP | B33: TIME_ZONE_CD | C33: Time Zone | D33: * CI_TIME_ZONE_L | F33: Left Join
A34: D1_MEASR_COMP | B34: USER_ID | C34: User | D34: * SC_USER | F34: Left Join
A35: D1_MEASR_COMP | B35: VERSION | C35: Version
A36: D1_INSTALL_EVT | B36: VERSION | C36: Version | D36: N/A | F36: N/A
A37: D1_INSTALL_EVT | B37: D1_SP_ID | C37: Service Point ID | D37: * D1_SP | E37: INSTALL_EVT_ID | F37: Inner Join
A38: D1_INSTALL_EVT | B38: ARM_STAT_FLG | C38: Arming Status | D38: N/A | F38: N/A
A39: D1_INSTALL_EVT | B39: D1_INSTALL_DTTM | C39: Installation Date/Time | D39: N/A | F39: N/A
A40: D1_INSTALL_EVT | B40: D1_REMOVAL_DTTM | C40: Removal Date/Time | D40: N/A | F40: N/A
A41: D1_INSTALL_EVT | B41: BO_STATUS_CD | C41: Status | D41: * F1_BUS_OBJ_STATUS_L | E41: BO_STATUS_CD IN ('ON','CONN-COMM','OFF','REMOVE','DISCONN-COMM','CONN-DECOMM') | F41: Inner Join | G41: This would retrieve all the devices that were installed/removed to an SP
A42: D1_DVC_CFG | B42: D1_DEVICE_ID | C42: Device ID | D42: * D1_DVC_CFG | E42: DEVICE_CONFIG_ID | F42: Inner Join | G42: Retrieve device using the device config from the install event table
A43: D1_DVC_IDENTIFIER | B43: ID_VALUE | C43: Identifier Value | D43: * D1_DVC_IDENTIFIER | E43: D1_DEVICE_ID DVC_ID_TYPE_FLG = D1BN | F43: Inner Join | G43: Can be removed and only use the install event status to filter the meter related to the SP
A44: D1_SP | B44: D1_SP_TYPE_CD | C44: Service Point Type | D44: * D1_SP_TYPE_CD_L | E44: D1_SP_ID | F44: Inner Join
A45: D1_SP | B45: BO_STATUS_CD | C45: Status | D45: * F1_BUS_OBJ_STATUS_L | E45: BO_STATUS_CD='ACTIVE'
A46: D1_MSRMT | B46: MEASR_COMP_ID | C46: Measuring Component ID | D46: * D1_MSRMT | E46: MEASR_COMP_ID
A47: D1_MSRMT | B47: MSRMT_COND_FLG | C47: Condition | D47: * F1_EXT_LOOKUP_VAL * F1_EXT_LOOKUP_VAL_L | E47: lookup BO: D1-MeasurementConditionLookup MSRMT_COND_FLG IN ('501000','402000' '301000') | G47: This would retrieve Regular and System Estimate and Office Estimate
A48: D1_MSRMT | B48: MSRMT_LOCAL_DTTM | C48: Local Date/Time | E48: MSRMT_LOCAL_DTTM >= :DAY OR :WEEK | G48: This filter is needed to limit the rows returned for the installed Measuring Components

Sheet D1_MSRMT
B1: Summary
B2: Table Name: D1_MSRMT
B3: Justification | C3: =Summary!O145 -> Measurements have gone through VEE(validate-edit-estimate) and is ready to be used for Usage Calculation. This is useful to Client, retrieve the information if there are Measuring Components having more Estimated Measurements against Regular.
B4: Designer | C4: Lennice
A6: Table Name | B6: Field Name | C6: Field Description | D6: Related Table | E6: Filter | F6: Join Type | G6: Designer Notes | H6: Reviewer Notes
A7: D1_MSRMT | B7: BO_STATUS_CD | C7: Status | D7: * F1_BUS_OBJ_STATUS_L | F7: Inner Join
A8: D1_MSRMT | B8: BUS_OBJ_CD | C8: Business Object | D8: * F1_BUS_OBJ_L | F8: Inner Join
A9: D1_MSRMT | B9: COMBINED_MULTIPLIER | C9: Combined Multiplier
A10: D1_MSRMT | B10: CRE_DTTM | C10: Create Date/Time
A11: D1_MSRMT | B11: LAST_UPDATE_DTTM | C11: Last Update Timestamp
A12: D1_MSRMT | B12: MEASR_COMP_ID | C12: Measuring Component ID | D12: * D1_MEASR_COMP | E12: MEASR_COMP_ID | F12: Inner Join
A13: D1_MSRMT | B13: MSRMT_COND_FLG | C13: Condition
A14: D1_MSRMT | B14: MSRMT_DTTM | C14: Measurement Date/Time
A15: D1_MSRMT | B15: MSRMT_LOCAL_DTTM | C15: Local Date/Time
A16: D1_MSRMT | B16: MSRMT_USE_FLG | C16: Measurement Use
A17: D1_MSRMT | B17: MSRMT_VAL | C17: Measurement
A18: D1_MSRMT | B18: MSRMT_VAL1 | C18: Value 1
A19: D1_MSRMT | B19: MSRMT_VAL10 | C19: Value 10
A20: D1_MSRMT | B20: MSRMT_VAL2 | C20: Value 2
A21: D1_MSRMT | B21: MSRMT_VAL3 | C21: Value 3
A22: D1_MSRMT | B22: MSRMT_VAL4 | C22: Value 4
A23: D1_MSRMT | B23: MSRMT_VAL5 | C23: Value 5
A24: D1_MSRMT | B24: MSRMT_VAL6 | C24: Value 6
... A34: D1_MSRMT | B34: VERSION | C34: Version
A35: D1_INIT_MSRMT_DATA | B35: INIT_MSRMT_DATA_ID | C35: Initial Measurement Data ID | E35: ORIG_INIT_MSRMT_ID
A36: D1_INIT_MSRMT_DATA | B36: D1_FROM_DTTM | C36: From Date/Time | D36: N/A
A37: D1_INIT_MSRMT_DATA | B37: D1_TO_DTTM | C37: To Date/Time | D37: N/A
A38: D1_INIT_MSRMT_DATA | B38: DATA_SRC_FLG | C38: Data Source | D38: * CI_LOOKUP_VAL_L | E38: Field: DATA_SRC_FLG
A39: D1_INIT_MSRMT_DATA | B39: TIME_ZONE_CD | C39: Time Zone | D39: * CI_TIME_ZONE_L
A40: D1_INIT_MSRMT_DATA | B40: BUS_OBJ_CD | C40: Business Object | D40: * F1_BUS_OBJ_L

Sheet D1_MSRMT_LOG
B1: Summary
B2: Table Name: D1_MSRMT_LOG
B3: Justification
B4: Designer | C4: Lennice
A6: Table Name | B6: Field Name | C6: Field Description | D6: Related Table | E6: Filter | F6: Join Type | G6: Designer Notes | H6: Reviewer Notes
A7: D1_MSRMT_LOG | B7: ADHOC_CHAR_VAL | C7: Adhoc Characteristic Value
A8: D1_MSRMT_LOG | B8: BO_DATA_AREA | C8: Business Object Data Area
A9: D1_MSRMT_LOG | B9: BUS_OBJ_CD | C9: Business Object | D9: * F1_BUS_OBJ_L
A10: D1_MSRMT_LOG | B10: CHAR_TYPE_CD | C10: Characteristic Type
A11: D1_MSRMT_LOG | B11: CHAR_VAL | C11: Characteristic Value
A12: D1_MSRMT_LOG | B12: CHAR_VAL_FK1 | C12: Characteristic Value FK 1
A13: D1_MSRMT_LOG | B13: CHAR_VAL_FK2 | C13: Characteristic Value FK 2
A14: D1_MSRMT_LOG | B14: CHAR_VAL_FK3 | C14: Characteristic Value FK 3
A15: D1_MSRMT_LOG | B15: CHAR_VAL_FK4 | C15: Characteristic Value FK 4
A16: D1_MSRMT_LOG | B16: CHAR_VAL_FK5 | C16: Characteristic Value FK 5
A17: D1_MSRMT_LOG | B17: DESCRLONG | C17: Detailed Description
A18: D1_MSRMT_LOG | B18: LOG_DTTM | C18: Date / Time
A19: D1_MSRMT_LOG | B19: MEASR_COMP_ID | C19: Measuring Component ID | D19: * D1_MEASR_COMP | E19: MEASR_COMP_ID
A20: D1_MSRMT_LOG | B20: MESSAGE_CAT_NBR | C20: Message Category | D20: * CI_MSG_L | E20: MESSAGE_CAT_NBR
A21: D1_MSRMT_LOG | B21: MESSAGE_NBR | C21: Message Number | D21: * CI_MSG_L | E21: MESSAGE_NBR
A22: D1_MSRMT_LOG | B22: MSRMT_DTTM | C22: Measurement Date/Time | D22: * D1_MSRMT
A23: D1_MSRMT_LOG | B23: MSRMT_LOG_ENTRY_TYPE_FLG | C23: Log Type
A24: D1_MSRMT_LOG | B24: ORIG_INIT_MSRMT_ID | C24: Initial Measurement | D24: * D1_INIT_MSRMT_DATA | E24: INIT_MSRMT_DATA_ID
A25: D1_MSRMT_LOG | B25: SEQNO | C25: Sequence
A26: D1_MSRMT_LOG | B26: USER_ID | C26: User | D26: * SC_USER | E26: USER_ID
A27: D1_MSRMT_LOG | B27: VERSION | C27: Version
A28: BO_DATA_AREA | B28: FLD_NAME | E28: fieldChange/name
A29: BO_DATA_AREA | B29: LABEL_LONG | E29: fieldChange/label
A30: BO_DATA_AREA | B30: XPATH | E30: fieldChange/xpath
A31: BO_DATA_AREA | B31: D1_BEFORE | E31: fieldChange/before
A32: BO_DATA_AREA | B32: D1_AFTER | E32: fieldChange/after
A33: BO_DATA_AREA | B33: DESCRLONG | E33: fieldChange/descrlong
A34: BO_DATA_AREA | B34: AUDIT_FLD_NAME | E34: fieldChange/mdField
A35: BO_DATA_AREA | B35: FLD_NAME | E35: fieldChange/lookupField
A36: BO_DATA_AREA | B36: FK_REF_CD | E36: fieldChange/fkRef
A37: BO_DATA_AREA | B37: ORIG_MSRMT_BO_NAME | E37: originalMeasurement/originalMeasurementBO
A38: BO_DATA_AREA | B38: ORIG_MSRMT_BO_DATA_AREA | E38: originalMeasurement/originalMeasurementBOData
A39: BO_DATA_AREA | B39: READING_VAL | E39: readingValue
A40: BO_DATA_AREA | B40: READING_COND_FLG | D40: * F1_EXT_LOOKUP_VAL * F1_EXT_LOOKUP_VAL_L | E40: BO: D1-MeasurementConditionLookup measurementCondition
A41: D1_MSRMT | B41: BO_STATUS_CD | C41: Status | D41: * F1_BUS_OBJ_STATUS_L
A42: D1_MSRMT | B42: BUS_OBJ_CD | C42: Business Object | D42: * F1_BUS_OBJ_L
A43: D1_MSRMT | B43: MEASR_COMP_ID | C43: Measuring Component ID | D43: * D1_MEASR_COMP
A44: D1_MSRMT | B44: MSRMT_VAL | C44: Measurement
A45: D1_MSRMT | B45: READING_VAL | C45: Reading Value
A46: D1_INIT_MSRMT_DATA | B46: INIT_MSRMT_DATA_ID | C46: Initial Measurement Data ID | D46: * D1_INIT_MSRMT_DATA | E46: ORIG_INIT_MSRMT_ID | G46: Use the value from the ORIG_INIT_MSRMT_ID as the INIT_MSRMT_DATA_ID

Sheet MDM Usage
B1: Summary
B2: Table Name: D1_USAGE
B3: Justification | C3: =Summary!O156 -> Usage Transactions are records of bill determinant calculations for a Usage Subscription. This is useful to the Client as it allows them to retrieve the Bill information to the usage and measurement
B4: Designer | C4: Lennice
A6: Table Name | B6: Field Name | C6: Field Description | D6: Related Table | E6: Filter | F6: Join Type | G6: Designer Notes | H6: Reviewer Notes
A7: D1_USAGE | B7: BO_STATUS_CD | C7: Status | D7: * F1_BUS_OBJ_STATUS_L
A8: D1_USAGE | B8: BO_STATUS_REASON_CD | C8: Status Reason | D8: * F1_BUS_OBJ_STATUS_RSN_L | F8: Left Join
A9: D1_USAGE | B9: BUS_OBJ_CD | C9: Business Object | D9: * F1_BUS_OBJ_L | F9: Inner Join
A10: D1_USAGE | B10: COMMENTS | C10: Comments
A11: D1_USAGE | B11: CRE_DTTM | C11: Create Date/Time
A12: D1_USAGE | B12: D1_SPR_CD | C12: Service Provider
A13: D1_USAGE | B13: D1_USAGE_ID | C13: Usage Transaction ID
A14: D1_USAGE | B14: D1_USG_CAL_TYPE_CD | C14: Usage Calculation Type | D14: * D1_USG_CAL_TYPE_L | E14: D1_USG_CAL_TYPE_CD | F14: Left Join
A15: D1_USAGE | B15: END_DTTM | C15: End Date/Time
A16: D1_USAGE | B16: ILM_ARCH_SW | C16: ILM Archive Switch
A17: D1_USAGE | B17: ILM_DT | C17: ILM Date
A18: D1_USAGE | B18: LINKED_TO_FRZN_BSEG_FLG | C18: Linked to Frozen Bill Segment
A19: D1_USAGE | B19: MSRMT_CYC_CD | C19: Measurement Cycle | D19: * D1_MSRMT_CYC_L
A20: D1_USAGE | B20: MSRMT_CYC_RTE_CD | C20: Route | D20: * D1_MSRMT_CYC_RTE_L
A21: D1_USAGE | B21: ORG_USAGE_ID | C21: Original Usage ID
A22: D1_USAGE | B22: REL_ORDER | C22: Relative Order
A23: D1_USAGE | B23: SCH_SELECTION_DT | C23: Scheduled Selection Date
A24: D1_USAGE | B24: START_DTTM | C24: Start Date/Time
A25: D1_USAGE | B25: STATUS_UPD_DTTM | C25: Status Date/Time
A26: D1_USAGE | B26: TOT_USG_TRANS_CNT | C26: Total Usage Transaction Count
A27: D1_USAGE | B27: USED_ON_BILL_FLG | C27: Used on Bill | D27: * CI_LOOKUP_VAL * CI_LOOKUP_VAL_L | E27: USED_ON_BILL_FLG | F27: Left Join
A28: D1_USAGE | B28: USG_EXT_ID | C28: Usage External ID
A29: D1_USAGE | B29: USG_GRP_CD | C29: Calculation Group | D29: * D1_USG_GRP_L | F29: Left Join
A30: D1_USAGE | B30: USG_SRC_FLG | C30: Usage Source
A31: D1_USAGE | B31: US_ID | C31: Usage Subscription | D31: * D1_US | E31: US_ID
A32: D1_USAGE | B32: VERSION | C32: Version
A33: D1_USAGE | B33: EST_THROUGH_DATE | C33: Estimate Through Date
A34: D1_USAGE | B34: PREV_USG_ID | C34: Previous Usage Transaction
A35: D1_USAGE | B35: BILL_COND_FLG | C35: Bill Condition
A36: D1_USAGE | B36: AUTO_RETRY_FLG | C36: Automated Retry
A37: D1_USAGE | B37: NEXT_RETRY_DTTM | C37: Next Retry Date/Time
A38: D1_USAGE | B38: RETRY_UNTIL_DTTM | C38: Retry Until Date/Time
A39: D1_USAGE | B39: DEFER_CALC_FLG | C39: Defer Calculation
A40: D1_USAGE | B40: SUB_UT_EXISTS_FLG | C40: Sub Usage Transactions Exist
A41: D1_USAGE | B41: TRACE_ON_FLG | C41: Trace
A42: D1_USAGE | B42: USG_CALC_MODE_FLG | C42: Calculation Mode
A43: D1_USAGE | B43: TD_ENTRY_ID | C43: To Do ID
... A45: D1_USAGE | B45: REQUEST_MODE_FLG | C45: Request Mode
A46: D1_USAGE_BO_DATA_AREA | B46: PROFILE_FACTOR_CD | C46: Profile Factor | D46: usageAdjustmentProfileFactors/profileFactorsList/profilefactor | G46: fields stored in the BO DATA AREA
A47: D1_USAGE_BO_DATA_AREA | B47: FACTOR_CHAR_VALUE | C47: Characteristic Value | D47: usageAdjustmentProfileFactors/profileFactorsList/value | G47: fields stored in the BO DATA AREA
A48: D1_USAGE_BO_DATA_AREA | B48: SKIP_FLG | C48: Skip | D48: skipDetails/skip | E48: SKIP_FLG | G48: fields stored in the BO DATA AREA
A49: D1_USAGE_BO_DATA_AREA | B49: D2_SKIP_REASON_FLG | C49: Skip Reason | D49: skipDetails/skipReason | E49: D2_SKIP_REASON_FLG | G49: fields stored in the BO DATA AREA
A50: D1_USAGE_BO_DATA_AREA | B50: DATE_BREAKS_LBL | C50: Date Break | G50: fields stored in the BO DATA AREA
A51: D1_USAGE_BO_DATA_AREA | B51: DATE_BREAK | C51: Date | D51: dateBreaks/dateBreakList/dateBreak | G51: fields stored in the BO DATA AREA
A52: D1_USAGE_BO_DATA_AREA | B52: INTERVAL_MC_LBL | C52: Interval Measuring Component | G52: fields stored in the BO DATA AREA
A53: D1_USAGE_BO_DATA_AREA | B53: START_DTTM | C53: Start Date/Time | D53: intervalMC/startDateTime | G53: fields stored in the BO DATA AREA
A54: D1_USAGE_BO_DATA_AREA | B54: END_FROM_DTTM | C54: End Date/Time - From | D54: intervalMC/endDateTimeFrom | G54: fields stored in the BO DATA AREA
A55: D1_USAGE_BO_DATA_AREA | B55: END_TO_DTTM | C55: End Date/Time - To | D55: intervalMC/endDateTimeTo | G55: fields stored in the BO DATA AREA
A56: D1_USAGE_BO_DATA_AREA | B56: SCALAR_MC_LBL | C56: Scalar Measuring Component | G56: fields stored in the BO DATA AREA
A57: D1_USAGE_BO_DATA_AREA | B57: START_DTTM | C57: Start Date/Time | D57: scalarMC/startDateTime | G57: fields stored in the BO DATA AREA
A58: D1_USAGE_BO_DATA_AREA | B58: D1_ESTIMATE_TIME_FLG | C58: Estimate Time | D58: scalarMC/estimateTime | G58: fields stored in the BO DATA AREA
A59: D1_USAGE_BO_DATA_AREA | B59: END_FROM_DTTM | C59: End Date/Time - From | D59: scalarMC/endDateTimeFrom | G59: fields stored in the BO DATA AREA
A60: D1_USAGE_BO_DATA_AREA | B60: END_TO_DTTM | C60: End Date/Time - To | D60: scalarMC/endDateTimeTo | G60: fields stored in the BO DATA AREA
A61: D1_USAGE_BO_DATA_AREA | B61: SCALAR_END_RANGE_OPT_FLG | C61: End Range Option | D61: scalarMC/endRangeOption | G61: fields stored in the BO DATA AREA
A62: D1_USAGE_BO_DATA_AREA | B62: SCALAR_MIN_OFFSET_DAYS | C62: Minimum Offset Days | D62: scalarMC/minDaysOffset | G62: fields stored in the BO DATA AREA
A63: D1_USAGE_BO_DATA_AREA | B63: SCALAR_MAX_OFFSET_DAYS | C63: Maximum Offset Days | D63: scalarMC/maxDaysOffset | G63: fields stored in the BO DATA AREA
A64: D1_USAGE_BO_DATA_AREA | B64: D2_ALLOW_EST_FLG | C64: Allow Estimate | D64: scalarMC/allowEstimate | G64: fields stored in the BO DATA AREA
A65: D1_USAGE_BO_DATA_AREA | B65: ESTMT_DT | C65: Estimate Date | D65: scalarMC/estimateDate | G65: fields stored in the BO DATA AREA
A66: D1_USAGE_BO_DATA_AREA | B66: IS_ESTIMATE_FLG | C66: Is Estimate | D66: scalarMC/isEstimate | G66: fields stored in the BO DATA AREA
A67: D1_US | B67: ACCESS_GRP_CD | C67: Access Group
A68: D1_US | B68: BO_STATUS_CD | C68: Status | D68: * F1_BUS_OBJ_STATUS_L | F68: Inner Join
A69: D1_US | B69: BO_STATUS_REASON_CD | C69: Status Reason | D69: * F1_BUS_OBJ_STATUS_RSN_L | F69: Left Join
A70: D1_US | B70: BUS_OBJ_CD | C70: Business Object | D70: * F1_BUS_OBJ_L | F70: Inner Join
A71: D1_US | B71: CRE_DTTM | C71: Create Date/Time
A72: D1_US | B72: D1_BILL_CYC_CD | C72: Bill Cycle | D72: * D1_BILL_CYC_L | F72: Left Join
A73: D1_US | B73: D1_SPR_CD | C73: Service Provider | D73: * D1_SPR_L | F73: Left Join
A74: D1_US | B74: DIVISION_CD | C74: Division | D74: * D1_DVISION_L | F74: Left Join
A75: D1_US | B75: END_DTTM | C75: End Date/Time
A76: D1_US | B76: MOST_RECENT_TRANS_DTTM | C76: Most Recent Transaction Date/Time
A77: D1_US | B77: START_DTTM | C77: Start Date/Time
A78: D1_US | B78: STATUS_UPD_DTTM | C78: Status Date/Time
A79: D1_US | B79: TIME_ZONE_CD | C79: Time Zone
A80: D1_US | B80: USG_APPR_REQ_FLG | C80: Usage Approval
A81: D1_US | B81: US_ID | C81: Usage Subscription | D81: * D1_USAGE | E81: US_ID
A82: D1_US | B82: US_MP_ID | C82: Usage Subscription Market Participant ID | D82: * D1_US_MKT_PART | E82: US_ID | F82: Left Join
A83: D1_US | B83: US_STAT_COND_FLG | C83: Status Condition
A84: D1_US | B84: US_TYPE_CD | C84: Usage Subscription Type | D84: * D1_US_TYPE_L | F84: Inner Join
A85: D1_US | B85: VERSION | C85: Version
A86: D1_US | B86: BO_DATA_AREA | C86: Business Object Data Area
A87: C1_USAGE | B87: BILL_CYC_CD | C87: Bill Cycle
A88: C1_USAGE | B88: BO_STATUS_CD | C88: Status | D88: * F1_BUS_OBJ_STATUS_L | E88: BO_STATUS_CD in ('BD-PROC') | F88: Left Join | G88: If filtered to retrieve BD-PROC status the next rows can retrieve up to account level. When filtered status is CANCELLED, no related BSEG is retrieved
A89: C1_USAGE | B89: BSEG_ID | C89: Bill Segment ID
A90: C1_USAGE | B90: BUS_OBJ_CD | C90: Business Object | D90: * F1_BUS_OBJ_L | F90: Inner Join
A91: C1_USAGE | B91: CRE_DTTM | C91: Create Date/Time
A92: C1_USAGE | B92: END_DTTM | C92: End Date/Time
A93: C1_USAGE | B93: EXT_REFERENCE_ID | C93: External Reference ID
A94: C1_USAGE | B94: ILM_ARCH_SW | C94: ILM Archive Switch
A95: C1_USAGE | B95: ILM_DT | C95: ILM Date
A96: C1_USAGE | B96: MASTER_USAGE_ID | C96: Master Usage ID
A97: C1_USAGE | B97: SA_ID | C97: Service Agreement
A98: C1_USAGE | B98: SA_REL_ID | C98: SA Relationship ID
A99: C1_USAGE | B99: SP_ID | C99: Service Point ID
A100: C1_USAGE | B100: START_DTTM | C100: Start Date/Time
A101: C1_USAGE | B101: STATUS_UPD_DTTM | C101: Status Date/Time
A102: C1_USAGE | B102: USAGE_ID | C102: Usage ID | D102: * D1_USAGE | E102: USG_EXT_ID | G102: The following rows retrieve the C-side information
...

Sheet Total Consumption
A1: Summary
A2: Justification: This domain answers the business question "Total consumption by region and customer type"
A4: Table Name | B4: Field Name | C4: Field Description | D4: Related Table | E4: Filter | F4: Join Type | G4: Designer Notes | H4: Reviewer Notes | K4: Sample Query (Customer Class)
A5: CI_ACCT | B5: ACCESS_GRP_CD | C5: Access Group | K5: select accts.cust_cl_cd, sum(mUsgDtl.final_quantity) from cisadm.ci_acct accts, cisadm.ci_sa sa1, cisadm.c1_usage cUsg, cisadm.d1_usage mUsg, cisadm.D1_USAGE_SCALAR_DTL mUsgDtl where accts.acct_id = sa1.acct_id and sa1.sa_id = cUsg.sa_id and cUsg.usage_id = mUsg.usg_ext_id and mUsg.d1_usage_id = mUsgDtl.d1_usage_id AND SA1.SA_STATUS_FLG IN ('20','30','40') and cUsg.bo_status_cd = 'BD-PROC' and cUsg.win_start_dt between TO_DATE('01-JUL-25', 'DD-MON-RR') and TO_DATE('31-JUL-25', 'DD-MON-RR') and mUsg.bo_status_cd = 'SENT' GROUP BY accts.cust_cl_cd;
A6: CI_ACCT | B6: ACCT_DATA_AREA | C6: Account Data Area
A7: CI_ACCT | B7: ACCT_ID | C7: Account ID | G7: This will be used to link the CI_SA record | K7: Sample Query (Georgraphic Area)
A8: CI_ACCT | B8: ACCT_MGMT_GRP_CD | C8: Account Management Group
A9: CI_ACCT | B9: ALERT_INFO | C9: Alert Information
A10: CI_ACCT | B10: BILL_AFTER_DT | C10: Bill After
A11: CI_ACCT | B11: BILL_CYC_CD | C11: Bill Cycle
A12: CI_ACCT | B12: BILL_PRT_INTERCEPT | C12: Bill Print Intercept
A13: CI_ACCT | B13: BUD_PLAN_CD | C13: Budget Plan
A14: CI_ACCT | B14: CIS_DIVISION | C14: CIS Division
A15: CI_ACCT | B15: COLL_CL_CD | C15: Collection Class
A16: CI_ACCT | B16: CR_REVIEW_DT | C16: Last Credit Review Date
A17: CI_ACCT | B17: CURRENCY_CD | C17: Currency Code
A18: CI_ACCT | B18: CUST_CL_CD | C18: Customer Class | G18: This can be used as a filter to group the usage
A19: CI_ACCT | B19: INT_CR_REVIEW_SW | C19: Internal Credit Review
A20: CI_ACCT | B20: MAILING_PREM_ID | C20: Mailing Premise ID
A21: CI_ACCT | B21: NO_DEP_RVW_SW | C21: No Deposit Review Switch
A22: CI_ACCT | B22: POSTPONE_CR_RVW_DT | C22: Postpone Credit Review Until
A23: CI_ACCT | B23: PROTECT_CYC_SW | C23: Protect Bill Cycle
A24: CI_ACCT | B24: PROTECT_DIV_SW | C24: Protect Division
A25: CI_ACCT | B25: PROTECT_PREM_SW | C25: Protect Mailing Premise
A26: CI_ACCT | B26: SETUP_DT | C26: Set Up Date
A27: CI_ACCT | B27: VERSION | C27: Version
A28: CI_SA | B28: ACCT_ID | C28: Account ID | D28: * CI_ACCT | E28: ACCT_ID
A29: CI_SA | B29: ALLOW_EST_SW | C29: Allow Estimates
A30: CI_SA | B30: BUS_ACTIVITY_DESC | C30: Business Activity
A31: CI_SA | B31: CHAR_PREM_ID | C31: Premise ID
A32: CI_SA | B32: CIAC_REVIEW_DT | C32: CIAC Review Date
A33: CI_SA | B33: CIS_DIVISION | C33: CIS Division
A34: CI_SA | B34: CURRENCY_CD | C34: Currency Code
A35: CI_SA | B35: CUST_READ_FLG | C35: Customer Read
A36: CI_SA | B36: END_DT | C36: End Date
A37: CI_SA | B37: ENRL_ID | C37: Order ID
A38: CI_SA | B38: EXPIRE_DT | C38: Expire Date
A39: CI_SA | B39: HIGH_BILL_AMT | C39: Maximum Bill Threshold
A40: CI_SA | B40: IB_BASE_TM_DAY_FLG | C40: Start Day Option
... A53: CI_SA | B53: SA_REL_ID | C53: SA Relationship ID
A54: CI_SA | B54: SA_STATUS_FLG | C54: SA Status | E54: SA_STATUS_FLG IN ('20','30','40')
A55: CI_SA | B55: SA_TYPE_CD | C55: SA Type
A56: CI_SA | B56: SIC_CD | C56: SIC
A57: CI_SA | B57: SPECIAL_USAGE_FLG | C57: Special Usage
A58: CI_SA | B58: START_DT | C58: Start Date
A59: CI_SA | B59: START_OPT_CD | C59: Start Option
A60: CI_SA | B60: STOP_REQED_BY | C60: Stop Requested By
A61: CI_SA | B61: STOP_RSN_FLG | C61: Stop Reason
A62: CI_SA | B62: STRT_REQED_BY | C62: Start Requested By
A63: CI_SA | B63: STRT_RSN_FLG | C63: Start Reason
A64: CI_SA | B64: TOT_TO_BILL_AMT | C64: Total Amount to Bill
A65: CI_SA | B65: VERSION | C65: Version
A66: C1_USAGE | B66: BILL_CYC_CD | C66: Bill Cycle
A67: C1_USAGE | B67: BO_STATUS_CD | C67: Status | E67: bo_status_cd = 'BD-PROC'
A68: C1_USAGE | B68: BSEG_ID | C68: Bill Segment ID
A69: C1_USAGE | B69: BUS_OBJ_CD | C69: Business Object
A70: C1_USAGE | B70: CRE_DTTM | C70: Create Date/Time
A71: C1_USAGE | B71: END_DTTM | C71: End Date/Time
A72: C1_USAGE | B72: EXT_REFERENCE_ID | C72: External Reference ID
A73: C1_USAGE | B73: ILM_ARCH_SW | C73: ILM Archive Switch
A74: C1_USAGE | B74: ILM_DT | C74: ILM Date
A75: C1_USAGE | B75: MASTER_USAGE_ID | C75: Master Usage ID
A76: C1_USAGE | B76: SA_ID | C76: Service Agreement | E76: CI_SA.SA_ID *
A77: C1_USAGE | B77: SA_REL_ID | C77: SA Relationship ID
A78: C1_USAGE | B78: SP_ID | C78: Service Point ID
A79: C1_USAGE | B79: START_DTTM | C79: Start Date/Time
A80: C1_USAGE | B80: STATUS_UPD_DTTM | C80: Status Date/Time
A81: C1_USAGE | B81: USAGE_ID | C81: Usage ID
A82: C1_USAGE | B82: USER_ID | C82: User
A83: C1_USAGE | B83: USG_DATA_AREA | C83: Consumption Data Area
A84: C1_USAGE | B84: VERSION | C84: Version
A85: C1_USAGE | B85: WIN_START_DT | C85: Window Start Date | E85: win_start_dt between TO_DATE('01-JUL-25', 'DD-MON-RR') and TO_DATE('31-JUL-25', 'DD-MON-RR') | G85: This can be used to filter the amount of data. I tried to use the create date but the sample query ran more than 10minutes
A86: D1_USAGE | B86: BO_DATA_AREA | C86: Business Object Data Area
A87: D1_USAGE | B87: BO_STATUS_CD | C87: Status | E87: bo_status_cd = 'SENT'
A88: D1_USAGE | B88: BO_STATUS_REASON_CD | C88: Status Reason
A89: D1_USAGE | B89: BUS_OBJ_CD | C89: Business Object
A90: D1_USAGE | B90: COMMENTS | C90: Comments
A91: D1_USAGE | B91: CRE_DTTM | C91: Create Date/Time
A92: D1_USAGE | B92: D1_SPR_CD | C92: Service Provider
A93: D1_USAGE | B93: D1_USAGE_ID | C93: Usage Transaction ID
A94: D1_USAGE | B94: D1_USG_CAL_TYPE_CD | C94: Usage Calculation Type
A95: D1_USAGE | B95: END_DTTM | C95: End Date/Time
A96: D1_USAGE | B96: ILM_ARCH_SW | C96: ILM Archive Switch
A97: D1_USAGE | B97: ILM_DT | C97: ILM Date
A98: D1_USAGE | B98: LINKED_TO_FRZN_BSEG_FLG | C98: Linked to Frozen Bill Segment
A99: D1_USAGE | B99: MSRMT_CYC_CD | C99: Measurement Cycle
... A107: D1_USAGE | B107: USED_ON_BILL_FLG | C107: Used on Bill
A108: D1_USAGE | B108: USG_EXT_ID | C108: Usage External ID | D108: C1_USAGE.USAGE_ID | E108: 1:1 relationship
A109: D1_USAGE | B109: USG_GRP_CD | C109: Calculation Group
A110: D1_USAGE | B110: USG_SRC_FLG | C110: Usage Source
A111: D1_USAGE | B111: US_ID | C111: Usage Subscription
A112: D1_USAGE | B112: VERSION | C112: Version
A113: D1_USAGE_SCALAR_DTL | B113: APPLIED_MLTR | C113: Applied Multiplier
A114: D1_USAGE_SCALAR_DTL | B114: BO_DATA_AREA | C114: Business Object Data Area
A115: D1_USAGE_SCALAR_DTL | B115: D1_FINAL_SQI_CD | C115: Final SQI
A116: D1_USAGE_SCALAR_DTL | B116: D1_FINAL_TOU_CD | C116: Final TOU
A117: D1_USAGE_SCALAR_DTL | B117: D1_FINAL_UOM_CD | C117: Final UOM
A118: D1_USAGE_SCALAR_DTL | B118: D1_SP_ID | C118: Service Point ID
A119: D1_USAGE_SCALAR_DTL | B119: D1_SQI_CD | C119: Service Quantity Identifier
A120: D1_USAGE_SCALAR_DTL | B120: D1_TOU_CD | C120: Time of Use
...

Sheet D1_USAGE_EXCP
B1: Summary
B2: Table Name: D1_USAGE_EXCP
B3: Justification
B4: Designer | C4: Lennice
A6: Table Name | B6: Field Name | C6: Field Description | D6: Related Table | E6: Filter | F6: Join Type | G6: Designer Notes | H6: Reviewer Notes
A7: D1_USAGE_EXCP | B7: BO_STATUS_CD | C7: Status | D7: * F1_BUS_OBJ_STATUS_L
A8: D1_USAGE_EXCP | B8: BO_STATUS_REASON_CD | C8: Status Reason | D8: * F1_BUS_OBJ_STATUS_RSN_L | F8: Left Join
A9: D1_USAGE_EXCP | B9: BUS_OBJ_CD | C9: Business Object | D9: * F1_BUS_OBJ_L | F9: Inner Join
A10: D1_USAGE_EXCP | B10: CRE_DTTM | C10: Create Date/Time
A11: D1_USAGE_EXCP | B11: D1_USAGE_ID | C11: Usage Transaction ID | D11: * D1_USAGE | E11: D1_USAGE_ID | F11: Inner Join
A12: D1_USAGE_EXCP | B12: EXCP_SEVERITY_FLG | C12: Exception Severity | D12: * CI_LOOKUP_VAL * CI_LOOKUP_VAL_L
A13: D1_USAGE_EXCP | B13: ILM_ARCH_SW | C13: ILM Archive Switch
A14: D1_USAGE_EXCP | B14: ILM_DT | C14: ILM Date
A15: D1_USAGE_EXCP | B15: MESSAGE_CAT_NBR | C15: Message Category | D15: * CI_MSG_CATEGORY | F15: Left Join
A16: D1_USAGE_EXCP | B16: MESSAGE_NBR | C16: Message Number | D16: * CI_MSG | F16: Left Join
A17: D1_USAGE_EXCP | B17: OPEN_CLOSE_FLG | C17: Exception Status | D17: * CI_LOOKUP_VAL * CI_LOOKUP_VAL_L
A18: D1_USAGE_EXCP | B18: STATUS_UPD_DTTM | C18: Status Date/Time
A19: D1_USAGE_EXCP | B19: USAGE_EXCP_ID | C19: Usage Transaction Exception
A20: D1_USAGE_EXCP | B20: USAGE_EXCP_TYPE_CD | C20: Exception Type | D20: * D1_USAGE_EXCP_TYPE_L | F20: Inner Join
A21: D1_USAGE_EXCP | B21: USG_GRP_CD | C21: Calculation Group | D21: * D1_USG_GRP_L | F21: Inner Join
A22: D1_USAGE_EXCP | B22: USG_RULE_CD | C22: Calculation Rule | D22: * D1_USG_RULE_L
A23: D1_USAGE_EXCP | B23: VERSION | C23: Version
A24: BO_DATA_AREA | B24: COMMENTS | C24: Comments
A25: BO_DATA_AREA | B25: TD_TYPE_CD | C25: To Do Type | D25: * CI_TD_TYPE
A26: BO_DATA_AREA | B26: ROLE_ID | C26: To Do Role | D26: * CI_TD_VAL_ROLE
A27: D1_USAGE_EXCP_CHAR | B27: USAGE_EXCP_ID | C27: Usage Transaction Exception | D27: * D1_USAGE_EXCP
A28: D1_USAGE_EXCP_CHAR | B28: CHAR_TYPE_CD | C28: Characteristic Type | D28: * CI_CHAR_TYPE_L
A29: D1_USAGE_EXCP_CHAR | B29: CHAR_VAL | C29: Characteristic Value | D29: * CI_CHAR_VAL_L

Sheet D1_SP_Archive
B1: Summary
B2: Table Name: D1_SP
B3: Justification | C3: =Summary!O118 -> This table records information about Field Activities. It is useful for Clients as it allows them to easily access and extract FA-related data via reports.
B4: Designer | C4: Lennice
A6: Table Name | B6: Field Name | C6: Field Description | D6: Related Table | E6: Filter | F6: Join Type | G6: Designer Notes | H6: Reviewer Notes
A7: D1_SP | B7: TIME_ZONE_CD | C7: Time Zone | D7: * CI_TIME_ZONE_L | F7: Inner Join
A8: D1_SP | B8: ACCESS_GRP_CD | C8: Access Group | D8: *CI_ACC_GRP_L | F8: Left Join
A9: D1_SP | B9: COUNTRY | C9: Country | D9: * CI_COUNTRY_L | F9: Inner Join
A10: D1_SP | B10: POSTAL | C10: Postal | D10: N/A | F10: N/A
A11: D1_SP | B11: ADDRESS1 | C11: Address | D11: N/A | F11: N/A
A12: D1_SP | B12: ADDRESS1_UPPER | C12: Address Line 1 Upper Case | D12: N/A | F12: N/A
A13: D1_SP | B13: ADDRESS2 | C13: Address 2 | D13: N/A | F13: N/A
A14: D1_SP | B14: ADDRESS3 | C14: Address 3 | D14: N/A | F14: N/A
A15: D1_SP | B15: ADDRESS4 | C15: Address 4 | D15: N/A | F15: N/A
A16: D1_SP | B16: CITY | C16: City | D16: N/A | F16: N/A
A17: D1_SP | B17: CITY_UPPER | C17: City Upper Case | D17: N/A | F17: N/A
A18: D1_SP | B18: NUM1 | C18: Number 1 | D18: N/A | F18: N/A
... A42: - | B42: D1_INSTALL_DT | C42: Install Date | D42: N/A | F42: N/A
A43: D1_SP | B43: SP_SRC_STAT_FLG | C43: Source Status
A44: D1_SP | B44: D1_LS_SL_FLG | C44: Life Support / Sensitive Load
A45: D1_SP | B45: D1_LS_SL_DESCR | C45: Description
A46: D1_SP | B46: MKT_CD | C46: Market | F46: Left Join
A47: D1_US_SP | B47: D1_SP_ID | C47: Service Point ID | D47: D1_SP | F47: Right Join | G47: The next rows retrieves the related information of the SP to the Usage Subscription, Contact, Premise
A48: D1_US_SP | B48: US_ID | C48: Usage Subscription | D48: D1_US | F48: Left Join
A49: D1_US | B49: US_TYPE_CD | C49: Usage Subscription Type | D49: D1_US_TYPE_L | F49: Left Join
A50: D1_US | B50: US_ID | C50: Usage Subscription | D50: N/A
A51: D1_US | B51: START_DTTM | C51: Start Date/Time | D51: N/A | F51: Inner Join
A52: D1_US | B52: END_DTTM | C52: End Date/Time | D52: N/A | F52: Left Join
A53: D1_SP_CONTACT | B53: D1_SP_ID | C53: Service Point ID | D53: D1_SP | F53: Right Join
A54: D1_SP_CONTACT | B54: CONTACT_ID | C54: Contact Id | D54: N/A
A55: D1_SP_IDENTIFIER | B55: ID_VALUE | C55: Id Value | D55: Id Value | E55: SP_ID_TYPE_FLG ="D1EP" | F55: Inner Join
A56: CMS_D1_SP_BODA_VW | B56: D1_SP_ID | C56: Service Point ID | D56: D1_SP | F56: Right Join
A57: CMS_D1_SP_BODA_VW | B57: PERIODIC_EST_ELIGIBILITY_FLG | C57: Estimation Eligibility | D57: N/A
A58: CMS_D1_SP_BODA_VW | B58: OK_TO_ETR_LBL | C58: OK To Enter | D58: N/A
A59: CMS_D1_SP_BODA_VW | B59: SP_WARN_LBL | C59: SP Warning | D59: N/A
A60: CMS_D1_SP_BODA_VW | B60: SP_INSTR_LBL | C60: SP Instruction | D60: N/A
A61: CMS_D1_SP_BODA_VW | B61: SP_INSTR_DTS_LBL | C61: SP Instruction Details | D61: N/A
A62: CMS_D1_SP_BODA_VW | B62: KEY_LBL | C62: Key | D62: N/A
A63: CMS_D1_SP_BODA_VW | B63: D1_KEY_ID_LBL | C63: Key ID | D63: N/A
A64: CMS_D1_SP_BODA_VW | B64: DEVICE_LOC_LBL | C64: Device Location | D64: N/A
A65: CMS_D1_SP_BODA_VW | B65: DEVICE_LOC_DTS_LBL | C65: Device Location Details | D65: N/A
A66: CMS_D1_SP_BODA_VW | B66: START_DTTM | C66: Start Date/Time | D66: N/A
A67: CMS_D1_SP_BODA_VW | B67: END_DTTM | C67: End Date/Time | D67: N/A
A68: CMS_D1_SP_BODA_VW | B68: INSTALLATION_OVERRIDE_QUANTITY | C68: Installation Override Quantity (Daily) | D68: N/A
... A73: CMS_D1_SP_BODA_VW | B73: CREW | C73: Crew | D73: N/A
A74: D1_SP_MSRMT_CYC_SCHED_RTE | B74: D1_SP_ID | C74: Service Point ID | D74: * D1_SP | E74: D1_SP_ID | F74: Left Join | G74: The next rows retrieves the related information of the SP's Measurement Cycle, Measurement Cycle Route, Measurement Cycle Schedule
A75: D1_SP_MSRMT_CYC_SCHED_RTE | B75: SCHED_SELECTION_DT | C75: Scheduled Selection Date | D75: * D1_SP | E75: D1_SP_ID | F75: Left Join
A76: D1_SP_MSRMT_CYC_SCHED_RTE | B76: MSRMT_CYC_CD | C76: Measurement Cycle | D76: * D1_MSRMT_CYC_L | F76: Inner Join
A77: D1_SP_MSRMT_CYC_SCHED_RTE | B77: MSRMT_CYC_RTE_CD | C77: Route | D77: * D1_MSRMT_CYC_RTE_L | F77: Inner Join
A78: D1_INSTALL_EVT | B78: INSTALL_EVT_ID | C78: Install Event Id | D78: * D1_INSTALL_EVT | E78: DEVICE_CONFIG_ID | F78: Left Outer
A79: D1_INSTALL_EVT | B79: D1_SP_ID | C79: Service Point Id | D79: * D1_INSTALL_EVT | F79: Inner Join
A80: D1_INSTALL_EVT | B80: BO_STATUS_CD | C80: Status | D80: * D1_INSTALL_EVT | E80: BO_STATUS_CD IN ('ON','CONN-COMM') | F80: Inner Join | G80: This is filter is used to retrieve the meter currently installed on the SP at a given date
A82: Note: Removing the SP Id and keeping the Schedule Selection Date and Measurement Date/Time it took 8 minutes in SQL DEV.
A83: SELECT A1.D1_SP_ID, A3.MSRMT_CYC_CD, A3.SCHED_SELECTION_DT, A3.MSRMT_CYC_RTE_CD, A4.BO_STATUS_CD, A5.DEVICE_CONFIG_ID, A6.MEASR_COMP_ID, A6.MOST_RECENT_MSRMT_DTTM, A7.MSRMT_COND_FLG, A7.MSRMT_VAL FROM CISADM.D1_SP A1 JOIN CISADM.D1_SP_MSRMT_CYC_SCHED_RTE A3 ON A1.D1_SP_ID = A3.D1_SP_ID JOIN CISADM.D1_INSTALL_EVT A4 ON A3.D1_SP_ID = A4.D1_SP_ID JOIN CISADM.D1_DVC_CFG A5 ON A4.DEVICE_CONFIG_ID = A5.DEVICE_CONFIG_ID JOIN CISADM.D1_MEASR_COMP A6 ON A5.DEVICE_CONFIG_ID = A6.DEVICE_CONFIG_ID JOIN CISADM.D1_MSRMT A7 ON A6.MEASR_COMP_ID = A7.MEASR_COMP_ID WHERE A4.BO_STATUS_CD IN ('ON', 'CONN-COMM') -- AND A1.D1_SP_ID = '403776764300' AND A3.SCHED_SELECTION_DT >= '01-JAN-25' AND A7.MSRMT_COND_FLG <> '501000' AND A7.MSRMT_DTTM >= '13-MAR-25';
A85: Business Questions
A86: Number of meters are in each cycle / route (Jim) | B86: filter by measurement cycle or mesurement route which is usally the same
A87: Meters that haven’t been read recently (Jim) | B87: this can be retrieved using the filter LATEST_MSRMT_DTTM
A88: Number of estimates that are created by route (Jim) | B88: this can be retrieved by adding the filter MSMRMT_COND_FLG <> '501000'
A90: D1_SP EQUIPMENT ALSO, DO NOT FORGET
A92: Table Name | B92: Field Name | C92: Field Description | D92: Related Table | E92: Filter | F92: Join Type | G92: Designer Notes | H92: Reviewer Notes
A93: D1_US_SP | B93: BO_DATA_AREA | C93: Business Object Data Area
A94: D1_US_SP | B94: D1_SP_ID | C94: Service Point ID
A95: D1_US_SP | B95: D1_STOP_DTTM | C95: End Date/Time
A96: D1_US_SP | B96: D1_USAGE_FLG | C96: Usage
A97: D1_US_SP | B97: OVRD_START_DTTM | C97: Override Start Date/Time
A98: D1_US_SP | B98: OVRD_STOP_DTTM | C98: Override Stop Date/Time
A99: D1_US_SP | B99: SEQNO | C99: Sequence
A100: D1_US_SP | B100: START_DTTM | C100: Start Date/Time
A101: D1_US_SP | B101: USE_PERCENT | C101: Use Percent
A102: D1_US_SP | B102: US_ID | C102: Usage Subscription
A103: D1_US_SP | B103: VERSION | C103: Version
A104: D1_US_CONTACT | B104: CONTACT_ID | C104: Contact ID
... A165: D1_INSTALL_EVT | B165: VERSION | C165: Version

Sheet D1_SP2
B1: Summary
B2: Table Name: D1_SP
B3: Justification | C3: =Summary!O118 -> This table records information about Field Activities. It is useful for Clients as it allows them to easily access and extract FA-related data via reports.
B4: Designer | C4: Lennice
A6: Table Name | B6: Field Name | C6: Field Description | D6: Related Table | E6: Filter | F6: Join Type | G6: Designer Notes | H6: Reviewer Notes
A7: D1_SP | B7: TIME_ZONE_CD | C7: Time Zone | D7: * CI_TIME_ZONE_L | F7: Inner Join
A8: D1_SP | B8: ACCESS_GRP_CD | C8: Access Group | D8: *CI_ACC_GRP_L | F8: Left Join
A9: D1_SP | B9: COUNTRY | C9: Country | D9: * CI_COUNTRY_L | F9: Inner Join
A10: D1_SP | B10: POSTAL | C10: Postal | D10: N/A | F10: N/A
A11: D1_SP | B11: ADDRESS1 | C11: Address | D11: N/A | F11: N/A
A12: D1_SP | B12: ADDRESS1_UPPER | C12: Address Line 1 Upper Case | D12: N/A | F12: N/A
A13: D1_SP | B13: ADDRESS2 | C13: Address 2 | D13: N/A | F13: N/A
A14: D1_SP | B14: ADDRESS3 | C14: Address 3 | D14: N/A | F14: N/A
A15: D1_SP | B15: ADDRESS4 | C15: Address 4 | D15: N/A | F15: N/A
A16: D1_SP | B16: CITY | C16: City | D16: N/A | F16: N/A
A17: D1_SP | B17: CITY_UPPER | C17: City Upper Case | D17: N/A | F17: N/A
A18: D1_SP | B18: NUM1 | C18: Number 1 | D18: N/A | F18: N/A
... A42: - | B42: D1_INSTALL_DT | C42: Install Date | D42: N/A | F42: N/A
A43: D1_SP | B43: SP_SRC_STAT_FLG | C43: Source Status
A44: D1_SP | B44: D1_LS_SL_FLG | C44: Life Support / Sensitive Load
A45: D1_SP | B45: D1_LS_SL_DESCR | C45: Description
A46: D1_SP | B46: MKT_CD | C46: Market | F46: Left Join
A47: CMS_D1_SP_BODA_VW | B47: D1_SP_ID | C47: Service Point ID | D47: D1_SP | F47: Right Join
A48: CMS_D1_SP_BODA_VW | B48: PERIODIC_EST_ELIGIBILITY_FLG | C48: Estimation Eligibility | D48: N/A
A49: CMS_D1_SP_BODA_VW | B49: OK_TO_ETR_LBL | C49: OK To Enter | D49: N/A
A50: CMS_D1_SP_BODA_VW | B50: SP_WARN_LBL | C50: SP Warning | D50: N/A
A51: CMS_D1_SP_BODA_VW | B51: SP_INSTR_LBL | C51: SP Instruction | D51: N/A
A52: CMS_D1_SP_BODA_VW | B52: SP_INSTR_DTS_LBL | C52: SP Instruction Details | D52: N/A
A53: CMS_D1_SP_BODA_VW | B53: KEY_LBL | C53: Key | D53: N/A
A54: CMS_D1_SP_BODA_VW | B54: D1_KEY_ID_LBL | C54: Key ID | D54: N/A
A55: CMS_D1_SP_BODA_VW | B55: DEVICE_LOC_LBL | C55: Device Location | D55: N/A
A56: CMS_D1_SP_BODA_VW | B56: DEVICE_LOC_DTS_LBL | C56: Device Location Details | D56: N/A
A57: CMS_D1_SP_BODA_VW | B57: START_DTTM | C57: Start Date/Time | D57: N/A
A58: CMS_D1_SP_BODA_VW | B58: END_DTTM | C58: End Date/Time | D58: N/A
A59: CMS_D1_SP_BODA_VW | B59: INSTALLATION_OVERRIDE_QUANTITY | C59: Installation Override Quantity (Daily) | D59: N/A
... A64: CMS_D1_SP_BODA_VW | B64: CREW | C64: Crew | D64: N/A
A65: D1_US_SP | B65: BO_DATA_AREA | C65: Business Object Data Area
A66: D1_US_SP | B66: D1_SP_ID | C66: Service Point ID | D66: D1_SP | E66: D1_SP_ID | F66: Left Join | G66: This is just to link the US and SP
A67: D1_US_SP | B67: D1_STOP_DTTM | C67: End Date/Time
A68: D1_US_SP | B68: D1_USAGE_FLG | C68: Usage
A69: D1_US_SP | B69: OVRD_START_DTTM | C69: Override Start Date/Time
A70: D1_US_SP | B70: OVRD_STOP_DTTM | C70: Override Stop Date/Time
A71: D1_US_SP | B71: SEQNO | C71: Sequence
A72: D1_US_SP | B72: START_DTTM | C72: Start Date/Time
A73: D1_US_SP | B73: USE_PERCENT | C73: Use Percent
A74: D1_US_SP | B74: US_ID | C74: Usage Subscription
A75: D1_US_SP | B75: VERSION | C75: Version
A76: D1_US_CONTACT | B76: CONTACT_ID | C76: Contact ID
A77: D1_US_CONTACT | B77: US_CNTCT_REL_FLG | C77: Relationship Type
A78: D1_US_CONTACT | B78: US_ID | C78: Usage Subscription | D78: D1_US_SP | E78: US_ID | F78: Left Join | G78: Link
A79: D1_US_CONTACT | B79: VERSION | C79: Version
A80: D1_CONTACT_IDENTIFIER | B80: CONTACT_ID | C80: Contact ID | D80: D1_US_CONTACT | E80: CONTACT_ID | F80: Left Join | G80: This links the US Contact to the Person
A81: D1_CONTACT_IDENTIFIER | B81: CONTACT_ID_TYPE_FLG | C81: Contact Identifier Type
A82: D1_CONTACT_IDENTIFIER | B82: ID_VALUE | C82: Identifier Value | G82: Person
A83: D1_CONTACT_IDENTIFIER | B83: VERSION | C83: Version
A84: CI_PER | B84: ADDRESS1 | C84: Address
A85: CI_PER | B85: ADDRESS2 | C85: Address 2
A86: CI_PER | B86: ADDRESS3 | C86: Address 3
A87: CI_PER | B87: ADDRESS4 | C87: Address 4
A88: CI_PER | B88: CITY | C88: City
A89: CI_PER | B89: COUNTRY | C89: Country
A90: CI_PER | B90: COUNTY | C90: County
A91: CI_PER | B91: EMAILID | C91: Email Address
A92: CI_PER | B92: GEO_CODE | C92: Geographical Code
A93: CI_PER | B93: HOUSE_TYPE | C93: House Type
A94: CI_PER | B94: IN_CITY_LIMIT | C94: In City Limit
... A103: CI_PER | B103: PER_DATA_AREA | C103: Person Data Area
A104: CI_PER | B104: PER_ID | C104: Person ID | D104: D1_CONTACT_IDENTIFIER | E104: ID_VALUE | F104: Left Join
A105: CI_PER | B105: PER_OR_BUS_FLG | C105: Person/Business
A106: CI_PER | B106: POSTAL | C106: Postal
A107: CI_PER | B107: RECV_MKTG_INFO_FLG | C107: Web Self Service Marketing Info
A108: CI_PER | B108: STATE | C108: State
A109: CI_PER | B109: TIME_ZONE_CD | C109: Time Zone
A110: CI_PER | B110: VERSION | C110: Version
A111: CI_PER | B111: WEB_PASSWD | C111: Web Self Service Password
A112: CI_PER | B112: WEB_PASSWD_ANS | C112: Web Self Service Password Hint Answer
A113: CI_PER | B113: WEB_PWD_HINT_FLG | C113: Password Hint
A114: D1_SP_MSRMT_CYC_SCHED_RTE | B114: BO_STATUS_CD | C114: Status
A115: D1_SP_MSRMT_CYC_SCHED_RTE | B115: BO_STATUS_REASON_CD | C115: Status Reason
A116: D1_SP_MSRMT_CYC_SCHED_RTE | B116: BUS_OBJ_CD | C116: Business Object
A117: D1_SP_MSRMT_CYC_SCHED_RTE | B117: CRE_DTTM | C117: Create Date/Time
A118: D1_SP_MSRMT_CYC_SCHED_RTE | B118: D1_SP_ID | C118: Service Point ID | D118: D1_SP | E118: D1_SP_ID | F118: Left Join | G118: Links the SP to the Measurement Cycle
A119: D1_SP_MSRMT_CYC_SCHED_RTE | B119: MSRMT_CYC_CD | C119: Measurement Cycle
A120: D1_SP_MSRMT_CYC_SCHED_RTE | B120: MSRMT_CYC_RTE_CD | C120: Route
A121: D1_SP_MSRMT_CYC_SCHED_RTE | B121: SCHED_SELECTION_DT | C121: Scheduled Selection Date
A122: D1_SP_MSRMT_CYC_SCHED_RTE | B122: STATUS_UPD_DTTM | C122: Status Date/Time
A123: D1_SP_MSRMT_CYC_SCHED_RTE | B123: VERSION | C123: Version
A124: D1_INSTALL_EVT | B124: ARM_STAT_FLG | C124: Arming Status
A125: D1_INSTALL_EVT | B125: BO_DATA_AREA | C125: Business Object Data Area
A126: D1_INSTALL_EVT | B126: BO_STATUS_CD | C126: Status
A127: D1_INSTALL_EVT | B127: BO_STATUS_REASON_CD | C127: Status Reason
A128: D1_INSTALL_EVT | B128: BUS_OBJ_CD | C128: Business Object | G128: Adhoc filter as the report should be able to retrieve Installed for a specific period
A129: D1_INSTALL_EVT | B129: CRE_DTTM | C129: Create Date/Time
A130: D1_INSTALL_EVT | B130: D1_INSTALL_DTTM | C130: Installation Date/Time
A131: D1_INSTALL_EVT | B131: D1_REMOVAL_DTTM | C131: Removal Date/Time
A132: D1_INSTALL_EVT | B132: D1_SP_ID | C132: Service Point ID | D132: D1_SP | E132: D1_SP_ID | F132: Left Join
A133: D1_INSTALL_EVT | B133: DEVICE_CONFIG_ID | C133: Device Configuration
A134: D1_INSTALL_EVT | B134: INSTALLATION_CONST | C134: Installation Constant
A135: D1_INSTALL_EVT | B135: INSTALL_EVT_ID | C135: Install Event ID
A136: D1_INSTALL_EVT | B136: STATUS_UPD_DTTM | C136: Status Date/Time
...

Sheet D1_US
B1: Summary
B2: Table Name: D1_US
B3: Justification
B4: Designer | C4: Lennice
A6: Table Name | B6: Field Name | C6: Field Description | D6: Related Table | E6: Filter | F6: Join Type | G6: Designer Notes | H6: Reviewer Notes
A7: D1_US | B7: ACCESS_GRP_CD | C7: Access Group
A8: D1_US | B8: BO_STATUS_CD | C8: Status | D8: * F1_BUS_OBJ_STATUS_L | F8: Inner Join
A9: D1_US | B9: BO_STATUS_REASON_CD | C9: Status Reason | D9: * F1_BUS_OBJ_STATUS_RSN_L | F9: Left Join
A10: D1_US | B10: BUS_OBJ_CD | C10: Business Object | D10: * F1_BUS_OBJ_L | F10: Inner Join
A11: D1_US | B11: CRE_DTTM | C11: Create Date/Time
A12: D1_US | B12: D1_BILL_CYC_CD | C12: Bill Cycle | D12: * D1_BILL_CYC_L | F12: Left Join
A13: D1_US | B13: D1_SPR_CD | C13: Service Provider | D13: * D1_SPR_L | F13: Left Join
A14: D1_US | B14: DIVISION_CD | C14: Division | D14: * D1_DVISION_L | F14: Left Join
A15: D1_US | B15: END_DTTM | C15: End Date/Time
A16: D1_US | B16: MOST_RECENT_TRANS_DTTM | C16: Most Recent Transaction Date/Time
A17: D1_US | B17: START_DTTM | C17: Start Date/Time
A18: D1_US | B18: STATUS_UPD_DTTM | C18: Status Date/Time
A19: D1_US | B19: TIME_ZONE_CD | C19: Time Zone
A20: D1_US | B20: USG_APPR_REQ_FLG | C20: Usage Approval
A21: D1_US | B21: US_ID | C21: Usage Subscription
A22: D1_US | B22: US_MP_ID | C22: Usage Subscription Market Participant ID | D22: * D1_US_MKT_PART | E22: US_ID | F22: Left Join
A23: D1_US | B23: US_STAT_COND_FLG | C23: Status Condition
A24: D1_US | B24: US_TYPE_CD | C24: Usage Subscription Type | D24: * D1_US_TYPE_L | F24: Inner Join
A25: D1_US | B25: VERSION | C25: Version
A26: D1_US | B26: BO_DATA_AREA | C26: Business Object Data Area
A27: D1_US_IDENTIFIER | B27: ID_VALUE | C27: Identifier Value
A28: D1_US_IDENTIFIER | B28: US_ID | C28: Usage Subscription | D28: * D1_US | E28: US_ID
A29: D1_US_IDENTIFIER | B29: US_ID_TYPE_FLG | C29: Usage Subscription Identifier Type | E29: US_ID_TYPE_FLG = D2EI
A30: D1_US_IDENTIFIER | B30: VERSION | C30: Version
A31: D1_US_CONTACT | B31: CONTACT_ID | C31: Contact ID
A32: D1_US_CONTACT | B32: US_CNTCT_REL_FLG | C32: Relationship Type
A33: D1_US_CONTACT | B33: US_ID | C33: Usage Subscription | D33: * D1_US | E33: US_ID
A34: D1_US_CONTACT | B34: VERSION | C34: Version
A35: D1_US_SP | B35: BO_DATA_AREA | C35: Business Object Data Area
A36: D1_US_SP | B36: D1_SP_ID | C36: Service Point ID
A37: D1_US_SP | B37: D1_STOP_DTTM | C37: End Date/Time
A38: D1_US_SP | B38: D1_USAGE_FLG | C38: Usage
A39: D1_US_SP | B39: OVRD_START_DTTM | C39: Override Start Date/Time
A40: D1_US_SP | B40: OVRD_STOP_DTTM | C40: Override Stop Date/Time
A41: D1_US_SP | B41: SEQNO | C41: Sequence
A42: D1_US_SP | B42: START_DTTM | C42: Start Date/Time
A43: D1_US_SP | B43: USE_PERCENT | C43: Use Percent
A44: D1_US_SP | B44: US_ID | C44: Usage Subscription | D44: * D1_US | E44: US_ID
A45: D1_US_SP | B45: VERSION | C45: Version
A46: CI_SA | B46: ACCT_ID | C46: Account ID
A47: CI_SA | B47: ALLOW_EST_SW | C47: Allow Estimates
A48: CI_SA | B48: BUS_ACTIVITY_DESC | C48: Business Activity
A49: CI_SA | B49: CHAR_PREM_ID | C49: Premise ID
A50: CI_SA | B50: CIAC_REVIEW_DT | C50: CIAC Review Date
A51: CI_SA | B51: CIS_DIVISION | C51: CIS Division
A52: CI_SA | B52: CURRENCY_CD | C52: Currency Code
A53: CI_SA | B53: CUST_READ_FLG | C53: Customer Read
A54: CI_SA | B54: END_DT | C54: End Date
A55: CI_SA | B55: ENRL_ID | C55: Order ID
A56: CI_SA | B56: EXPIRE_DT | C56: Expire Date
... A69: CI_SA | B69: SA_DATA_AREA | C69: SA Data Area
A70: CI_SA | B70: SA_ID | C70: Service Agreement | D70: * D1_US_IDENTIFIER | E70: ID_VALUE
A71: CI_SA | B71: SA_REL_ID | C71: SA Relationship ID
A72: CI_SA | B72: SA_STATUS_FLG | C72: SA Status
A73: CI_SA | B73: SA_TYPE_CD | C73: SA Type
A74: CI_SA | B74: SIC_CD | C74: SIC
A75: CI_SA | B75: SPECIAL_USAGE_FLG | C75: Special Usage
A76: CI_SA | B76: START_DT | C76: Start Date
A77: CI_SA | B77: START_OPT_CD | C77: Start Option
A78: CI_SA | B78: STOP_REQED_BY | C78: Stop Requested By
A79: CI_SA | B79: STOP_RSN_FLG | C79: Stop Reason
A80: CI_SA | B80: STRT_REQED_BY | C80: Start Requested By
A81: CI_SA | B81: STRT_RSN_FLG | C81: Start Reason
A82: CI_SA | B82: TOT_TO_BILL_AMT | C82: Total Amount to Bill
A83: CI_SA | B83: VERSION | C83: Version
A84: D1_USAGE | B84: BO_STATUS_CD | C84: Status | D84: * F1_BUS_OBJ_STATUS_L
A85: D1_USAGE | B85: BO_STATUS_REASON_CD | C85: Status Reason | D85: * F1_BUS_OBJ_STATUS_RSN_L | F85: Left Join
A86: D1_USAGE | B86: BUS_OBJ_CD | C86: Business Object | D86: * F1_BUS_OBJ_L | F86: Inner Join
A87: D1_USAGE | B87: COMMENTS | C87: Comments
A88: D1_USAGE | B88: CRE_DTTM | C88: Create Date/Time
A89: D1_USAGE | B89: D1_SPR_CD | C89: Service Provider
A90: D1_USAGE | B90: D1_USAGE_ID | C90: Usage Transaction ID
A91: D1_USAGE | B91: D1_USG_CAL_TYPE_CD | C91: Usage Calculation Type | D91: * D1_USG_CAL_TYPE_L | E91: D1_USG_CAL_TYPE_CD | F91: Left Join
A92: D1_USAGE | B92: END_DTTM | C92: End Date/Time
A93: D1_USAGE | B93: ILM_ARCH_SW | C93: ILM Archive Switch
A94: D1_USAGE | B94: ILM_DT | C94: ILM Date
A95: D1_USAGE | B95: LINKED_TO_FRZN_BSEG_FLG | C95: Linked to Frozen Bill Segment
A96: D1_USAGE | B96: MSRMT_CYC_CD | C96: Measurement Cycle | D96: * D1_MSRMT_CYC_L
A97: D1_USAGE | B97: MSRMT_CYC_RTE_CD | C97: Route | D97: * D1_MSRMT_CYC_RTE_L
A98: D1_USAGE | B98: ORG_USAGE_ID | C98: Original Usage ID
A99: D1_USAGE | B99: REL_ORDER | C99: Relative Order
A100: D1_USAGE | B100: SCH_SELECTION_DT | C100: Scheduled Selection Date
A101: D1_USAGE | B101: START_DTTM | C101: Start Date/Time
A102: D1_USAGE | B102: STATUS_UPD_DTTM | C102: Status Date/Time
A103: D1_USAGE | B103: TOT_USG_TRANS_CNT | C103: Total Usage Transaction Count
A104: D1_USAGE | B104: USED_ON_BILL_FLG | C104: Used on Bill | D104: * CI_LOOKUP_VAL * CI_LOOKUP_VAL_L | E104: USED_ON_BILL_FLG | F104: Left Join
A105: D1_USAGE | B105: USG_EXT_ID | C105: Usage External ID
A106: D1_USAGE | B106: USG_GRP_CD | C106: Calculation Group | D106: * D1_USG_GRP_L | F106: Left Join
A107: D1_USAGE | B107: USG_SRC_FLG | C107: Usage Source
A108: D1_USAGE | B108: US_ID | C108: Usage Subscription | D108: * D1_US | E108: US_ID
A109: D1_USAGE | B109: VERSION | C109: Version
A110: D1_USAGE | B110: EST_THROUGH_DATE | C110: Estimate Through Date
A111: D1_USAGE | B111: PREV_USG_ID | C111: Previous Usage Transaction
A112: D1_USAGE | B112: BILL_COND_FLG | C112: Bill Condition
A113: D1_USAGE | B113: AUTO_RETRY_FLG | C113: Automated Retry
...

Sheet Meter Read Upload Req1
A1: Summary
A2: Table Name:
A3: Justification:
A4: Designer
A6: Table Name | B6: Field Name | C6: Field Description | D6: Related Table | E6: Filter | F6: Join Type | G6: Designer Notes | H6: Reviewer Notes
A7: D1_ACTIVITY | B7: ACTIVITY_TYPE_CD | C7: Activity Type | D7: D1_ACTIVITY_TYPE | E7: BUS_OBJ_CD=D1-MeterReadDownloadActivity | F7: Left
A8: D1_ACTIVITY | B8: BO_STATUS_CD | C8: Status | D8: F1_BUS_OBJ_STATUS_L | F8: Inner Join
A9: D1_ACTIVITY | B9: BO_STATUS_REASON_CD | C9: Status Reason | D9: F1_BUS_OBJ_STATUS_RSN_L | F9: Left Join
A10: D1_ACTIVITY | B10: BUS_OBJ_CD | C10: Business Object | D10: F1_BUS_OBJ_L | F10: Inner Join
A11: D1_ACTIVITY | B11: CANCEL_REASON | C11: Cancel Reason
A12: D1_ACTIVITY | B12: CRE_DTTM | C12: Create Date/Time | G12: This will be used as the start date to look for the regular read
A13: D1_ACTIVITY | B13: D1_ACTIVITY_ID | C13: Activity ID
A14: D1_ACTIVITY | B14: EFF_DTTM | C14: Effective Date/Time
A15: D1_ACTIVITY | B15: END_DTTM | C15: End Date/Time
A16: D1_ACTIVITY | B16: FIELD_TASK_TYPE | C16: Field Task Type
A17: D1_ACTIVITY | B17: ILM_ARCH_SW | C17: ILM Archive Switch
A18: D1_ACTIVITY | B18: ILM_DT | C18: ILM Date
A19: D1_ACTIVITY | B19: RESCHEDULE_REASON | C19: Reschedule Reason
A20: D1_ACTIVITY | B20: RETENTION_PERIOD | C20: Retention Period
A21: D1_ACTIVITY | B21: START_DTTM | C21: Start Date/Time
A22: D1_ACTIVITY | B22: STATUS_UPD_DTTM | C22: Status Date/Time
A23: D1_ACTIVITY | B23: VERSION | C23: Version
A24: BODA_VIEW | B24: MSRMT_CYC_CD | E24: measurementCycle | G24: This will be used to retrieve the Bill Cycle
A25: BODA_VIEW | B25: SCHED_SELECTION_DT | E25: scheduledSelectionDate
A26: BODA_VIEW | B26: MSRMT_CYC_RTE_CD | E26: route
A27: BODA_VIEW | B27: D1_SCHED_TYPE_FLG | E27: scheduleType
A28: BODA_VIEW | B28: MSRMT_CYC_RTE_SEQ | E28: measurementCycleRouteSequence
A29: BODA_VIEW | B29: D1_MEASR_COMP_ID | E29: mc/mcList/measuringComponentId | G29: The MC Id value will be used to filter the measurement table
A30: BODA_VIEW | B30: ESTM_READING | E30: mc/mcList/estimatedReading
A31: BODA_VIEW | B31: LOW_BOUNDARY_READING | E31: mc/mcList/lowBoundaryReading
A32: BODA_VIEW | B32: HIGH_BOUNDARY_READING | E32: mc/mcList/highBoundaryReading
A33: D1_MSRMT | B33: BO_STATUS_CD | C33: Status | D33: F1_BUS_OBJ_STATUS_L | F33: Inner Join
A34: D1_MSRMT | B34: BUS_OBJ_CD | C34: Business Object | D34: F1_BUS_OBJ_L | F34: Inner Join
A35: D1_MSRMT | B35: COMBINED_MULTIPLIER | C35: Combined Multiplier
A36: D1_MSRMT | B36: CRE_DTTM | C36: Create Date/Time
A37: D1_MSRMT | B37: LAST_UPDATE_DTTM | C37: Last Update Timestamp
A38: D1_MSRMT | B38: MEASR_COMP_ID | C38: Measuring Component ID | D38: D1_ACTIVITY | E38: MEASR_COMP_ID | F38: Left Join
A39: D1_MSRMT | B39: MSRMT_COND_FLG | C39: Condition | D39: * F1_EXT_LOOKUP_VAL * F1_EXT_LOOKUP_VAL_L | E39: lookup BO: D1-MeasurementConditionLookup MSRMT_COND_FLG IN ('501000') | G39: This would only return regular reads related to the period specified
A40: D1_MSRMT | B40: MSRMT_DTTM | C40: Measurement Date/Time | D40: D1_ACTIVITY | E40: Filter using the Create Date Time of the activity up to the end of the bill window | F40: Left Join
A41: D1_MSRMT | B41: MSRMT_LOCAL_DTTM | C41: Local Date/Time
A42: D1_MSRMT | B42: MSRMT_USE_FLG | C42: Measurement Use
A43: D1_MSRMT | B43: MSRMT_VAL | C43: Measurement
A44: D1_MSRMT | B44: MSRMT_VAL1 | C44: Value 1
A45: D1_MSRMT | B45: MSRMT_VAL10 | C45: Value 10
A46: D1_MSRMT | B46: MSRMT_VAL2 | C46: Value 2
A47: D1_MSRMT | B47: MSRMT_VAL3 | C47: Value 3
A48: D1_MSRMT | B48: MSRMT_VAL4 | C48: Value 4
A49: D1_MSRMT | B49: MSRMT_VAL5 | C49: Value 5
A50: D1_MSRMT | B50: MSRMT_VAL6 | C50: Value 6
A51: D1_MSRMT | B51: MSRMT_VAL7 | C51: Value 7
A52: D1_MSRMT | B52: MSRMT_VAL8 | C52: Value 8
... A70: D1_INIT_MSRMT_DATA | B70: IMD_BO_DATA_AREA | C70: IMD Data Area
A71: D1_INIT_MSRMT_DATA | B71: IMD_EXT_ID | C71: External ID | G71: This could be used to group the meter reads that came in per Meter Upload Files
A72: D1_INIT_MSRMT_DATA | B72: INIT_MSRMT_DATA_ID | C72: Initial Measurement Data ID | D72: D1_MSRMT | E72: ORIG_INIT_MSRMT_ID | F72: Left Join | G72: This is the column we would use to filter the IMD table to retrieve the External Id which would correspond to the Meter Read Upload Filename
A73: D1_INIT_MSRMT_DATA | B73: LAST_UPDATE_DTTM | C73: Last Update Timestamp
A74: D1_INIT_MSRMT_DATA | B74: MEASR_COMP_ID | C74: Measuring Component ID
A75: D1_INIT_MSRMT_DATA | B75: POSTVEE_BO_DATA_AREA | C75: Post VEE BO Data Area
A76: D1_INIT_MSRMT_DATA | B76: PREVEE_BO_DATA_AREA | C76: Pre VEE BO Data Area
A77: D1_INIT_MSRMT_DATA | B77: RAW_BO_DATA_AREA | C77: Raw BO Data Area
A78: D1_INIT_MSRMT_DATA | B78: RETENTION_PERIOD | C78: Retention Period
A79: D1_INIT_MSRMT_DATA | B79: STATUS_UPD_DTTM | C79: Status Date/Time
A80: D1_INIT_MSRMT_DATA | B80: TIME_ZONE_CD | C80: Time Zone
A81: D1_INIT_MSRMT_DATA | B81: TRACE_BO_DATA_AREA | C81: Trace BO Data Area
A82: D1_INIT_MSRMT_DATA | B82: VERSION | C82: Version
A84: Sample query that retrieves the Download Meter Activity and the Upload file using the Measuring Component inn the measurement table and related IMD
B85: SELECT act.d1_activity_id, act.cre_dttm, act.start_dttm, act.bo_status_cd, EXTRACTVALUE(act.xml_data, '/ROOT/measurementCycle') AS measurementCycle, EXTRACTVALUE(act.xml_data, '/ROOT/route') AS route, EXTRACTVALUE(act.xml_data, '/ROOT/scheduleType') AS scheduleType, EXTRACTVALUE(act.xml_data, '/ROOT/scheduledSelectionDate') AS scheduledSelectionDate, EXTRACTVALUE(act.xml_data, '/ROOT/mcs/mcList/measuringComponentId') AS measuringComponentId, msrmt.msrmt_dttm, msrmt.reading_val, msrmt.msrmt_val, msrmt.orig_init_msrmt_id, imd.imd_ext_id FROM ( SELECT d1_activity_id, cre_dttm, start_dttm, bo_status_cd, XMLTYPE('<ROOT>' || BO_DATA_AREA || '</ROOT>') AS xml_data, bus_obj_cd FROM cisadm.d1_activity WHERE bus_obj_cd = 'D1-MeterReadDownloadActivity' AND cre_dttm >= TO_DATE('28-APR-25', 'DD-MON-RR') ) act JOIN cisadm.d1_msrmt msrmt ON EXTRACTVALUE(act.xml_data, '/ROOT/mcs/mcList/measuringComponentId') = msrmt.measr_comp_id AND msrmt.msrmt_cond_flg = '501000' AND msrmt.msrmt_dttm BETWEEN TO_DATE('28-APR-25', 'DD-MON-RR') AND TO_DATE('12-MAY-25', 'DD-MON-RR') LEFT JOIN cisadm.d1_init_msrmt_data imd ON msrmt.orig_init_msrmt_id = imd.init_msrmt_data_id
A87: Sample query to get percentage (still needs to be tweaked running the query takes 38.7 seconds to run in TST
A88: WITH meter_read_activities AS ( SELECT d1_activity_id, cre_dttm, start_dttm, bo_status_cd, XMLTYPE('<ROOT>' || BO_DATA_AREA || '</ROOT>') AS xml_data FROM cisadm.d1_activity WHERE bus_obj_cd = 'D1-MeterReadDownloadActivity' AND cre_dttm >= TO_DATE('28-APR-25', 'DD-MON-RR') AND cre_dttm <= TO_DATE('29-APR-25', 'DD-MON-RR') ), expected_meters AS ( SELECT EXTRACTVALUE(xml_data, '/ROOT/mcs/mcList/measuringComponentId') AS measr_comp_id FROM meter_read_activities ), actual_reads AS ( SELECT DISTINCT measr_comp_id FROM cisadm.d1_msrmt WHERE msrmt_dttm BETWEEN TO_DATE('28-APR-25', 'DD-MON-RR') AND TO_DATE('12-MAY-25', 'DD-MON-RR') AND CRE_DTTM BETWEEN TO_DATE('28-APR-25', 'DD-MON-RR') AND TO_DATE('12-MAY-25', 'DD-MON-RR') --AND msrmt_cond_flg = '501000' and orig_init_msrmt_id in (select init_msrmt_data_id from cisadm.d1_init_msrmt_data where imd_ext_id <> ' ') ) SELECT COUNT(DISTINCT e.measr_comp_id) AS total_expected_meters, COUNT(DISTINCT a.measr_comp_id) AS meters_with_reads, ROUND( COUNT(DISTINCT a.measr_comp_id) * 100.0 / NULLIF(COUNT(DISTINCT e.measr_comp_id), 0), 2 ) AS read_completion_percentage FROM expected_meters e LEFT JOIN actual_reads a ON e.measr_comp_id = a.measr_comp_id;
A92: Updated query: SELECT act.d1_activity_id, aro.pk_value1, mc.measr_comp_id, msrmt.msrmt_dttm, msrmt.msrmt_val, imd.imd_ext_id FROM cisadm.d1_activity act JOIN cisadm.d1_activity_rel_obj aro ON act.d1_activity_id = aro.d1_activity_id JOIN cisadm.d1_sp sp ON aro.pk_value1 = sp.d1_sp_id JOIN cisadm.d1_install_evt ie ON sp.d1_sp_id = ie.d1_sp_id JOIN cisadm.d1_measr_comp mc ON ie.device_config_id = mc.device_config_id JOIN cisadm.d1_msrmt msrmt ON mc.measr_comp_id = msrmt.measr_comp_id JOIN cisadm.d1_init_msrmt_data imd ON msrmt.orig_init_msrmt_id = imd.init_msrmt_data_id WHERE ie.bo_status_cd IN ('ON', 'CONN-COMM') AND act.activity_type_cd = 'MRDOWNLOAD' AND act.bo_status_cd = 'EXTRACTED' AND msrmt.msrmt_cond_flg = '501000' AND msrmt.msrmt_dttm >= TO_DATE('14-MAY-25', 'DD-MON-RR') AND ACT.STATUS_UPD_DTTM >= TO_DATE('14-MAY-25', 'DD-MON-RR');

Sheet Meter Read Upload Req2
A1: Summary
A2: Table Name:
A3: Justification:
A4: Designer
A6: Table Name | B6: Field Name | C6: Field Description | D6: Related Table | E6: Filter | F6: Join Type | G6: Designer Notes | H6: Reviewer Notes
A7: D1_MSRMT_CYC_SCHED | B7: BO_DATA_AREA | C7: Business Object Data Area
A8: D1_MSRMT_CYC_SCHED | B8: BUS_OBJ_CD | C8: Business Object
A9: D1_MSRMT_CYC_SCHED | B9: EXP_WRK_DT | C9: Expected Work Date | G9: The date can be used as a filter that the meter is expecting a read on this date. This would be the check the number of meters expected to have reads
A10: D1_MSRMT_CYC_SCHED | B10: MSRMT_CYC_CD | C10: Measurement Cycle | G10: This can be used as a filter on the expected meters
A11: D1_MSRMT_CYC_SCHED | B11: PRE_GEN_RTE_FLG | C11: Pre Generate Route
A12: D1_MSRMT_CYC_SCHED | B12: SCHED_SELECTION_DT | C12: Scheduled Selection Date
A13: D1_MSRMT_CYC_SCHED | B13: VERSION | C13: Version
A14: D1_SP | B14: ACCESS_GRP_CD | C14: Access Group
A15: D1_SP | B15: ADDRESS1 | C15: Address
A16: D1_SP | B16: ADDRESS1_UPPER | C16: Address Line 1 Upper Case
A17: D1_SP | B17: ADDRESS2 | C17: Address 2
A18: D1_SP | B18: ADDRESS3 | C18: Address 3
A19: D1_SP | B19: ADDRESS4 | C19: Address 4
A20: D1_SP | B20: BO_DATA_AREA | C20: Business Object Data Area
A21: D1_SP | B21: BO_STATUS_CD | C21: Status
A22: D1_SP | B22: BO_STATUS_REASON_CD | C22: Status Reason
... A42: D1_SP | B42: MKT_CD | C42: Market
A43: D1_SP | B43: MSRMT_CYC_CD | C43: Measurement Cycle | D43: D1_MSRMT_CYC_SCHED | E43: MSRMT_CYC_CD | F43: Left | G43: This will be used to retrieve the measurement cycle schedule date
A44: D1_SP | B44: MSRMT_CYC_RTE_CD | C44: Route
A45: D1_SP | B45: MSRMT_CYC_RTE_SEQ | C45: Sequence
A46: D1_SP | B46: NUM1 | C46: Number 1
A47: D1_SP | B47: NUM2 | C47: Number 2
A48: D1_SP | B48: POSTAL | C48: Postal
A49: D1_SP | B49: SP_SRC_STAT_FLG | C49: Source Status
A50: D1_SP | B50: STATE | C50: State
A51: D1_SP | B51: STATUS_UPD_DTTM | C51: Status Date/Time
A52: D1_SP | B52: TIME_ZONE_CD | C52: Time Zone
A53: D1_SP | B53: VERSION | C53: Version
A54: D1_INSTALL_EVT | B54: ARM_STAT_FLG | C54: Arming Status
A55: D1_INSTALL_EVT | B55: BO_DATA_AREA | C55: Business Object Data Area
A56: D1_INSTALL_EVT | B56: BO_STATUS_CD | C56: Status | E56: BO_STATUS_CD in ('ON','CONN-COMM') | F56: Inner | G56: Use this filter to ensure the Meter is installed
A57: D1_INSTALL_EVT | B57: BO_STATUS_REASON_CD | C57: Status Reason
A58: D1_INSTALL_EVT | B58: BUS_OBJ_CD | C58: Business Object
A59: D1_INSTALL_EVT | B59: CRE_DTTM | C59: Create Date/Time
A60: D1_INSTALL_EVT | B60: D1_INSTALL_DTTM | C60: Installation Date/Time
A61: D1_INSTALL_EVT | B61: D1_REMOVAL_DTTM | C61: Removal Date/Time
A62: D1_INSTALL_EVT | B62: D1_SP_ID | C62: Service Point ID | D62: D1_SP | E62: D1_SP_ID | F62: Inner
A63: D1_INSTALL_EVT | B63: DEVICE_CONFIG_ID | C63: Device Configuration | G63: This will be retrieved using the filter for status and sp id
A64: D1_INSTALL_EVT | B64: INSTALLATION_CONST | C64: Installation Constant
A65: D1_INSTALL_EVT | B65: INSTALL_EVT_ID | C65: Install Event ID
A66: D1_INSTALL_EVT | B66: STATUS_UPD_DTTM | C66: Status Date/Time
A67: D1_INSTALL_EVT | B67: VERSION | C67: Version
A68: D1_MEASR_COMP | B68: ACCESS_GRP_CD | C68: Access Group
A69: D1_MEASR_COMP | B69: ADJ_LATEST_MSRMT_DTTM | C69: Adjust Latest Measurement Date/Time
A70: D1_MEASR_COMP | B70: ATTR_VAL_ID | C70: Attribute Value ID
A71: D1_MEASR_COMP | B71: BO_DATA_AREA | C71: Business Object Data Area
A72: D1_MEASR_COMP | B72: BO_STATUS_CD | C72: Status
A73: D1_MEASR_COMP | B73: BO_STATUS_REASON_CD | C73: Status Reason
A74: D1_MEASR_COMP | B74: BUS_OBJ_CD | C74: Business Object
A75: D1_MEASR_COMP | B75: CRE_DTTM | C75: Create Date/Time
... A79: D1_MEASR_COMP | B79: D1_READ_SEQ | C79: Read Sequence
A80: D1_MEASR_COMP | B80: DEVICE_CONFIG_ID | C80: Device Configuration | D80: D1_INSTALL_EVT | E80: DEVICE_CONFIG_ID | F80: Left
A81: D1_MEASR_COMP | B81: LATEST_MSRMT_DTTM | C81: Latest Measurement Date/Time
A82: D1_MEASR_COMP | B82: MEASR_COMP_ID | C82: Measuring Component ID | G82: Retrieve the MC Id using the device configuration from the Install Event
A83: D1_MEASR_COMP | B83: MEASR_COMP_MULTIPLIER | C83: Measuring Component Multiplier
A84: D1_MEASR_COMP | B84: MEASR_COMP_TYPE_CD | C84: Measuring Component Type
A85: D1_MEASR_COMP | B85: MEASR_COMP_USAGE_FLG | C85: How To Use
A86: D1_MEASR_COMP | B86: MOST_RECENT_MSRMT_DTTM | C86: Most Recent Read Date/Time
A87: D1_MEASR_COMP | B87: MOST_RECENT_MSRMT_READING_COND | C87: Most Recent Read Condition
A88: D1_MEASR_COMP | B88: MOST_RECENT_MSRMT_READING_VAL | C88: Most Recent Read Value
A89: D1_MEASR_COMP | B89: MOST_RECENT_NON_EST_MSRMT_DTTM | C89: Most Recent Non Estimated Read Date/Time
A90: D1_MEASR_COMP | B90: STATUS_UPD_DTTM | C90: Status Date/Time
A91: D1_MEASR_COMP | B91: TIME_ZONE_CD | C91: Time Zone
A92: D1_MEASR_COMP | B92: USER_ID | C92: User
A93: D1_MEASR_COMP | B93: VERSION | C93: Version
A94: D1_MSRMT | B94: BO_STATUS_CD | C94: Status
... A98: D1_MSRMT | B98: LAST_UPDATE_DTTM | C98: Last Update Timestamp
A99: D1_MSRMT | B99: MEASR_COMP_ID | C99: Measuring Component ID | D99: D1_MEASR_COMP | E99: MEASR_COMP_ID
A100: D1_MSRMT | B100: MSRMT_COND_FLG | C100: Condition | D100: F1_EXT_LOOKUP_VAL F1_EXT_LOOKUP_VAL_L | E100: lookup BO: D1-MeasurementConditionLookup MSRMT_COND_FLG IN ('501000') | G100: In order to create the percentage, need to count the number of regular against other condition codes
A101: D1_MSRMT | B101: MSRMT_DTTM | C101: Measurement Date/Time
A102: D1_MSRMT | B102: MSRMT_LOCAL_DTTM | C102: Local Date/Time
A103: D1_MSRMT | B103: MSRMT_USE_FLG | C103: Measurement Use
A104: D1_MSRMT | B104: MSRMT_VAL | C104: Measurement
A105: D1_MSRMT | B105: MSRMT_VAL1 | C105: Value 1
A106: D1_MSRMT | B106: MSRMT_VAL10 | C106: Value 10
A107: D1_MSRMT | B107: MSRMT_VAL2 | C107: Value 2
A108: D1_MSRMT | B108: MSRMT_VAL3 | C108: Value 3
A109: D1_MSRMT | B109: MSRMT_VAL4 | C109: Value 4
A110: D1_MSRMT | B110: MSRMT_VAL5 | C110: Value 5
A111: D1_MSRMT | B111: MSRMT_VAL6 | C111: Value 6
A112: D1_MSRMT | B112: MSRMT_VAL7 | C112: Value 7
... A114: D1_MSRMT | B114: MSRMT_VAL9 | C114: Value 9
A115: D1_MSRMT | B115: ORIG_INIT_MSRMT_ID | C115: Initial Measurement | D115: D1_INIT_MSRMT_DATA | E115: INIT_MSRMT_DATA_ID | F115: Left
A116: D1_MSRMT | B116: PREV_MSRMT_DTTM | C116: Previous Measurement Date/Time
A117: D1_MSRMT | B117: READING_COND_FLG | C117: Reading Condition
A118: D1_MSRMT | B118: READING_VAL | C118: Reading Value
A119: D1_MSRMT | B119: STATUS_UPD_DTTM | C119: Status Date/Time
A120: D1_MSRMT | B120: USER_EDITED_FLG | C120: User Edited
A121: D1_MSRMT | B121: VERSION | C121: Version
A122: D1_INIT_MSRMT_DATA | B122: BO_STATUS_CD | C122: Status | G122: Noticed in CS TEST there were IMD's with a Discard status but it came from an upload file
A123: D1_INIT_MSRMT_DATA | B123: BO_STATUS_REASON_CD | C123: Status Reason
A124: D1_INIT_MSRMT_DATA | B124: BUS_OBJ_CD | C124: Business Object
A125: D1_INIT_MSRMT_DATA | B125: CRE_DTTM | C125: Create Date/Time
A126: D1_INIT_MSRMT_DATA | B126: D1_FROM_DTTM | C126: From Date/Time
A127: D1_INIT_MSRMT_DATA | B127: D1_TO_DTTM | C127: To Date/Time
...

Sheet D1_SP_MSRMT_CYC_SCHED_RTE
B1: Summary
B2: Table Name: D1_SP_MSRMT_CYC_SCHED_RTE
B3: Justification:
B4: Designer: | C4: =Summary!I127 -> Lennice
A7: Table Name | B7: Field Name | C7: Field Description | D7: Related Table / XPAth | E7: Filter | F7: Join Type | G7: Designer Notes | H7: Reviewer Notes
A8: D1_SP_MSRMT_CYC_SCHED_RTE | B8: BO_STATUS_CD | C8: Status
A9: D1_SP_MSRMT_CYC_SCHED_RTE | B9: BO_STATUS_REASON_CD | C9: Status Reason
A10: D1_SP_MSRMT_CYC_SCHED_RTE | B10: BUS_OBJ_CD | C10: Business Object
A11: D1_SP_MSRMT_CYC_SCHED_RTE | B11: CRE_DTTM | C11: Create Date/Time
A12: D1_SP_MSRMT_CYC_SCHED_RTE | B12: D1_SP_ID | C12: Service Point ID | D12: * D1_SP
A13: D1_SP_MSRMT_CYC_SCHED_RTE | B13: MSRMT_CYC_CD | C13: Measurement Cycle | D13: * D1_MSRMT_CYC_L
A14: D1_SP_MSRMT_CYC_SCHED_RTE | B14: MSRMT_CYC_RTE_CD | C14: Route | D14: * D1_MSRMT_CYC_RTE_L
A15: D1_SP_MSRMT_CYC_SCHED_RTE | B15: SCHED_SELECTION_DT | C15: Scheduled Selection Date | D15: * D1_SP_MSRMT_CYC_SCHED_RTE
A16: D1_SP_MSRMT_CYC_SCHED_RTE | B16: STATUS_UPD_DTTM | C16: Status Date/Time
A17: D1_SP_MSRMT_CYC_SCHED_RTE | B17: VERSION | C17: Version
A18: D1_INSTALL_EVT | B18: INSTALL_EVT_ID | C18: Install Event Id | D18: * D1_INSTALL_EVT | E18: DEVICE_CONFIG_ID | F18: Left Outer
A19: D1_INSTALL_EVT | B19: D1_SP_ID | C19: Service Point Id | D19: * D1_INSTALL_EVT | F19: Inner Join
A20: D1_INSTALL_EVT | B20: BO_STATUS_CD | C20: Status | D20: * D1_INSTALL_EVT | E20: BO_STATUS_CD IN ('ON','CONN-COMM') | F20: Inner Join | G20: This is filter is used to retrieve the meter currently installed on the SP at a given date
A21: D1_MEASR_COMP | B21: MEASR_COMP_ID | C21: Measuring Component ID | D21: * D1_MEASR_COMP | E21: DEVICE_CONFIG_ID | F21: Inner Join | G21: This is dependent if the Install Event is Connected/Commissioned or ON
A22: D1_MEASR_COMP | B22: MEASR_COMP_TYPE_CD | C22: Measuring Component Type | D22: * D1_MEASR_COMP_TYPE_L | F22: Inner Join
A23: D1_MEASR_COMP | B23: LATEST_MSRMT_DTTM | C23: Latest Measurement Date/Time | D23: * D1_MEASR_COMP | F23: Left Outer | G23: This would only provide the most recent non estimated read date but not the actual measurement value.
A24: D1_MEASR_COMP | B24: MOST_RECENT_NON_EST_MSRMT_DTTM | C24: Most Recent Non Estimated Read Date/Time | D24: * D1_MEASR_COMP | F24: Left Outer | G24: This would only provide the most recent non estimated read date but not the actual measurement value.
A25: D1_MSRMT | B25: MEASR_COMP_ID | C25: Measuring Component ID | D25: * D1_MEASR_COMP | E25: MEASR_COMP_ID | F25: Left Outer
A26: D1_MSRMT | B26: MSRMT_DTTM | C26: Measurement Date/Time | D26: * D1_MSRMT | E26: MSRMT_DTTM >=MOST_RECENT_MSRMT_DTTM | F26: Left Outer
A27: D1_MSRMT | B27: MSRMT_VAL | C27: Measurement | D27: * D1_MSRMT | E27: Retrieve estimated reads AND MSRMT_COND_FLG <> '501000' Retrieve Regular reads AND MSRMT_COND_FLG = '501000' | F27: Left Outer | G27: Need to have separate filter for regular and estimated reads per route
A28: D1_MSRMT | B28: MSRMT_COND_FLG | C28: Condition | D28: * F1_EXT_LOOKUP_VAL_L | E28: BUS_OBJ_CD='D1-MeasurementConditionLookup' | F28: Left Outer

Sheet F1_BNDL
B1: Summary
B2: Table Name: F1_BNDL
B3: Justification | C3: =Summary!O163 -> On a release management standpoint, wherein one query will allow us to know what is released or installed for a certain period
A5: Table Name | B5: Field Name | C5: Field Description | D5: Related Table | E5: Filter | F5: Join Type | G5: Designer Notes | H5: Reviewer Notes
A6: F1_BNDL | B6: BNDL_ID (PK) | C6: Bundle ID | D6: F1_BNDL_ENTITY | F6: Left Join | G6: Bundle will not have a Bundle Entity if not yet Applied
A7: F1_BNDL | B7: BNDL_TYPE_FLG | C7: Bundle Type | D7: CI_LOOKUP_VAL_L | F7: Inner Join
A8: F1_BNDL | B8: BUS_OBJ_CD | C8: Business Object | D8: F1_BUS_OBJ_L | F8: Inner Join
A9: F1_BNDL | B9: BO_STATUS_CD | C9: Status | D9: F1_BUS_OBJ_STATUS_L | F9: Inner Join
A10: F1_BNDL | B10: STATUS_UPD_DTTM | C10: Status Date/Time | D10: N/A | F10: N/A
A11: F1_BNDL | B11: CRE_DTTM | C11: Create Date/Time | D11: N/A | F11: N/A
A12: F1_BNDL | B12: USER_ID | C12: User | D12: SC_USER | F12: Inner Join
A13: F1_BNDL | B13: EXT_REFERENCE_ID | C13: External Reference ID | D13: N/A | F13: N/A | G13: This is the Bundle Name
A14: F1_BNDL | B14: VERSION | C14: Version | D14: N/A | F14: N/A
A15: F1_BNDL | B15: DESCRLONG | C15: Detailed Description | D15: N/A | F15: N/A
A16: F1_BNDL | B16: BNDL_DETAIL | C16: Bundle Detail
A17: F1_BNDL_ENTTY | B17: BNDL_ID (PK) | C17: Bundle ID | D17: N/A | F17: N/A | G17: Bundle Entity is Left Joined to Bundle Object on row #2
A18: F1_BNDL_ENTTY | B18: SEQNO (PK) | C18: Sequence | D18: N/A | F18: N/A
A19: F1_BNDL_ENTTY | B19: MAINT_OBJ_CD | C19: Maintenance Object | D19: CI_MD_MO_L | F19: Inner Join
A20: F1_BNDL_ENTTY | B20: PROC_SEQ | C20: Processing Sequence | D20: N/A | F20: N/A
A21: F1_BNDL_ENTTY | B21: PK_VALUE1 | C21: Primary Key 1 | D21: N/A | F21: N/A
A22: F1_BNDL_ENTTY | B22: PK_VALUE2 | C22: Primary Key 2 | D22: N/A | F22: N/A
A23: F1_BNDL_ENTTY | B23: PK_VALUE3 | C23: Primary Key 3 | D23: N/A | F23: N/A
A24: F1_BNDL_ENTTY | B24: PK_VALUE4 | C24: Primary Key 4 | D24: N/A | F24: N/A
A25: F1_BNDL_ENTTY | B25: PK_VALUE5 | C25: Primary Key 5 | D25: N/A | F25: N/A
A26: F1_BNDL_ENTTY | B26: VERSION | C26: Version | D26: N/A | F26: N/A
A27: F1_BNDL_ENTTY | B27: USER_ID | C27: User | D27: SC_USER | F27: Left Join

Sheet F1_MIGR_DATA_ST
A1: Summary
A2: Table Name: F1_MIGR_DATA_ST
A3: Justification | B3: =Summary!O175 -> On a release management standpoint, wherein one query will allow us to know what is released or installed for a certain period
A5: Table Name | B5: Field Name | C5: Field Description | D5: Related Table | E5: Filter | F5: Join Type | G5: Designer Notes | H5: Reviewer Notes
A6: F1_MIGR_DATA_ST | B6: MIGR_DATA_SET_ID | C6: Migration Data Set | D6: F1_MIGR_TRANS | F6: Left Join | G6: Migration Data Set will not have a Migration Transaction if not yet Applied
A7: F1_MIGR_DATA_ST | B7: BUS_OBJ_CD | C7: Business Object | D7: F1_BUS_OBJ_L | F7: Inner Join
A8: F1_MIGR_DATA_ST | B8: BO_STATUS_CD | C8: Status | D8: F1_BUS_OBJ_STATUS_L | F8: Inner Join
A9: F1_MIGR_DATA_ST | B9: STATUS_UPD_DTTM | C9: Status Date/Time | D9: N/A | F9: N/A
A10: F1_MIGR_DATA_ST | B10: BO_STATUS_REASON_CD | C10: Status Reason | D10: F1_BUS_OBJ_STATUS_RSN_L | F10: Left Join
A11: F1_MIGR_DATA_ST | B11: MIGR_REQ_CD | C11: Migration Request | D11: F1_MIGR_REQ_L | F11: Left Join
A12: F1_MIGR_DATA_ST | B12: EXT_REFERENCE_ID | C12: External Reference ID | D12: N/A | F12: N/A | G12: This is the CMA Name
A13: F1_MIGR_DATA_ST | B13: EXPORT_DTTM | C13: Export Date/Time | D13: N/A | F13: N/A
A14: F1_MIGR_DATA_ST | B14: COMPARE_DTTM | C14: Compare Date/Time | D14: N/A | F14: N/A
A15: F1_MIGR_DATA_ST | B15: MIGR_FILENAME | C15: Migration File Name | D15: N/A | F15: N/A | G15: This is the CMA File Name
A16: F1_MIGR_DATA_ST | B16: ADD_BO_STATUS_CD | C16: Default Status for Add | D16: F1_BUS_OBJ_STATUS_L | F16: Left Join
A17: F1_MIGR_DATA_ST | B17: CHG_BO_STATUS_CD | C17: Default Status for Change | D17: F1_BUS_OBJ_STATUS_L | F17: Left Join
A18: F1_MIGR_DATA_ST | B18: VERSION | C18: Version | D18: N/A | F18: N/A
A19: F1_MIGR_DATA_ST | B19: CRE_DTTM | C19: Create Date/Time | D19: N/A | F19: N/A
A20: F1_MIGR_DATA_ST | B20: USER_ID | C20: User | D20: SC_USER | F20: Inner Join
A21: F1_MIGR_DATA_ST | B21: TRANS_RETRY_NBR | C21: Transaction Retry Number | D21: N/A | F21: N/A
A22: F1_MIGR_DATA_ST | B22: OBJ_RETRY_NBR | C22: Object Retry Number | D22: N/A | F22: N/A
A23: F1_MIGR_DATA_ST | B23: MIGR_FILEVERSION | C23: Migration File Number | D23: N/A | F23: N/A
A24: F1_MIGR_DATA_ST | B24: BULK_IMPORT_FLG | C24: Bulk Import | D24: CI_LOOKUP_VAL_L | F24: Left Join
A25: F1_MIGR_DATA_ST | B25: REDACT_OPT_FLG | C25: Redaction Option | D25: CI_LOOKUP_VAL_L | F25: Left Join
A26: F1_MIGR_DATA_ST | B26: INSERT_ONLY_FLG | C26: Insert Only | D26: CI_LOOKUP_VAL_L | F26: Left Join
A27: F1_MIGR_TRANS | B27: MIGR_TRANS_ID (PK) | C27: Migration Transaction | D27: N/A | F27: N/A
A28: F1_MIGR_TRANS | B28: MIGR_DATA_SET_ID | C28: Migration Data Set | D28: N/A | F28: N/A | G28: Migration Transaction is Left Joined to Migration Data Set on row #2
A29: F1_MIGR_TRANS | B29: BUS_OBJ_CD | C29: Business Object | D29: F1_BUS_OBJ_L | F29: Inner Join
A30: F1_MIGR_TRANS | B30: BO_STATUS_CD | C30: Status | D30: F1_BUS_OBJ_STATUS_L | F30: Inner Join
A31: F1_MIGR_TRANS | B31: STATUS_UPD_DTTM | C31: Status Date/Time | D31: N/A | F31: N/A
A32: F1_MIGR_TRANS | B32: BO_STATUS_REASON_CD | C32: Status Reason | D32: F1_BUS_OBJ_STATUS_RSN_L | F32: Left Join
A33: F1_MIGR_TRANS | B33: MIGR_PLAN_CD | C33: Migration Plan | D33: F1_MIGR_PLAN_L | F33: Left Join
A34: F1_MIGR_TRANS | B34: MAINT_OBJ_CD | C34: Maintenance Object | D34: CI_MD_MO_L | F34: Inner Join
A35: F1_MIGR_TRANS | B35: PK_VALUE1 | C35: Primary Key 1 | D35: N/A | F35: N/A
A36: F1_MIGR_TRANS | B36: PK_VALUE2 | C36: Primary Key 2 | D36: N/A | F36: N/A
A37: F1_MIGR_TRANS | B37: PK_VALUE3 | C37: Primary Key 3 | D37: N/A | F37: N/A
A38: F1_MIGR_TRANS | B38: PK_VALUE4 | C38: Primary Key 4 | D38: N/A | F38: N/A
A39: F1_MIGR_TRANS | B39: PK_VALUE5 | C39: Primary Key 5 | D39: N/A | F39: N/A
A40: F1_MIGR_TRANS | B40: VERSION | C40: Version | D40: N/A | F40: N/A
... A42: F1_MIGR_TRANS | B42: TRANS_RETRY_NBR | C42: Transaction Retry Number | D42: N/A | F42: N/A

Sheet CI_PREM
A1: Summary
A2: Table Name: CI_PREM
A3: Justification: This domain will retrieve Premise Information, Service Point Information as well as the related Account and Bill Cycle
A4: Designer: Lennice
A6: Table | B6: Field Name | C6: Field Description | D6: Related Table | F6: Join Type | G6: Designer Notes
A7: CI_PREM | B7: PREM_ID | C7: Premise ID | D7: N/A | F7: N/A
A8: CI_PREM | B8: PREM_TYPE_CD | C8: Premise Type | D8: * CI_PREM_TYPE_L | F8: Inner Join
A9: CI_PREM | B9: CIS_DIVISION | C9: CIS Division | D9: *CI_CIS_DIVISION | F9: Left Join
A10: CI_PREM | B10: LL_ID | C10: Landlord Agreement ID | D10: * CI_LANDLORD | F10: Left Join
A11: CI_PREM | B11: KEY_SW | C11: Key | D11: N/A | F11: N/A
A12: CI_PREM | B12: KEY_ID | C12: Key ID | D12: N/A | F12: N/A
A13: CI_PREM | B13: OK_TO_ENTER_SW | C13: OK to Enter | D13: N/A | F13: N/A
A14: CI_PREM | B14: MR_INSTR_CD | C14: Meter Read Instruction | D14: * CI_MR_INSTR_L | F14: Left Join
A15: CI_PREM | B15: MR_INSTR_DETAILS | C15: Instruction Details | D15: N/A | F15: N/A
A16: CI_PREM | B16: MR_WARN_CD | C16: Meter Read Warning | D16: * CI_MR_WARN_L | F16: Left Join
A17: CI_PREM | B17: TREND_AREA_CD | C17: Trend Area | D17: * CI_TREND_AREA_L | F17: Left Join
A18: CI_PREM | B18: ADDRESS1 | C18: Address | D18: N/A | F18: N/A
... A36: CI_PREM | B36: LS_SL_DESCR | C36: Life Support / Sensitive Load | D36: N/A | F36: N/A
A37: CI_PREM | B37: PRNT_PREM_ID | C37: Parent Premise ID | F37: Left Outer
A38: CI_PREM | B38: ADDRESS1_UPR | C38: Address Uppercase | D38: N/A | F38: N/A
A39: CI_PREM | B39: CITY_UPR | C39: City Uppercase | D39: N/A | F39: N/A
A40: CI_PREM_CHAR | B40: ADHOC_CHAR_VAL | C40: Adhoc Characteristic Value
A41: CI_PREM_CHAR | B41: CHAR_TYPE_CD | C41: Characteristic Type
A42: CI_PREM_CHAR | B42: CHAR_VAL | C42: Characteristic Value
A43: CI_PREM_CHAR | B43: CHAR_VAL_FK1 | C43: Characteristic Value FK 1
A44: CI_PREM_CHAR | B44: CHAR_VAL_FK2 | C44: Characteristic Value FK 2
A45: CI_PREM_CHAR | B45: CHAR_VAL_FK3 | C45: Characteristic Value FK 3
A46: CI_PREM_CHAR | B46: CHAR_VAL_FK4 | C46: Characteristic Value FK 4
A47: CI_PREM_CHAR | B47: CHAR_VAL_FK5 | C47: Characteristic Value FK 5
A48: CI_PREM_CHAR | B48: EFFDT | C48: Effective Date
A49: CI_PREM_CHAR | B49: PREM_ID | C49: Premise ID | D49: *CI_PREM | E49: PREM_ID | F49: Left
A50: CI_PREM_CHAR | B50: SRCH_CHAR_VAL | C50: Search Characteristic Value
A51: CI_PREM_CHAR | B51: VERSION | C51: Version
A52: CI_PREM_CHAR | B52: get the value whose char type code is xxx | E52: CHAR_TYPE_CD IN (C2MRESTY,IN-OUT)
A53: CI_PREM_GEO | B53: GEO_TYPE_CD | C53: Geographic Type | E53: GEO_TYPE_CD: Lat/Long. | G53: identify common geotype
A54: CI_PREM_GEO | B54: GEO_VAL | C54: Geographic Value
A55: CI_PREM_GEO | B55: PREM_ID | C55: Premise ID
A56: CI_PREM_GEO | B56: VERSION | C56: Version
A57: CI_SA | B57: ACCT_ID | C57: Account ID
A58: CI_SA | B58: ALLOW_EST_SW | C58: Allow Estimates
A59: CI_SA | B59: BUS_ACTIVITY_DESC | C59: Business Activity
A60: CI_SA | B60: CHAR_PREM_ID | C60: Premise ID | D60: *CI_PREM | E60: PREM_ID | F60: Left
A61: CI_SA | B61: CIAC_REVIEW_DT | C61: CIAC Review Date
A62: CI_SA | B62: CIS_DIVISION | C62: CIS Division
A63: CI_SA | B63: CURRENCY_CD | C63: Currency Code
A64: CI_SA | B64: CUST_READ_FLG | C64: Customer Read
A65: CI_SA | B65: END_DT | C65: End Date
A66: CI_SA | B66: ENRL_ID | C66: Order ID
A67: CI_SA | B67: EXPIRE_DT | C67: Expire Date
A68: CI_SA | B68: HIGH_BILL_AMT | C68: Maximum Bill Threshold
A69: CI_SA | B69: IB_BASE_TM_DAY_FLG | C69: Start Day Option
A70: CI_SA | B70: IB_SA_CUTOFF_TM | C70: IB SA Cutoff Time
A71: CI_SA | B71: INT_CALC_DT | C71: Deposit Interest Calculated
A72: CI_SA | B72: NBR_PYMNT_PERIODS | C72: Number of Payment Periods
... A82: CI_SA | B82: SA_REL_ID | C82: SA Relationship ID
A83: CI_SA | B83: SA_STATUS_FLG | C83: SA Status | D83: *CI_LOOKUP_VAL_L | G83: Add a filter, the user can choose the status of the SA relarted to the Premsie
A84: CI_SA | B84: SA_TYPE_CD | C84: SA Type
A85: CI_SA | B85: SIC_CD | C85: SIC
A86: CI_SA | B86: SPECIAL_USAGE_FLG | C86: Special Usage
A87: CI_SA | B87: START_DT | C87: Start Date
A88: CI_SA | B88: START_OPT_CD | C88: Start Option
A89: CI_SA | B89: STOP_REQED_BY | C89: Stop Requested By
A90: CI_SA | B90: STOP_RSN_FLG | C90: Stop Reason
A91: CI_SA | B91: STRT_REQED_BY | C91: Start Requested By
A92: CI_SA | B92: STRT_RSN_FLG | C92: Start Reason
A93: CI_SA | B93: TOT_TO_BILL_AMT | C93: Total Amount to Bill
A94: CI_SA | B94: VERSION | C94: Version
A95: CI_ACCT | D95: *CI_SA | E95: ACCT_ID
A96: CI_ACCT_PER | D96: *CI_ACCT | E96: ACCT_ID
A97: CI_PER_NAME | B97: Just get the name
A98: CI_LANDLORD | B98: ACCT_ID | C98: Account ID
A99: CI_LANDLORD | B99: DESCR | C99: Description
A100: CI_LANDLORD | B100: DESCR_UPR | C100: Description
A101: CI_LANDLORD | B101: LL_ID | C101: Landlord Agreement ID | D101: *CI_PREM | E101: LL_ID | F101: Left
A102: CI_LANDLORD | B102: VERSION | C102: Version
A106: Josh Suggestions:
A107: CI_PREM | B107: full display; all foreign keys with description
A108: CI_PREM_GEO | B108: create a database view that extracts the folloiwng; yes there are three, but for future projects, we will use separate LAT and LONG.
B109: * LAT/LONG
B110: * LAT
B111: * LONG
A112: CI_PREM_CHAR | B112: I don't think there's anything that is generic (part of DV) where we put PREM_CHAR. For this case, we don't need to include this for now.
A113: CI_SA | B113: full display; some foreign keys with description; refer to BSEG Exception; via char prem id
A114: CI_ACCT | B114: full display; some foreign keys with description; refer to BSEG Exception
A115: Name | B115: Via CI_ACCT, CI_ACCT_PER and CI_PER_NAME with name type flag = PRIM and Main Customer Switch = Y
A117: Formula | B117: First five digit of the postal code from the premise
A119: Location | B119: Customer Operations/Premise
A120: Ad Hoc View Tabular 1 | B120: Name, Address Upper, City Upper, SA ID, SA Type, SA Status, Account ID, Customer Class
B121: filter: name, starts with; address upper, starts with, customer class desc one of; sa type description, one of.
A122: Ad Hoc View 1 | B122: Count of distinct premises, grouped by Premise Type; cross tab
B123: filter: premise type desc, one of
A124: Ad Hoc View 2 | B124: Count of distinct premises, group by Postal (first five digits); cross tab
B125: filter: postal 5 (one of); premise type, one-of
A126: Dashboard | B126: Combination of Ad Hoc Views 1 and 2.
B127: filter is premise type

Sheet W1_ASSET
A1: Summary
A2: Table Name: W1_ASSET
A3: Justification | B3: =Summary!O199 -> Asset is the equivalent for M-Side's Device Record. The only difference with Asset record is that it stores the history of the movement of the Asset from the Storage Location until its installed to actual SP / Location. This is helpful for the Clients as it allows them to fetch available Assets from the Storeroom that can be installed at an available location.
A5: Table Name | B5: Field Name | C5: Field Description | D5: Related Table | E5: Filter | F5: Join Type | G5: Designer Notes | H5: Reviewer Notes
A6: W1_ASSET | B6: ASSET_ID | C6: Asset | D6: * W1_ASSET_NODE * W1_ASSET_CHAR? * CMS_W1_ASSET_IDENTIFIER_VW | F6: Left Join - W1_ASSET_CHAR Inner Join - W1_ASSET_NODE Inner Join - W1_ASSET_IDENTIFIER | G6: Asset can have 0 to many Chars Asset Node is the history of the movement of Asset from Location to Another. This should be 1 to many
A7: W1_ASSET | B7: ASSET_TYPE_CD | C7: Asset Type | D7: W1_ASSET_TYPE_L | F7: Inner Join
A8: W1_ASSET | B8: BUS_OBJ_CD | C8: Business Object | D8: F1_BUS_OBJ_L | F8: Inner Join
A9: W1_ASSET | B9: BO_STATUS_CD | C9: Status | D9: F1_BUS_OBJ_STATUS_L | F9: Inner Join
A10: W1_ASSET | B10: STATUS_UPD_DTTM | C10: Status Date/Time | D10: N/A | F10: N/A
A11: W1_ASSET | B11: BO_STATUS_REASON_CD | C11: Status Reason | D11: F1_BUS_OBJ_STATUS_RSN_L | F11: Left Join
A12: W1_ASSET | B12: ASSET_COND_FLG | C12: Asset Condition | D12: CI_LOOKUP_VAL_L | F12: Left Join
A13: W1_ASSET | B13: SPECIFICATION_CD | C13: Specification | D13: W1_SPECIFICATION_L | F13: Left Join
A14: W1_ASSET | B14: CRE_DTTM | C14: Create Date/Time | D14: N/A | F14: N/A
A15: W1_ASSET | B15: VERSION | C15: Version | D15: N/A | F15: N/A
A16: W1_ASSET | B16: ACT_ID | C16: Activity | D16: W1_ASSET_ACTIVITY | F16: Left Join | G16: Asset can be created via the Asset Replicator Asset Activity
A17: W1_ASSET | B17: FINAL_DTTM | C17: Final Date/Time | D17: N/A | F17: N/A
A18: W1_ASSET | B18: OWNING_ACCESS_GRP_CD | C18: Owning Organization | D18: CI_ACC_GRP_L | F18: Left Join
A19: W1_ASSET | B19: CONDITION_RATING | C19: Condition Rating | D19: N/A | F19: N/A
A20: W1_ASSET | B20: CONFIDENCE_RATING | C20: Confidence Rating | D20: N/A | F20: N/A
A21: W1_ASSET | B21: BOM_PART_ID | C21: BOM Part | D21: W1_BOM_PART *** Get Description from BOM_PART_DESCR Column | F21: Left Join
A22: W1_ASSET | B22: UNIT_PRICE | C22: Unit Price | D22: N/A | F22: N/A
A23: W1_ASSET | B23: VENDOR_LOC_ID | C23: Vendor Location | D23: W1_VENDOR_LOC *** Get Description from LOC_NAME Column | F23: Left Join
A24: W1_ASSET | B24: DESCRLONG | C24: Detailed Description | D24: N/A | F24: N/A
A25: W1_ASSET | B25: MAINT_SPEC_CD | C25: Maintenance Specification | D25: W1_SPECIFICATION_L | F25: Left Join
A26: W1_ASSET | B26: PROPERTY_UNIT_CD | C26: Property Unit | D26: W1_PROPERTY_UNIT_L | F26: Left Join
A27: W1_ASSET | B27: CST_SCORE | C27: Cost Score | D27: N/A | F27: N/A
A28: W1_ASSET | B28: CST_SCR_DTTM | C28: Cost Score Date Time | D28: N/A | F28: N/A
... A47: W1_ASSET | B47: USEFUL_LIFE | C47: Useful Life (Years) | D47: N/A | F47: N/A
A48: W1_ASSET | B48: BO_DATA_AREA: configuration (no display; no mapping) | C48: Configuration | F48: N/A | G48: No mapping needed. This configuration dictates which device and measurement configurations will be created on the D1 side during the sync process. This information is already available on the device related tables (D1 Tables).
A49: W1_ASSET | B49: BO_DATA_AREA: configurationDateTime (no display; no mapping) | C49: Configuration Date Time | F49: N/A
A50: W1_ASSET | B50: BO_DATA_AREA: c2mDeviceId (no display; no mapping) | C50: Device ID | F50: N/A | G50: No mapping needed. This is the M-Side Device ID which is stored on the Asset Identifier with Type of EI
A51: W1_ASSET | B51: BO_DATA_AREA: warrantyDetail (no display; no mapping) | C51: Warranty Detail | F51: N/A | G51: No mapping needed
A52: W1_ASSET_CHAR | D52: N/A | F52: N/A
A53: CMS_W1_ASSET_IDENTIFIER_VW | B53: ASSET_ID | C53: Asset | D53: N/A | F53: N/A | G53: Asset Identifier is Inner Joined to Asset Table on row #2
A54: CMS_W1_ASSET_IDENTIFIER_VW | B54: EXTERNAL_ID | C54: Asset Identifier Type | D54: N/A | E54: ASSET_ID_TYPE_FLG = W1EI | F54: Inner Join | G54: Join Type set to Inner Join because Assets are required to have a Badge Number
A55: CMS_W1_ASSET_IDENTIFIER_VW | B55: PALLET_NUMBER | C55: Pallet Number | D55: N/A | E55: ASSET_ID_TYPE_FLG = W1PN | F55: N/A
A56: CMS_W1_ASSET_IDENTIFIER_VW | B56: SERIAL_NUMBER | C56: Serial Number | D56: N/A | E56: ASSET_ID_TYPE_FLG = W1SN | F56: N/A
A57: CMS_W1_ASSET_IDENTIFIER_VW | B57: BADGE_NUMBER | C57: Badge Number | D57: N/A | E57: ASSET_ID_TYPE_FLG = W1BN | F57: N/A
A58: CMS_W1_ASSET_IDENTIFIER_VW | B58: PURCHASE_ORDER | C58: Purchase Order | D58: N/A | E58: ASSET_ID_TYPE_FLG = W2PO | F58: N/A
A59: CMS_W1_ASSET_IDENTIFIER_VW | B59: METROLOGY_FIRMWARE_VERSION | C59: Metrology Firmware Version | D59: N/A | E59: ASSET_ID_TYPE_FLG = W2MF | F59: N/A
A60: CMS_W1_ASSET_IDENTIFIER_VW | B60: NIC_FIRMWARE_VERSION | C60: NIC Firmware Version | D60: N/A | E60: ASSET_ID_TYPE_FLG = W2NF | F60: N/A
A61: W1_ASSET_NODE | B61: ASSET_ID | C61: Asset | D61: N/A | F61: N/A | G61: Asset Node is Inner Joined to Asset Table on row #2. For the reports, we would need to filter the most effective Asset Node linked to the Asset
A62: W1_ASSET_NODE | B62: EFF_DTTM | C62: Create Date/Time | D62: N/A | F62: N/A
A63: W1_ASSET_NODE | B63: ASSET_DPOS_FLG | C63: Asset Disposition | D63: F1_EXT_LOOKUP_VAL_L | E63: W1-AssetDisposition | F63: Inner Join
A64: W1_ASSET_NODE | B64: NODE_ID | C64: Location/Organization | D64: W1_NODE | F64: Inner Join | G64: Joining to W1_NODE to display the Address Details on the report
A65: W1_ASSET_NODE | B65: ATTCH_TO_ASSET_ID | C65: Attached to Asset ID | D65: N/A | F65: N/A
A66: W1_ASSET_NODE | B66: VERSION | C66: Version | D66: N/A | F66: N/A
A67: W1_ASSET_NODE | B67: CURR_ASSET_ID | C67: Current Asset ID | D67: N/A | F67: N/A
A68: W1_ASSET_NODE | B68: CURR_NODE_ID | C68: Current Node ID | D68: N/A | F68: N/A
A69: W1_ASSET_NODE | B69: CURR_ATTCH_TO_ASSET_ID | C69: Current Attached to Asset ID | D69: N/A | F69: N/A
A70: W1_ASSET_NODE | B70: ACT_ID | C70: Activity | D70: N/A | F70: N/A
A71: W1_ASSET_NODE | B71: FAILURE_FLG | C71: Failure | D71: CI_LOOKUP_VAL_L | F71: Left Join
A72: W1_NODE | B72: NODE_ID | C72: Location/Organization | D72: N/A | F72: N/A | G72: Node is joined to W1_ASSET_NODE
A73: W1_NODE | B73: DESCR100 | C73: Description | D73: N/A | F73: N/A
A74: W1_NODE | B74: W1_DESCR100_UPR | C74: Description Upper | D74: N/A | F74: N/A
A75: W1_NODE | B75: NODE_TYPE_CD | C75: Location/Organization Type | D75: W1_NODE_TYPE_L | F75: Inner Join
A76: W1_NODE | B76: BUS_OBJ_CD | C76: Business Object | D76: F1_BUS_OBJ_L | F76: Inner Join
A77: W1_NODE | B77: NODE_DPOS_FLG | C77: Location/Organization Disposition | D77: CI_LOOKUP_VAL_L | E77: NODE_DPOS_FLG | F77: Inner Join
A78: W1_NODE | B78: W1_OPERATION_FLG | C78: Operation | D78: CI_LOOKUP_VAL_L | E78: W1_OPERATION_FLG | F78: Left Join
A79: W1_NODE | B79: PARENT_NODE_ID | C79: Parent Location/Organization | E79: Left Join | F79: Display the Parent Node Description
A80: W1_NODE | B80: CRITICALITY_FLG | C80: Criticality | D80: CI_LOOKUP_VAL_L | E80: CRITICALITY_FLG | F80: Left Join
A81: W1_NODE | B81: LOCATION_CLASS_FLG | C81: Location Class | D81: CI_LOOKUP_VAL_L | E81: LOCATION_CLASS_FLG | F81: Left Join
A82: W1_NODE | B82: ADDRESS1 | C82: Address | D82: N/A | F82: N/A
A83: W1_NODE | B83: W1_ADDRESS1_UPR | C83: Address Uppercase | D83: N/A | F83: N/A
A84: W1_NODE | B84: ADDRESS2 | C84: Address 2 | D84: N/A | F84: N/A
A85: W1_NODE | B85: ADDRESS3 | C85: Address 3 | D85: N/A | F85: N/A
A86: W1_NODE | B86: ADDRESS4 | C86: Address 4 | D86: N/A | F86: N/A
A87: W1_NODE | B87: W1_CROSS_STREET | C87: Cross Street | D87: N/A | F87: N/A
A88: W1_NODE | B88: CITY | C88: City | D88: N/A | F88: N/A
A89: W1_NODE | B89: W1_CITY_UPR | C89: City Uppercase | D89: N/A | F89: N/A
A90: W1_NODE | B90: W1_SUBURB | C90: Suburb | D90: N/A | F90: N/A
A91: W1_NODE | B91: COUNTY | C91: County | D91: N/A | F91: N/A
A92: W1_NODE | B92: STATE | C92: State | D92: CI_STATE_L | F92: Left Join
A93: W1_NODE | B93: POSTAL | C93: Postal | D93: N/A | F93: N/A
... A109: W1_NODE | B109: POSITION | C109: Position | D109: N/A | F109: N/A
A110: W1_NODE | B110: RCM_SYSTEM_FLG | C110: RCM System | D110: CI_LOOKUP_VAL_L | E110: RCM_SYSTEM_FLG | F110: Left Join
A111: W1_NODE | B111: RUN_TO_FAILURE_FLG | C111: Run to Failure | D111: CI_LOOKUP_VAL_L | E111: RUN_TO_FAILURE_FLG | F111: Left Join
A112: W1_NODE | B112: INV_COST_CENTER_CD | C112: Inventory Cost Center | D112: W1_COST_CENTER_L | F112: Left Join
A113: W1_NODE | B113: INV_ADJTMT_COST_CENTER_CD | C113: Inventory Adjustment Cost Center | D113: W1_COST_CENTER_L | F113: Left Join
A114: W1_NODE | B114: MARK_UP_COST_CENTER_CD | C114: Markup Cost Center | D114: W1_COST_CENTER_L | F114: Left Join
A115: W1_NODE | B115: STOCK_TRANSFER_COST_CENTER_CD | C115: Stock Transfer Cost Center | D115: W1_COST_CENTER_L | F115: Left Join
A116: W1_NODE | B116: INV_EXPENSE_CD | C116: Inventory Expense Code | D116: W1_EXPENSE_CD_L | F116: Left Join
A117: W1_NODE | B117: BUYER_CD | C117: Buyer | D117: W1_BUYER_L | F117: Left Join
A118: W1_NODE | B118: MARK_UP_EXPENSE_CD | C118: Markup Expense Code | D118: W1_EXPENSE_CD_L | F118: Left Join
A119: W1_NODE | B119: RR_APP_REQ_FLG | C119: Reorder Review Approval Required | D119: CI_LOOKUP_VAL_L | E119: RR_APP_REQ_FLG | F119: Left Join
A120: W1_NODE | B120: PUR_DOC_ACTION_FLG | C120: Purchasing Document Action | D120: CI_LOOKUP_VAL_L | E120: PUR_DOC_ACTION_FLG | F120: Left Join
A121: W1_NODE | B121: PLANNER_CD | C121: Planner | D121: W1_PLANNER_L | F121: Left Join
A122: W1_NODE | B122: BACK_LOG_GRP_FLG | C122: Backlog Group | D122: CI_LOOKUP_VAL_L | F122: Left Join
A123: W1_NODE | B123: MAINTMGR_CD | C123: Maintenance Manager | D123: W1_MAINTMGR_L | F123: Left Join
A124: W1_NODE | B124: TAX_COST_CENTER_CD | C124: Tax Cost Center | D124: W1_COST_CENTER_L | F124: Left Join
A125: W1_NODE | B125: INVOICE_WRITEOFF_COST_CTR_CD | C125: Invoice Write-Off Cost Center Code | D125: W1_COST_CENTER_L | F125: Left Join
A126: W1_NODE | B126: TAX_EXPENSE_CD | C126: Tax Expense Code | D126: W1_EXPENSE_CD_L | F126: Left Join
A127: W1_NODE | B127: INVOICE_WRITEOFF_EXPENSE_CD | C127: Invoice Write-Off Expense Code | D127: W1_EXPENSE_CD_L | F127: Left Join
A128: W1_NODE | B128: SERVICE_COND_FLG | C128: Service Condition | D128: F1_EXT_LOOKUP_VAL_L | E128: W1-ServiceCondition | F128: Left Join

Sheet W1_NODE
A1: Summary
A2: Table Name: W1_NODE
A3: Justification | B3: =Summary!O237 -> Node (Location) is the equiavalent for M-Side's SP Record. The only difference with Node record is that it stores the Out of Service Locations (e.g. Storeroom). This is helpful for the Clients as it allows them to fetch Ouf of Service Locations where new Assets can be stored into.
A5: Table Name | B5: Field Name | C5: Field Description | D5: Related Table | E5: Filter | F5: Join Type | G5: Designer Notes | H5: Reviewer Notes
A6: W1_NODE | B6: NODE_ID | C6: Location/Organization | D6: * W1_NODE_IDENTIFIER | F6: Left Join - W1_NODE_IDENTIFIER
A7: W1_NODE | B7: DESCR100 | C7: Description | D7: N/A | F7: N/A
A8: W1_NODE | B8: W1_DESCR100_UPR | C8: Description Upper | D8: N/A | F8: N/A
A9: W1_NODE | B9: NODE_TYPE_CD | C9: Location/Organization Type | D9: W1_NODE_TYPE_L | F9: Inner Join
A10: W1_NODE | B10: BUS_OBJ_CD | C10: Business Object | D10: F1_BUS_OBJ_L | F10: Inner Join
A11: W1_NODE | B11: NODE_DPOS_FLG | C11: Location/Organization Disposition | D11: CI_LOOKUP_VAL_L | F11: Inner Join
A12: W1_NODE | B12: W1_OPERATION_FLG | C12: Operation | D12: CI_LOOKUP_VAL_L | F12: Left Join
A13: W1_NODE | B13: PARENT_NODE_ID | C13: Parent Location/Organization | D13: W1_NODE | F13: Left Join | G13: Display the Parent Node Description
A14: W1_NODE | B14: CRITICALITY_FLG | C14: Criticality | D14: CI_LOOKUP_VAL_L | F14: Left Join
A15: W1_NODE | B15: LOCATION_CLASS_FLG | C15: Location Class | D15: CI_LOOKUP_VAL_L | F15: Left Join
A16: W1_NODE | B16: ADDRESS1 | C16: Address | D16: N/A | F16: N/A
A17: W1_NODE | B17: W1_ADDRESS1_UPR | C17: Address Uppercase | D17: N/A | F17: N/A
A18: W1_NODE | B18: ADDRESS2 | C18: Address 2 | D18: N/A | F18: N/A
A19: W1_NODE | B19: ADDRESS3 | C19: Address 3 | D19: N/A | F19: N/A
A20: W1_NODE | B20: ADDRESS4 | C20: Address 4 | D20: N/A | F20: N/A
A21: W1_NODE | B21: W1_CROSS_STREET | C21: Cross Street | D21: N/A | F21: N/A
A22: W1_NODE | B22: CITY | C22: City | D22: N/A | F22: N/A
A23: W1_NODE | B23: W1_CITY_UPR | C23: City Uppercase | D23: N/A | F23: N/A
A24: W1_NODE | B24: W1_SUBURB | C24: Suburb | D24: N/A | F24: N/A
A25: W1_NODE | B25: COUNTY | C25: County | D25: N/A | F25: N/A
... A73: W1_NODE | B73: BO_DATA_AREA: okToEnter | C73: Ok To Enter | D73: D1_SP | F73: No Mapping Needed
A74: W1_NODE_IDENTIFIER | B74: NODE_ID | C74: Location/Organization | D74: N/A | F74: N/A | G74: Node Identifier is Left Joined to Asset Table on row #2
A75: W1_NODE_IDENTIFIER | B75: NODE_ID_TYPE_FLG | C75: Location/Organization Identifier Type | E75: NODE_ID_TYPE_FLG=W1EI | F75: Left Join
A76: W1_NODE_IDENTIFIER | B76: W1_ID_VALUE | C76: Identifier Value | D76: N/A | F76: N/A

Sheet CI_SP
A1: Summary
A2: Table Name: CI_SP
A3: Justification
A5: Field Name | B5: Field Description | C5: Related Table | D5: Filter | E5: Join Type | F5: Designer Notes | G5: Reviewer Notes
A6: SP_ID | B6: Service Point ID | C6: N/A | E6: N/A
A7: SP_TYPE_CD | B7: SP Type | C7: * CI_SP_TYPE * CI_SP_TYPE_L | E7: Inner Join
A8: PREM_ID | B8: Premise ID | C8: * CI_PREM | E8: Inner Join
A9: SP_STATUS_FLG | B9: Service Point Status | C9: * CI_LOOKUP_VAL * CI_LOOKUP_VAL_L | D9: Field = SP_STATUS_FLG | E9: Left Outer
A10: INSTALL_DT | B10: Install Date | C10: N/A | E10: N/A
A11: ABOLISH_DT | B11: Out of Service Date | C11: N/A | E11: N/A
A12: SP_SRC_STATUS_FLG | B12: Service Point Source Status | C12: * CI_LOOKUP_VAL * CI_LOOKUP_VAL_L | D12: Field = SP_SRC_STATUS_FLG | E12: Left Outer
A13: DISCON_LOC_CD | B13: Disconnect Location | C13: * CI_DISCON_LOC * DISCON_LOC_L | E13: Left Outer
A14: MR_CYC_CD | B14: Service Cycle | C14: * CI_MR_CYC * CI_MR_CYC_L | E14: Left Outer
A15: MR_RTE_CD | B15: Service Route | C15: * CI_MR_RTE_L | E15: Left Outer
A16: MR_CYC_RTE_SEQ | B16: Service Cycle/Route Sequence | C16: N/A | E16: N/A
A17: MTR_LOC_CD | B17: Meter Location | C17: * CI_MTR_LOC * CI_MTR_LOC_L | E17: Left Outer
A18: MTR_LOC_DETAILS | B18: Location Details | C18: N/A | E18: N/A
A19: FAC_LVL_1_CD | B19: Facility Level 1 | C19: * CI_FAC_LVL_1 * CI_FAC_LVL_1_L | E19: Left Outer
A20: VERSION | B20: Version | C20: N/A | E20: N/A
A21: FAC_LVL_2_CD | B21: Facility Level 2 | C21: * CI_FAC_LVL_2 * CI_FAC_LVL_2_L | E21: Left Outer
A22: FAC_LVL_3_CD | B22: Facility Level 3 | C22: * CI_FAC_LVL_3 * CI_FAC_LVL_3_L | E22: Left Outer
A23: DESCRLONG | B23: Detailed Description | C23: N/A | E23: N/A
A24: OVRD_PREM_FLD_INFO_FLG | B24: Override Premise Field Information | C24: * CI_LOOKUP_VAL * CI_LOOKUP_VAL_L | D24: Field = OVRD_PREM_FLD_INFO_FLG | E24: Left Outer
A25: MR_INSTR_CD | B25: Meter Read Instruction | C25: N/A | E25: N/A
A26: MR_WARN_CD | B26: Meter Read Warning | C26: * CI_MR_WARN * CI_MR_WARN_L | E26: Left Outer
A27: KEY_SW | B27: Key | C27: N/A | E27: N/A
A28: KEY_ID | B28: Key ID | C28: N/A | E28: N/A
A29: OK_TO_ENTER_SW | B29: OK to Enter | C29: N/A | E29: N/A
A30: MR_INSTR_DETAILS | B30: Instruction Details | C30: N/A | E30: N/A
A31: SP_DATA_AREA | B31: SP Data Area | C31: N/A | E31: N/A

Sheet C1_USAGE
A1: Summary
A2: Table Name: C1_USAGE
A3: Justification
A4: Designer
A5: Field Name | B5: Field Description | C5: Related Table | D5: Filter | E5: Join Type | F5: Designer Notes | G5: Reviewer Notes
A6: USAGE_ID | B6: Usage ID | C6: N/A | E6: N/A
A7: SA_ID | B7: Service Agreement | C7: * CI_SA | E7: Inner Join
A8: SP_ID | B8: Service Point ID | C8: * CI_SP | E8: Left Outer
A9: BILL_CYC_CD | B9: Bill Cycle | C9: * CI_BILL_CYC_SCH * CI_BILL_CYC_SCH_L | E9: Left Outer
A10: WIN_START_DT | B10: Window Start Date | C10: * CI_BILL_CYC_SCH | E10: Left Outer
A11: EXT_REFERENCE_ID | B11: External Reference ID | C11: N/A | E11: N/A
A12: BUS_OBJ_CD | B12: Business Object | C12: * F1_BUS_OBJ_L | E12: Inner Join
A13: BO_STATUS_CD | B13: Status | C13: * F1_BUS_OBJ_STATUS_L | E13: Inner Join
A14: STATUS_UPD_DTTM | B14: Status Date/Time | C14: N/A | E14: N/A
A15: USG_DATA_AREA | B15: Consumption Data Area | C15: N/A | E15: N/A
A16: VERSION | B16: Version | C16: N/A | E16: N/A
A17: BSEG_ID | B17: Bill Segment ID | C17: * CI_BSEG | E17: Left Outer
... A24: SA_REL_ID | B24: SA Relationship ID | C24: * CI_SA_REL | E24: Left Outer
A25: MASTER_USAGE_ID | B25: Master Usage ID | C25: * C1_USAGE | E25: Left Outer | F25: Information would be retrieve if there's a master - sub SA that's billed. both records will be stored in the C1_USAGE table
A26: C1_BILL_COND_FLG | B26: Bill Condition | F26: TBD.Inner Join if we are going to use a View to get the USG_DATA_AREA values
A27: C1_IS_ESTIMATE_SW | B27: Estimate Switch
A28: C1_USAGE_TYPE_FLG | B28: Usage Request Type | F28: TBD.Inner Join if we are going to use a View to get the USG_DATA_AREA values

Sheet C1_PA_RQST
B1: Summary
B2: Table Name: C1_PA_RQST
B3: Data Area: C1-PARequest
B4: Justification | C4: =Summary!O23 -> This table contains information on the arrangement downpayment, arrangement amounts, number of installments, and installment amount.
A6: Table Name | B6: Field Name | C6: Field Description | D6: Related Table / XPAth | E6: Filter | F6: Join Type | G6: Designer Notes | H6: Reviewer Notes
A7: C1_PA_RQST | B7: PA_RQST_ID | C7: Payment Arrangement Request ID | D7: N/A | F7: N/A
A8: C1_PA_RQST | B8: BO_STATUS_REASON_CD | C8: Status Reason | D8: *F1_BUS_OBJ_STATUS_RSN *F1_BUS_OBJ_STATUS_RSN_L | E8: *F1_BUS_OBJ_STATUS_RSN.BO_STATUS_BO_CD = C1_PA_RQST.BUS_OBJ_ CD *F1_BUS_OBJ_STATUS_RSN.BO_STATUS_CD = C1_PA_RQST.BO_STATUS_CD | F8: Left Join
A9: C1_PA_RQST | B9: BO_STATUS_CD | C9: Status | D9: *F1_BUS_OBJ_STATUS *F1_BUS_OBJ_STATUS_L | E9: *F1_BUS_OBJ_STATUS.BUS_OBJ_CD = C1_PA_RQST.BUS_OBJ_ CD *F1_BUS_OBJ_STATUS.BUS_OBJ_CD = C1_PA_RQST.BO_STATUS_CD | F9: Inner Join
A10: C1_PA_RQST | B10: PA_RQST_NBR_INSTALLMENT | C10: Number of Installments | D10: N/A | F10: N/A
A11: C1_PA_RQST | B11: STATUS_UPD_DTTM | C11: Status Date/Time | D11: N/A | F11: N/A
A12: C1_PA_RQST | B12: ILM_DT | C12: ILM Date | D12: N/A | F12: N/A
A13: C1_PA_RQST | B13: PA_RQST_RSLT_FLG | C13: Request Result | D13: CI_LOOKUP_VAL_L | E13: Field Name = 'PA_RQST_RSLT_FLG' | F13: Inner Join
A14: C1_PA_RQST | B14: ILM_ARCH_SW | C14: ILM Archive Switch | D14: N/A | F14: N/A
A15: C1_PA_RQST | B15: PA_RQST_REASON | C15: Request Reason | D15: F1_EXT_LOOKUP_VAL_L | E15: BUS_OBJ_CD = 'C1-PARequestReasonLookup' | F15: Left Join
A16: C1_PA_RQST | B16: VERSION | C16: Version | D16: N/A | F16: N/A
A17: C1_PA_RQST | B17: PA_RQST_DOWN_PAY_DUE_DT | C17: Down Payment Due Date | D17: N/A | F17: N/A
A18: C1_PA_RQST | B18: PA_RQST_DOWN_PAY_AMT | C18: Down Payment Amount | D18: N/A | F18: N/A
A19: C1_PA_RQST | B19: BUS_OBJ_CD | C19: Business Object | D19: F1_BUS_OBJ_L | F19: Inner Join
A20: C1_PA_RQST | B20: CRE_DTTM | C20: Create Date/Time | D20: N/A | F20: N/A
A21: C1_PA_RQST | B21: PA_RQST_TOT_AMT | C21: Total PA Amount | D21: N/A | F21: N/A
A22: C1_PA_RQST | B22: ACCT_ID | C22: Account ID | D22: *CI_ACCT_PER *CI_PER_PRIM_WV ***Display the Customer Name | E22: MAIN_CUST_SW = 'Y' | F22: Inner Join
A23: C1_PA_RQST | B23: PA_RQST_DT | C23: Request Date | D23: N/A | F23: N/A
A24: C1_PA_RQST | B24: PA_RQST_INSTALLMENT_AMT | C24: Installment Amount | D24: N/A | F24: N/A
A25: C1_PA_RQST | B25: PA_RQST_INSTALLMENT_AMT | C25: Installment Amount | D25: N/A | F25: N/A
A26: C1_PA_RQST | B26: PA_RQST_TYPE_CD | C26: Payment Arrangement Request Type | D26: C1_PA_RQST_TYPE_L | F26: Inner Join
A27: CMS_C1_PA_RQST_BODA_VW | B27: BO_XML_DATA_AREA: XML Element - paymentAmount Field - PA_RQST_DOWN_PAY_PAYMENT | C27: Actual Down Payment Amount | D27: /paymentAmount | F27: N/A | G27: Mapping needed
A28: CMS_C1_PA_RQST_BODA_VW | B28: BO_XML_DATA_AREA: XML Element - processFlowStatus Field - BO_STATUS_CD | C28: Process Flow Status *** Manual Label | D28: Related Table - F1_BUS_OBJ_STATUS_L Xpath - /processFlowStatus | F28: N/A | G28: No mapping needed. This is suppressed from the Schema, so this information will not be displayed in C2M
A29: CMS_C1_PA_RQST_BODA_VW | B29: BO_XML_DATA_AREA: XML Element - approvalToDoEntryId Field - TD_ENTRY_ID | C29: Approval To Do Entry ID *** Manual Label | D29: Xpath - /approvalToDoEntryId | F29: N/A | G29: No mapping needed. This is suppressed from the Schema, so this information will not be displayed in C2M
A30: CMS_C1_PA_RQST_BODA_VW | B30: BO_XML_DATA_AREA: XML Element - downpaymentStartDate Field - PA_RQST_DOWN_PAY_START_DATE | C30: Down Payment Start Date | D30: Xpath - /downpaymentStartDate | F30: N/A | G30: No mapping needed. This is suppressed from the Schema, so this information will not be displayed in C2M
A31: CMS_C1_PA_RQST_BODA_VW | B31: BO_XML_DATA_AREA: XML Element - downpaymentEndDate Field - PA_RQST_DOWN_PAY_END_DATE | C31: Down Payment Start Date | D31: Xpath - /downpaymentEndDate | F31: N/A | G31: No mapping needed. This is suppressed from the Schema, so this information will not be displayed in C2M
A32: CMS_C1_PA_RQST_BODA_VW | B32: BO_XML_DATA_AREA: XML Element - isCancelledFromProcessFlow Field - C1_CANCEL_FROM_PF_SW | C32: Cancel from Process Flow | D32: Xpath - /isCancelledFromProcessFlow | F32: N/A | G32: No mapping needed. This is suppressed from the Schema, so this information will not be displayed in C2M
A33: CMS_C1_PA_RQST_BODA_VW | B33: BO_XML_DATA_AREA: XML Element - remainingAmount Field - PA_REMAINING_AMOUNT | C33: Recalculated Remaining Amount *** Manual Label | D33: Xpath - recalculated/remainingAmount | F33: N/A | G33: Mapping needed
A34: CMS_C1_PA_RQST_BODA_VW | B34: BO_XML_DATA_AREA: XML Element - numberOfInstallments Field - PA_RQST_NBR_INSTALLMENT | C34: Recalculated Number of Installments *** Manual Label | D34: Xpath - recalculated/numberOfInstallments | F34: N/A | G34: Mapping needed
A35: CMS_C1_PA_RQST_BODA_VW | B35: BO_XML_DATA_AREA: XML Element - installmentAmount Field - PA_RQST_INSTALLMENT_AMT | C35: Recalculated Installment Amount *** Manual Label | D35: Xpath - recalculated/installmentAmount | F35: N/A | G35: Mapping needed
A36: CMS_C1_PA_RQST_BODA_VW | B36: BO_XML_DATA_AREA: XML Element - termsSummary Field - PA_PAYMENT_TERMS | C36: Recalculated Payment Terms *** Manual Label | D36: Xpath - recalculated/termsSummary | F36: N/A | G36: Mapping needed
A37: C1_PA_RQST_REL_OBJ RELOBJ1 | B37: PA_RQST_ID | C37: Payment Arrangement Request ID | D37: C1_PA_RQST | F37: Left Join | G37: Joined to link to the Payment Arrangement SA that will be created
A38: C1_PA_RQST_REL_OBJ RELOBJ1 | B38: PA_RQST_REL_OBJ_TYPE_FLG | C38: PA Request Related Object Type | D38: CI_LOOKUP_VAL_L | E38: Field Name = 'PA_RQST_REL_OBJ_TYPE_FLG' Field Value = 'C1PA' | F38: Left Join
A39: C1_PA_RQST_REL_OBJ RELOBJ1 | B39: SEQ_NUM | C39: Sequence | D39: N/A | F39: N/A
A40: C1_PA_RQST_REL_OBJ RELOBJ1 | B40: MAINT_OBJ_CD | C40: Maintenance Object | D40: CI_MD_MO_L | E40: MAINT_OBJ_CD = 'SA' | F40: Left Join
A41: C1_PA_RQST_REL_OBJ RELOBJ1 | B41: PK_VALUE1 | C41: Primary Key 1 | D41: * CI_SA * CI_SA_TYPE_L ***Display the SA Status and SA Type Description | F41: Left Join
A42: C1_PA_RQST_REL_OBJ RELOBJ1 | B42: PK_VALUE2 | C42: Primary Key 2 | D42: N/A | F42: N/A
A43: C1_PA_RQST_REL_OBJ RELOBJ1 | B43: PK_VALUE3 | C43: Primary Key 3 | D43: N/A | F43: N/A
A44: C1_PA_RQST_REL_OBJ RELOBJ1 | B44: PK_VALUE4 | C44: Primary Key 4 | D44: N/A | F44: N/A
A45: C1_PA_RQST_REL_OBJ RELOBJ1 | B45: PK_VALUE5 | C45: Primary Key 5 | D45: N/A | F45: N/A
A46: C1_PA_RQST_REL_OBJ RELOBJ1 | B46: VERSION | C46: Version | D46: N/A | F46: N/A
A47: C1_PA_RQST_REL_OBJ RELOBJ2 | B47: PA_RQST_ID | C47: Payment Arrangement Request ID | D47: C1_PA_RQST | F47: Left Join | G47: Joined to link to the Covered SAs with balance that will be transferred to the Payment Arrangement SA
A48: C1_PA_RQST_REL_OBJ RELOBJ2 | B48: PA_RQST_REL_OBJ_TYPE_FLG | C48: PA Request Related Object Type | D48: CI_LOOKUP_VAL_L | E48: Field Name = 'PA_RQST_REL_OBJ_TYPE_FLG' Field Value = 'C1SA' | F48: Left Join
A49: C1_PA_RQST_REL_OBJ RELOBJ2 | B49: SEQ_NUM | C49: Sequence | D49: N/A | F49: N/A
A50: C1_PA_RQST_REL_OBJ RELOBJ2 | B50: MAINT_OBJ_CD | C50: Maintenance Object | D50: CI_MD_MO_L | E50: MAINT_OBJ_CD = 'SA' | F50: Left Join
A51: C1_PA_RQST_REL_OBJ RELOBJ2 | B51: PK_VALUE1 | C51: Primary Key 1 | D51: * CI_SA * CI_SA_TYPE_L ***Display the SA Status and SA Type Description | F51: Left Join
A52: C1_PA_RQST_REL_OBJ RELOBJ2 | B52: PK_VALUE2 | C52: Primary Key 2 | D52: N/A | F52: N/A
A53: C1_PA_RQST_REL_OBJ RELOBJ2 | B53: PK_VALUE3 | C53: Primary Key 3 | D53: N/A | F53: N/A
A54: C1_PA_RQST_REL_OBJ RELOBJ2 | B54: PK_VALUE4 | C54: Primary Key 4 | D54: N/A | F54: N/A
A55: C1_PA_RQST_REL_OBJ RELOBJ2 | B55: PK_VALUE5 | C55: Primary Key 5 | D55: N/A | F55: N/A
A56: C1_PA_RQST_REL_OBJ RELOBJ2 | B56: VERSION | C56: Version | D56: N/A | F56: N/A
A57: CMS_C1_PA_RQST_BODA_VW | B57: BO_XML_DATA_AREA: XML Element - currentBalance Field - PA_RQST_CUR_BAL | C57: SA Current Balance *** Manual Label | D57: Xpath - paSAs/paSa/currentBalance ***paSA is a List Element | E57: Join paSAs/paSa/saId to RELOBJ2.PK_VALUE1 | F57: Left Join | G57: Mapping needed
A58: CMS_C1_PA_RQST_BODA_VW | B58: BO_XML_DATA_AREA: XML Element - paSa/amount Field - PA_RQST_SA_AMT | C58: SA Included Amount *** Manual Label | D58: Xpath - paSAs/paSa/amount ***paSA is a List Element | G58: Mapping needed
A59: CMS_C1_PA_RQST_BODA_VW | B59: BO_XML_DATA_AREA: XML Element -paSa/recalculated/amount Field - PA_RQST_SA_AMT_RECALC | C59: SA Recalculated Amount *** Manual Label | D59: Xpath - paSAs/paSa/recalculated/amount ***paSA is a List Element | G59: Mapping needed
A60: C1_PA_RQST_REL_OBJ RELOBJ2 | B60: BO_XML_DATA_AREA: XML Element - saArrears | C60: N/A - This is a List Node for the SA Arrears info storing the SA aging balance bucket | D60: Xpath - paSAs/paSa/saArrears/* | G60: No mapping needed. This is suppressed from the Schema, so this information will not be displayed in C2M
A61: C1_PA_RQST_ELIG_RSLT | B61: BO_XML_DATA_AREA: XML Element - paEligibility | C61: N/A - This is a List Node for the Eligibility Criteria Information | D61: Xpath - /paEligibility | G61: No mapping needed. This is suppressed from the Schema, so this information will not be displayed in C2M

Sheet C1_REPRESENTATIVE (with ML)
B1: Summary
B2: Table Name: C1_REPRESENTATIVE
B3: Data Area: C1-ThirdPartyRepresentative
B4: Justification | C4: =Summary!O291 -> This will be used for the creation of Crew Based domain to measure Field Worker Performance (How many FAs can a crew complete within the Day)
A6: Table Name | B6: Field Name | C6: Field Description | D6: Related Table / XPAth | E6: Filter | F6: Join Type | G6: Designer Notes | H6: Reviewer Notes
A7: C1_REPRESENTATIVE | B7: C1_REPRESENTATIVE_CD | C7: Crew *** Manual Label | D7: * C1_REPRESENTATIVE_L * D1_ACTIVITY_CHAR | E7: * D1_ACTIVITY_CHAR.CHAR_TYPE_CD = 'CMFAREP' * D1_ACTIVITY_CHAR.SRCH_CHAR_VAL = 'CMFAREP' = C1_REPRESENTATIVE_CD | F7: * C1_REPRESENTATIVE_L - Inner Join * D1_ACTIVITY_CHAR - Left Join
A8: C1_REPRESENTATIVE | B8: BUS_OBJ_CD | C8: Business Object | D8: F1_BUS_OBJ_L | E8: BUS_OBJ_CD = 'C1-ThirdPartyRepresentative' | F8: Inner Join
A9: C1_REPRESENTATIVE | B9: BO_STATUS_CD | C9: Status | D9: F1_BUS_OBJ_STATUS_L | F9: Inner Join
A10: C1_REPRESENTATIVE | B10: BO_STATUS_REASON_CD | C10: Status Reason | D10: F1_BUS_OBJ_STATUS_RSN_L | F10: Left Join
A11: C1_REPRESENTATIVE | B11: C1_REPRESENTATIVE_TYPE_FLG | C11: Sales Representative Type | D11: CI_LOOKUP_VAL_L | E11: Field Name = 'C1_REPRESENTATIVE_TYPE_FLG' | F11: Inner Join | G11: Can be excluded, Representative Type will be always Third Party. This is more on internal and the Field Description might confuse Customer
A12: C1_REPRESENTATIVE | B12: USER_ID | C12: User | D12: SC_USER | F12: Left Join
A13: C1_REPRESENTATIVE | B13: CRE_DTTM | C13: Create Date/Time | D13: N/A | F13: N/A
A14: C1_REPRESENTATIVE | B14: STATUS_UPD_DTTM | C14: Status Date/Time | D14: N/A | F14: N/A
A15: C1_REPRESENTATIVE | B15: VERSION | C15: Version | D15: N/A | F15: N/A
A16: C1_REPRESENTATIVE | B16: PER_ID | C16: Person ID | D16: N/A | F16: N/A | G16: Will not be joined to Person Table. Crew Name will be fetched from C1_REPRESENTATIVE_L Table
A17: C1_REPRESENTATIVE | B17: NT_XID_CD | C17: External System | D17: CI_NT_XID_L | F17: Inner Join
A18: CMS_C1_REPRESENTATIVE_BODA_VW | B18: C1_PA_RQST.BO_XML_DATA_AREA: XML Element - serviceArea Field - CM_ML_CREW_SVC_AREA_LBL | C18: Service Area | D18: Xpath - cmMobileLiteDetails/serviceAreas/serviceAreaList/serviceArea ***serviceAreaList is a List Element | F18: Left Join *** This will be introduced on 25.1 Release | G18: Mapping needed
A19: CMS_C1_REPRESENTATIVE_BODA_VW | B19: C1_PA_RQST.BO_XML_DATA_AREA: XML Element - capability Field - CM_ML_WORKER_CAPABILITY | C19: Worker Capability | D19: Xpath - cmMobileLiteDetails/workerCapability/capabilities/capability ***capabilities is a List Element | F19: Left Join *** This will be introduced on 25.1 Release | G19: Mapping needed
A20: D1_ACTIVITY_CHAR (linkage only) | B20: D1_ACTIVITY | C20: Activity ID | D20: D1_ACTIVITY | F20: Inner Join | G20: Activity Char is Left Joined to Representative Table
A21: D1_ACTIVITY_CHAR (linkage only) | B21: CHAR_TYPE_CD | C21: Characteristic Type | E21: CMFAREP | F21: Inner Join
A22: D1_ACTIVITY_CHAR (linkage only) | B22: SEQ_NUM | C22: Sequence | D22: N/A | F22: N/A
A23: D1_ACTIVITY_CHAR (linkage only) | B23: CHAR_VAL | C23: Characteristic Value | D23: N/A | F23: Inner Join
A24: D1_ACTIVITY_CHAR (linkage only) | B24: ADHOC_CHAR_VAL | C24: Adhoc Characteristic Value | D24: N/A | F24: N/A
A25: D1_ACTIVITY_CHAR (linkage only) | B25: CHAR_VAL_FK1 | C25: Characteristic Value FK 1 | D25: N/A | F25: N/A
A26: D1_ACTIVITY_CHAR (linkage only) | B26: CHAR_VAL_FK2 | C26: Characteristic Value FK 2 | D26: N/A | F26: N/A
A27: D1_ACTIVITY_CHAR (linkage only) | B27: CHAR_VAL_FK3 | C27: Characteristic Value FK 3 | D27: N/A | F27: N/A
A28: D1_ACTIVITY_CHAR (linkage only) | B28: CHAR_VAL_FK4 | C28: Characteristic Value FK 4 | D28: N/A | F28: N/A
A29: D1_ACTIVITY_CHAR (linkage only) | B29: CHAR_VAL_FK5 | C29: Characteristic Value FK 5 | D29: N/A | F29: N/A
A30: D1_ACTIVITY_CHAR (linkage only) | B30: SRCH_CHAR_VAL | C30: Search Characteristic Value | D30: C1_REPRESENTATIVE | E30: C1_Representative_Cd | F30: N/A
A31: D1_ACTIVITY_CHAR (linkage only) | B31: VERSION | C31: Version | D31: N/A | F31: N/A
A32: D1_ACTIVITY | B32: ACTIVITY_TYPE_CD | C32: Activity Type | D32: D1_ACTIVITY_TYPE_L | E32: ACTIVITY_TYPE_CAT_FLG = 'D1FA' | F32: Left Join | G32: We only need the main information of the FA since the purpose of this domain is to measure Field Worker Performance (How many FAs can a crew complete within the Day)
A33: D1_ACTIVITY | B33: BO_DATA_AREA | C33: Business Object Data Area | D33: N/A | F33: N/A
A34: D1_ACTIVITY | B34: BO_STATUS_CD | C34: Status | D34: F1_BUS_OBJ_STATUS_L | F34: Inner Join
A35: D1_ACTIVITY | B35: BO_STATUS_REASON_CD | C35: Status Reason | D35: F1_BUS_OBJ_STATUS_RSN_L | F35: Left Join
A36: D1_ACTIVITY | B36: BUS_OBJ_CD | C36: Business Object | D36: F1_BUS_OBJ_L | F36: Inner Join
A37: D1_ACTIVITY | B37: CANCEL_REASON | C37: Cancel Reason | D37: F1_EXT_LOOKUP_VAL_L | E37: BUS_OBJ_CD = 'D1-CancelReasonLookup' | F37: Left Outer
A38: D1_ACTIVITY | B38: CRE_DTTM | C38: Create Date/Time | D38: N/A | F38: N/A
A39: D1_ACTIVITY | B39: D1_ACTIVITY_ID | C39: Activity ID | D39: N/A | F39: N/A
A40: D1_ACTIVITY | B40: EFF_DTTM | C40: Effective Date/Time | D40: N/A | F40: N/A
A41: D1_ACTIVITY | B41: END_DTTM | C41: End Date/Time | D41: N/A | F41: N/A
A42: D1_ACTIVITY | B42: FIELD_TASK_TYPE | C42: Field Task Type | D42: F1_EXT_LOOKUP_VAL_L | E42: BUS_OBJ_CD = 'D1-FieldTaskTypeLookup' | F42: Left Outer
